Workbook

Sheet Лист27
A1: ФИО | B1: e-mail | C1: e-mail МУДЛ | D1: hfccskrf
A2: Гапоненко Сергей Алексеевич | B2: s.a.gaponenko@mtuci.ru | C2: ggserongg@gmail.com | D2: {=_xlfn.XLOOKUP(C2,#REF!,#REF!,0)} -> #REF!
A3: Заликов Руслан Артурович | B3: r.a.zalikov@edu.mtuci.ru | C3: rus.zalikov@bk.ru | D3: {=_xlfn.XLOOKUP(C3,#REF!,#REF!,0)} -> #REF!
A4: Иевлев Кирилл Олегович | B4: k.o.ievlev@mtuci.ru | C4: ievlev.k.o@yandex.ru | D4: {=_xlfn.XLOOKUP(C4,#REF!,#REF!,0)} -> #REF!
A5: Кулагин Владимир Петрович | B5: v.p.kulagin@mtuci.ru | C5: v.p.kulagin@mtuci.ru | D5: {=_xlfn.XLOOKUP(C5,#REF!,#REF!,0)} -> #REF!
A6: Мкртчян Грач Маратович | B6: g.m.mkrtchyan@mtuci.ru | C6: g.m.mkrtchyan@mtuci.ru | D6: {=_xlfn.XLOOKUP(C6,#REF!,#REF!,0)} -> #REF!
A7: Мокин Александр Игоревич | B7: a.i.mokin@mtuci.ru | C7: alejmokin@yandex.ru | D7: {=_xlfn.XLOOKUP(C7,#REF!,#REF!,0)} -> #REF!
A8: Мосева Алеся Сергеевна | B8: a.s.moseva@mtuci.ru | C8: mosevaa@yandex.ru | D8: {=_xlfn.XLOOKUP(C8,#REF!,#REF!,0)} -> #REF!
A9: Мосева Марина Сергеевна | B9: m.s.moseva@mtuci.ru | C9: m.s.moseva@mtuci.ru | D9: {=_xlfn.XLOOKUP(C9,#REF!,#REF!,0)} -> #REF!
A10: Павликов Артем Евгеньевич | B10: a.e.pavlikov@mtuci.ru | C10: a.e.pavlikov@mtuci.ru | D10: {=_xlfn.XLOOKUP(C10,#REF!,#REF!,0)} -> #REF!
A11: Петросян Вера Рафаэловна | B11: v.r.petrosyan@mtuci.ru | C11: v.r.petrosyan@mtuci.ru | D11: {=_xlfn.XLOOKUP(C11,#REF!,#REF!,0)} -> #REF!
A12: Полянцева Ксения Андреевна | B12: k.a.poliantseva@mtuci.ru | C12: k.a.poliantseva@mtuci.ru | D12: {=_xlfn.XLOOKUP(C12,#REF!,#REF!,0)} -> #REF!
A13: Потапченко Тимур Дмитриевич | B13: t.d.potapchenko@mtuci.ru | C13: t.d.potapchenko@mtuci.ru | D13: {=_xlfn.XLOOKUP(C13,#REF!,#REF!,0)} -> #REF!
... A27: Круглов Георгий Николаевич | B27: ronimizy@itmo.ru | C27: ronimizy@niuitmo.ru | D27: {=_xlfn.XLOOKUP(C27,#REF!,#REF!,0)} -> #REF!
A28: Кугаевских Александр Владимирович | B28: avkugaevskikh@itmo.ru | D28: {=_xlfn.XLOOKUP(C28,#REF!,#REF!,0)} -> #REF!
A29: Лимар Иван Александрович | B29: ivan.limar@itmo.ru | C29: ivan.limar@itmo.ru | D29: {=_xlfn.XLOOKUP(C29,#REF!,#REF!,0)} -> #REF!
A30: Ким Станислав Евгеньевич | B30: codeilece@itmo.ru | C30: codeilece@gmail.com | D30: {=_xlfn.XLOOKUP(C30,#REF!,#REF!,0)} -> #REF!
A31: Маркина Татьяна Анатольевна | B31: markina_t@itmo.ru | C31: markina_t@itmo.ru | D31: {=_xlfn.XLOOKUP(C31,#REF!,#REF!,0)} -> #REF!
A32: Москаленко Мария Александровна | B32: mamoskalenko@itmo.ru | C32: moskalenko.mary@gmail.com | D32: {=_xlfn.XLOOKUP(C32,#REF!,#REF!,0)} -> #REF!
A33: Попков Роман Андреевич | B33: rpopkov@itmo.ru | C33: rpopkov@itmo.ru | D33: {=_xlfn.XLOOKUP(C33,#REF!,#REF!,0)} -> #REF!
A34: Правдин Константин Владимирович | B34: kvpravdin@itmo.ru | C34: construeman@gmail.com | D34: {=_xlfn.XLOOKUP(C34,#REF!,#REF!,0)} -> #REF!
A35: Пушкарев Даниил Александрович | B35: dpushkarev@itmo.ru | C35: pushkarevd.89@gmail.com | D35: {=_xlfn.XLOOKUP(C35,#REF!,#REF!,0)} -> #REF!
A36: Свинцов Михаил Викторович | B36: mvsvintsov@itmo.ru | C36: misha.svintsow@gmail.com | D36: {=_xlfn.XLOOKUP(C36,#REF!,#REF!,0)} -> #REF!
A37: Табиева Арина Вадимовна | B37: tabieva.arina@itmo.ru | C37: tabieva.arina@itmo.ru | D37: {=_xlfn.XLOOKUP(C37,#REF!,#REF!,0)} -> #REF!
A38: Трифанов Александр Игоревич | B38: alextrifanov@itmo.ru | C38: alextrifanov@gmail.com | D38: {=_xlfn.XLOOKUP(C38,#REF!,#REF!,0)} -> #REF!
A39: Агарева Ольга Юрьевна | B39: OYAgareva@mephi.ru | C39: oyagareva@mephi.ru | D39: {=_xlfn.XLOOKUP(C39,#REF!,#REF!,0)} -> #REF!
A40: Григорьев Андрей Александрович | B40: AAGrigorev1@mephi.ru | C40: grig.and.al@yandex.ru | D40: {=_xlfn.XLOOKUP(C40,#REF!,#REF!,0)} -> #REF!
... A45: Киреев Василий Сергеевич | B45: VSKireev@mephi.ru | C45: v.kireev1982@gmail.com | D45: {=_xlfn.XLOOKUP(C45,#REF!,#REF!,0)} -> #REF!
A46: Кирова Валерия Орлановна | B46: VOKirova@mephi.ru | D46: {=_xlfn.XLOOKUP(C46,#REF!,#REF!,0)} -> #REF!
A47: Коваленко Александр Евгеньевич | B47: sasha@kovalenko.net.ru | C47: sasha@kovalenko.net.ru | D47: {=_xlfn.XLOOKUP(C47,#REF!,#REF!,0)} -> #REF!
A48: Овчинникова Анастасия Олеговна | B48: AOOvchinnikova@mephi.ru | C48: aoantonova@mail.ru | D48: {=_xlfn.XLOOKUP(C48,#REF!,#REF!,0)} -> #REF!
A49: Рословцев Владимир Владимирович | B49: VVRoslovtsev@mephi.ru | C49: vvroslovtsev@mephi.ru | D49: {=_xlfn.XLOOKUP(C49,#REF!,#REF!,0)} -> #REF!
A50: Смирнов Дмитрий Сергеевич | B50: DSSmirnov@mephi.ru | C50: dvonrims@yandex.ru | D50: {=_xlfn.XLOOKUP(C50,#REF!,#REF!,0)} -> #REF!
A51: Сорока Артем Александрович | B51: AASoroka@mephi.ru | C51: 40aaa@mail.ru | D51: {=_xlfn.XLOOKUP(C51,#REF!,#REF!,0)} -> #REF!
A52: Трофимов Александр Геннадьевич | B52: AGTrofimov@mephi.ru | C52: atrofimov@list.ru | D52: {=_xlfn.XLOOKUP(C52,#REF!,#REF!,0)} -> #REF!
A53: Шильников Кирилл Евгеньевич | B53: KEShilnikov@mephi.ru | C53: shilnikov.k@yandex.ru | D53: {=_xlfn.XLOOKUP(C53,#REF!,#REF!,0)} -> #REF!
A54: Абрамович Александра Юрьевна | B54: ayabramovich@sevsu.ru | C54: ayabramovich@mail.ru | D54: {=_xlfn.XLOOKUP(C54,#REF!,#REF!,0)} -> #REF!
A55: Амосова Светлана Геннадьевна | B55: sgamosova@sevsu.ru | C55: amosovasg@yandex.ru | D55: {=_xlfn.XLOOKUP(C55,#REF!,#REF!,0)} -> #REF!
A56: Безуглая Анна Евгеньевна | B56: aebezuglaya@sevsu.ru | C56: aebezuglaya@sevsu.ru | D56: {=_xlfn.XLOOKUP(C56,#REF!,#REF!,0)} -> #REF!
A57: Бондарев Владимир Николаевич | B57: bondarev@sevsu.ru | C57: bondarev@sevsu.ru | D57: {=_xlfn.XLOOKUP(C57,#REF!,#REF!,0)} -> #REF!
A58: Брюховецкий Алексей Алексеевич | B58: bryukhovetskiy@sevsu.ru | C58: a.alexir@mail.ru | D58: {=_xlfn.XLOOKUP(C58,#REF!,#REF!,0)} -> #REF!
... A332: Штейнберг Борис Яковлевич | B332: byshtyaynberg@sfedu.ru | C332: boris.j.steinberg@gmail.com | D332: {=_xlfn.XLOOKUP(C332,#REF!,#REF!,0)} -> #REF!

Sheet Отказы и замены
A1: a | B1: Наименование направляющей организации | C1: SHORT_NAME | D1: CITY | E1: ФИО | F1: Ф | G1: И | H1: О | I1: ИФ | J1: Должность | K1: Телефон | L1: e-mail | M1: e-mail МУДЛ | N1: Чат | O1: Мудл | P1: Битрикс | Q1: В оф. пис. от 22.06 | R1: Рассылка 22-23 июня | S1: Рассылка про мудл и мах 30.06
A2: =ROW()-1 -> 1 | B2: Федеральное государственное автономное образовательное учреждение высшего образования "Российский университет дружбы народов имени Патриса Лумумбы" | C2: РУДН | D2: Москва | E2: Красиков Виталий Александрович | F2: Красиков | G2: Виталий | H2: Александрович | I2: =G2&" "&F2 -> Виталий Красиков | J2: Доцент кафедры прикладного искусственного интеллекта | K2: 89504211787 | L2: vitkras@inbox.ru | M2: {=_xlfn.XLOOKUP(I2,#REF!,#REF!,"")} -> #REF! | N2: FALSE | O2: =IF(M2="",FALSE,TRUE) -> #REF! | P2: TRUE | Q2: TRUE | R2: TRUE | S2: TRUE | T2: Согласовано с АЦ
A3: 2 | B3: Ордена Трудового Красного Знамени Федеральное государственное бюджетное образовательное учреждение высшего образования "Московский технический университет связи и информатики" | C3: МТУСИ | D3: Санкт-Петербург | E3: Рогов Олег Юрьевич | F3: Рогов | G3: Олег | H3: Юрьевич | I3: =G3&" "&F3 -> Олег Рогов | J3: доцент | K3: =79268976297 -> 79268976297 | L3: o.yu.rogov@mtuci.ru | N3: FALSE | O3: =IF(M3="",FALSE,TRUE) -> FALSE | P3: FALSE | Q3: TRUE | R3: TRUE | S3: FALSE | T3: Согласовано с АЦ
A4: =ROW()-1 -> 3 | B4: Федеральное государственное автономное образовательное учреждение высшего образования "Национальный исследовательский университет ИТМО" | C4: ИТМО | D4: Санкт-Петербург | E4: Лукина Марина Владимировна | F4: Лукина | G4: Марина | H4: Владимировна | I4: =G4&" "&F4 -> Марина Лукина | J4: Преподаватель | K4: 8-921-349-64-04 | L4: mvlukina@itmo.ru | M4: {=_xlfn.XLOOKUP(I4,#REF!,#REF!,"")} -> #REF! | N4: FALSE | O4: =IF(M4="",FALSE,TRUE) -> #REF! | P4: FALSE | Q4: TRUE | R4: TRUE | S4: FALSE | T4: Вместо неё - Ким

Sheet Журнал_conflict1319477655

Sheet Moodle_данные
A1: Синхронизировано | B1: Course ID | C1: Moodle user ID | D1: Moodle ID number | E1: ФИО | F1: Почта | G1: Grade item ID | H1: Элемент оценивания | I1: Тип элемента | J1: Модуль | K1: Минимум | L1: Максимум | M1: Балл | N1: Отображение Moodle | O1: Дата отправки | P1: Дата оценивания
A2: 46230.016 | B2: 12 | C2: 638 | E2: Айсу Бодур | F2: bodur_a@rgau-msha.ru | G2: 181 | H2: Итоговая аттестация | I2: manual | N2: -
A3: 46230.016 | B3: 12 | C3: 638 | E3: Айсу Бодур | F3: bodur_a@rgau-msha.ru | G3: 182 | H3: Кроссвалидация | I3: manual | N3: -
A4: 46230.016 | B4: 12 | C4: 638 | E4: Айсу Бодур | F4: bodur_a@rgau-msha.ru | G4: 174 | H4: Посещение вебинаров | I4: mod | J4: attendance | M4: 100 | N4: 100 | P4: 46209.707
A5: 46230.016 | B5: 12 | C5: 638 | E5: Айсу Бодур | F5: bodur_a@rgau-msha.ru | G5: 180 | H5: Промежуточная аттестация | I5: manual | N5: -
A6: 46230.016 | B6: 12 | C6: 638 | E6: Айсу Бодур | F6: bodur_a@rgau-msha.ru | G6: 175 | H6: Тестирование по модулю 1 | I6: mod | J6: quiz | M6: 75 | N6: 75 | O6: 46216.528 | P6: 46216.528
A7: 46230.016 | B7: 12 | C7: 638 | E7: Айсу Бодур | F7: bodur_a@rgau-msha.ru | G7: 177 | H7: Тестирование по модулю 4 | I7: mod | J7: quiz | N7: -
A8: 46230.016 | B8: 12 | C8: 638 | E8: Айсу Бодур | F8: bodur_a@rgau-msha.ru | G8: 176 | H8: Тестирование по модулям 2 и 3 | I8: mod | J8: quiz | M8: 90 | N8: 90 | O8: 46228.694 | P8: 46228.694
A9: 46230.016 | B9: 12 | C9: 638 | E9: Айсу Бодур | F9: bodur_a@rgau-msha.ru | G9: 168 | H9: Элемент 168 | I9: course | M9: 100 | N9: 100 | P9: 46209.707
A10: 46230.016 | B10: 12 | C10: 747 | D10: 161631 | E10: Александр Багмутов | F10: bagmutov94@mail.ru | G10: 181 | H10: Итоговая аттестация | I10: manual | N10: -
A11: 46230.016 | B11: 12 | C11: 747 | D11: 161631 | E11: Александр Багмутов | F11: bagmutov94@mail.ru | G11: 182 | H11: Кроссвалидация | I11: manual | N11: -
A12: 46230.016 | B12: 12 | C12: 747 | D12: 161631 | E12: Александр Багмутов | F12: bagmutov94@mail.ru | G12: 174 | H12: Посещение вебинаров | I12: mod | J12: attendance | M12: 100 | N12: 100 | P12: 46209.707
A13: 46230.016 | B13: 12 | C13: 747 | D13: 161631 | E13: Александр Багмутов | F13: bagmutov94@mail.ru | G13: 180 | H13: Промежуточная аттестация | I13: manual | N13: -
A14: 46230.016 | B14: 12 | C14: 747 | D14: 161631 | E14: Александр Багмутов | F14: bagmutov94@mail.ru | G14: 175 | H14: Тестирование по модулю 1 | I14: mod | J14: quiz | M14: 100 | N14: 100 | O14: 46216.592 | P14: 46216.592
A15: 46230.016 | B15: 12 | C15: 747 | D15: 161631 | E15: Александр Багмутов | F15: bagmutov94@mail.ru | G15: 177 | H15: Тестирование по модулю 4 | I15: mod | J15: quiz | N15: -
A16: 46230.016 | B16: 12 | C16: 747 | D16: 161631 | E16: Александр Багмутов | F16: bagmutov94@mail.ru | G16: 176 | H16: Тестирование по модулям 2 и 3 | I16: mod | J16: quiz | M16: 95 | N16: 95 | O16: 46227.965 | P16: 46227.965
A17: 46230.016 | B17: 12 | C17: 747 | D17: 161631 | E17: Александр Багмутов | F17: bagmutov94@mail.ru | G17: 168 | H17: Элемент 168 | I17: course | M17: 100 | N17: 100 | P17: 46209.707
A18: 46230.016 | B18: 12 | C18: 758 | E18: Александр Бакулев | F18: contact-bav@mail.ru | G18: 181 | H18: Итоговая аттестация | I18: manual | N18: -
A19: 46230.016 | B19: 12 | C19: 758 | E19: Александр Бакулев | F19: contact-bav@mail.ru | G19: 182 | H19: Кроссвалидация | I19: manual | N19: -
A20: 46230.016 | B20: 12 | C20: 758 | E20: Александр Бакулев | F20: contact-bav@mail.ru | G20: 174 | H20: Посещение вебинаров | I20: mod | J20: attendance | M20: 100 | N20: 100 | P20: 46209.681
A21: 46230.016 | B21: 12 | C21: 758 | E21: Александр Бакулев | F21: contact-bav@mail.ru | G21: 180 | H21: Промежуточная аттестация | I21: manual | N21: -
A22: 46230.016 | B22: 12 | C22: 758 | E22: Александр Бакулев | F22: contact-bav@mail.ru | G22: 175 | H22: Тестирование по модулю 1 | I22: mod | J22: quiz | M22: 87.5 | N22: 87.5 | O22: 46216.347 | P22: 46216.347
A23: 46230.016 | B23: 12 | C23: 758 | E23: Александр Бакулев | F23: contact-bav@mail.ru | G23: 177 | H23: Тестирование по модулю 4 | I23: mod | J23: quiz | N23: -
A24: 46230.016 | B24: 12 | C24: 758 | E24: Александр Бакулев | F24: contact-bav@mail.ru | G24: 176 | H24: Тестирование по модулям 2 и 3 | I24: mod | J24: quiz | M24: 85 | N24: 85 | O24: 46229.966 | P24: 46229.966
A25: 46230.016 | B25: 12 | C25: 758 | E25: Александр Бакулев | F25: contact-bav@mail.ru | G25: 168 | H25: Элемент 168 | I25: course | M25: 100 | N25: 100 | P25: 46209.681
A26: 46230.016 | B26: 12 | C26: 671 | E26: Александр Бастрычкин | F26: a_s_bas@mail.ru | G26: 181 | H26: Итоговая аттестация | I26: manual | N26: -
A27: 46230.016 | B27: 12 | C27: 671 | E27: Александр Бастрычкин | F27: a_s_bas@mail.ru | G27: 182 | H27: Кроссвалидация | I27: manual | N27: -
A28: 46230.016 | B28: 12 | C28: 671 | E28: Александр Бастрычкин | F28: a_s_bas@mail.ru | G28: 174 | H28: Посещение вебинаров | I28: mod | J28: attendance | M28: 100 | N28: 100 | P28: 46211.052
A29: 46230.016 | B29: 12 | C29: 671 | E29: Александр Бастрычкин | F29: a_s_bas@mail.ru | G29: 180 | H29: Промежуточная аттестация | I29: manual | N29: -
A30: 46230.016 | B30: 12 | C30: 671 | E30: Александр Бастрычкин | F30: a_s_bas@mail.ru | G30: 175 | H30: Тестирование по модулю 1 | I30: mod | J30: quiz | M30: 100 | N30: 100 | O30: 46215.831 | P30: 46215.831
A31: 46230.016 | B31: 12 | C31: 671 | E31: Александр Бастрычкин | F31: a_s_bas@mail.ru | G31: 177 | H31: Тестирование по модулю 4 | I31: mod | J31: quiz | N31: -
A32: 46230.016 | B32: 12 | C32: 671 | E32: Александр Бастрычкин | F32: a_s_bas@mail.ru | G32: 176 | H32: Тестирование по модулям 2 и 3 | I32: mod | J32: quiz | M32: 100 | N32: 100 | O32: 46226.406 | P32: 46226.406
A33: 46230.016 | B33: 12 | C33: 671 | E33: Александр Бастрычкин | F33: a_s_bas@mail.ru | G33: 168 | H33: Элемент 168 | I33: course | M33: 100 | N33: 100 | P33: 46211.052
A34: 46230.016 | B34: 12 | C34: 777 | E34: Александр Булычев | F34: bulytchev.isa.ran@gmail.com | G34: 181 | H34: Итоговая аттестация | I34: manual | N34: -
A35: 46230.016 | B35: 12 | C35: 777 | E35: Александр Булычев | F35: bulytchev.isa.ran@gmail.com | G35: 182 | H35: Кроссвалидация | I35: manual | N35: -
A36: 46230.016 | B36: 12 | C36: 777 | E36: Александр Булычев | F36: bulytchev.isa.ran@gmail.com | G36: 174 | H36: Посещение вебинаров | I36: mod | J36: attendance | M36: 100 | N36: 100 | P36: 46209.707
A37: 46230.016 | B37: 12 | C37: 777 | E37: Александр Булычев | F37: bulytchev.isa.ran@gmail.com | G37: 180 | H37: Промежуточная аттестация | I37: manual | N37: -
A38: 46230.016 | B38: 12 | C38: 777 | E38: Александр Булычев | F38: bulytchev.isa.ran@gmail.com | G38: 175 | H38: Тестирование по модулю 1 | I38: mod | J38: quiz | M38: 100 | N38: 100 | O38: 46216.986 | P38: 46216.986
A39: 46230.016 | B39: 12 | C39: 777 | E39: Александр Булычев | F39: bulytchev.isa.ran@gmail.com | G39: 177 | H39: Тестирование по модулю 4 | I39: mod | J39: quiz | N39: -
A40: 46230.016 | B40: 12 | C40: 777 | E40: Александр Булычев | F40: bulytchev.isa.ran@gmail.com | G40: 176 | H40: Тестирование по модулям 2 и 3 | I40: mod | J40: quiz | M40: 90 | N40: 90 | O40: 46229.996 | P40: 46229.996
A41: 46230.016 | B41: 12 | C41: 777 | E41: Александр Булычев | F41: bulytchev.isa.ran@gmail.com | G41: 168 | H41: Элемент 168 | I41: course | M41: 100 | N41: 100 | P41: 46209.707
A42: 46230.016 | B42: 12 | C42: 656 | E42: Александр Владимирович | F42: aazkr@yandex.ru | G42: 181 | H42: Итоговая аттестация | I42: manual | N42: -
A43: 46230.016 | B43: 12 | C43: 656 | E43: Александр Владимирович | F43: aazkr@yandex.ru | G43: 182 | H43: Кроссвалидация | I43: manual | N43: -
A44: 46230.016 | B44: 12 | C44: 656 | E44: Александр Владимирович | F44: aazkr@yandex.ru | G44: 174 | H44: Посещение вебинаров | I44: mod | J44: attendance | M44: 100 | N44: 100 | P44: 46210.415
A45: 46230.016 | B45: 12 | C45: 656 | E45: Александр Владимирович | F45: aazkr@yandex.ru | G45: 180 | H45: Промежуточная аттестация | I45: manual | N45: -
A46: 46230.016 | B46: 12 | C46: 656 | E46: Александр Владимирович | F46: aazkr@yandex.ru | G46: 175 | H46: Тестирование по модулю 1 | I46: mod | J46: quiz | M46: 75 | N46: 75 | O46: 46216.548 | P46: 46216.548
A47: 46230.016 | B47: 12 | C47: 656 | E47: Александр Владимирович | F47: aazkr@yandex.ru | G47: 177 | H47: Тестирование по модулю 4 | I47: mod | J47: quiz | N47: -
A48: 46230.016 | B48: 12 | C48: 656 | E48: Александр Владимирович | F48: aazkr@yandex.ru | G48: 176 | H48: Тестирование по модулям 2 и 3 | I48: mod | J48: quiz | M48: 90 | N48: 90 | O48: 46227.477 | P48: 46227.477
A49: 46230.016 | B49: 12 | C49: 656 | E49: Александр Владимирович | F49: aazkr@yandex.ru | G49: 168 | H49: Элемент 168 | I49: course | M49: 100 | N49: 100 | P49: 46210.415
A50: 46230.016 | B50: 12 | C50: 727 | E50: Александр Грищенко | F50: alexgrihalex@yandex.ru | G50: 181 | H50: Итоговая аттестация | I50: manual | N50: -
A51: 46230.016 | B51: 12 | C51: 727 | E51: Александр Грищенко | F51: alexgrihalex@yandex.ru | G51: 182 | H51: Кроссвалидация | I51: manual | N51: -
A52: 46230.016 | B52: 12 | C52: 727 | E52: Александр Грищенко | F52: alexgrihalex@yandex.ru | G52: 174 | H52: Посещение вебинаров | I52: mod | J52: attendance | M52: 100 | N52: 100 | P52: 46209.707
A53: 46230.016 | B53: 12 | C53: 727 | E53: Александр Грищенко | F53: alexgrihalex@yandex.ru | G53: 180 | H53: Промежуточная аттестация | I53: manual | N53: -
A54: 46230.016 | B54: 12 | C54: 727 | E54: Александр Грищенко | F54: alexgrihalex@yandex.ru | G54: 175 | H54: Тестирование по модулю 1 | I54: mod | J54: quiz | M54: 100 | N54: 100 | O54: 46216.349 | P54: 46216.349
A55: 46230.016 | B55: 12 | C55: 727 | E55: Александр Грищенко | F55: alexgrihalex@yandex.ru | G55: 177 | H55: Тестирование по модулю 4 | I55: mod | J55: quiz | M55: 100 | N55: 100 | O55: 46229.411 | P55: 46229.411
A56: 46230.016 | B56: 12 | C56: 727 | E56: Александр Грищенко | F56: alexgrihalex@yandex.ru | G56: 176 | H56: Тестирование по модулям 2 и 3 | I56: mod | J56: quiz | M56: 100 | N56: 100 | O56: 46229.407 | P56: 46229.407
A57: 46230.016 | B57: 12 | C57: 727 | E57: Александр Грищенко | F57: alexgrihalex@yandex.ru | G57: 168 | H57: Элемент 168 | I57: course | M57: 100 | N57: 100 | P57: 46209.707
A58: 46230.016 | B58: 12 | C58: 765 | E58: Александр Золотарев | F58: amzolotarev@mephi.ru | G58: 181 | H58: Итоговая аттестация | I58: manual | N58: -
A59: 46230.016 | B59: 12 | C59: 765 | E59: Александр Золотарев | F59: amzolotarev@mephi.ru | G59: 182 | H59: Кроссвалидация | I59: manual | N59: -
A60: 46230.016 | B60: 12 | C60: 765 | E60: Александр Золотарев | F60: amzolotarev@mephi.ru | G60: 174 | H60: Посещение вебинаров | I60: mod | J60: attendance | M60: 100 | N60: 100 | P60: 46209.71
A61: 46230.016 | B61: 12 | C61: 765 | E61: Александр Золотарев | F61: amzolotarev@mephi.ru | G61: 180 | H61: Промежуточная аттестация | I61: manual | N61: -
A62: 46230.016 | B62: 12 | C62: 765 | E62: Александр Золотарев | F62: amzolotarev@mephi.ru | G62: 175 | H62: Тестирование по модулю 1 | I62: mod | J62: quiz | M62: 75 | N62: 75 | O62: 46216.979 | P62: 46216.979
A63: 46230.016 | B63: 12 | C63: 765 | E63: Александр Золотарев | F63: amzolotarev@mephi.ru | G63: 177 | H63: Тестирование по модулю 4 | I63: mod | J63: quiz | N63: -
A64: 46230.016 | B64: 12 | C64: 765 | E64: Александр Золотарев | F64: amzolotarev@mephi.ru | G64: 176 | H64: Тестирование по модулям 2 и 3 | I64: mod | J64: quiz | M64: 85 | N64: 85 | O64: 46225.893 | P64: 46225.893
A65: 46230.016 | B65: 12 | C65: 765 | E65: Александр Золотарев | F65: amzolotarev@mephi.ru | G65: 168 | H65: Элемент 168 | I65: course | M65: 100 | N65: 100 | P65: 46209.71
A66: 46230.016 | B66: 12 | C66: 487 | E66: Александр Катаев | F66: alexander.kataev@gmail.com | G66: 181 | H66: Итоговая аттестация | I66: manual | N66: -
A67: 46230.016 | B67: 12 | C67: 487 | E67: Александр Катаев | F67: alexander.kataev@gmail.com | G67: 182 | H67: Кроссвалидация | I67: manual | N67: -
A68: 46230.016 | B68: 12 | C68: 487 | E68: Александр Катаев | F68: alexander.kataev@gmail.com | G68: 174 | H68: Посещение вебинаров | I68: mod | J68: attendance | M68: 100 | N68: 100 | P68: 46209.707
A69: 46230.016 | B69: 12 | C69: 487 | E69: Александр Катаев | F69: alexander.kataev@gmail.com | G69: 180 | H69: Промежуточная аттестация | I69: manual | N69: -
A70: 46230.016 | B70: 12 | C70: 487 | E70: Александр Катаев | F70: alexander.kataev@gmail.com | G70: 175 | H70: Тестирование по модулю 1 | I70: mod | J70: quiz | N70: -
A71: 46230.016 | B71: 12 | C71: 487 | E71: Александр Катаев | F71: alexander.kataev@gmail.com | G71: 177 | H71: Тестирование по модулю 4 | I71: mod | J71: quiz | N71: -
A72: 46230.016 | B72: 12 | C72: 487 | E72: Александр Катаев | F72: alexander.kataev@gmail.com | G72: 176 | H72: Тестирование по модулям 2 и 3 | I72: mod | J72: quiz | N72: -
A73: 46230.016 | B73: 12 | C73: 487 | E73: Александр Катаев | F73: alexander.kataev@gmail.com | G73: 168 | H73: Элемент 168 | I73: course | M73: 100 | N73: 100 | P73: 46209.707
A74: 46230.016 | B74: 12 | C74: 726 | D74: 498651 | E74: Александр Коваленко | F74: sasha@kovalenko.net.ru | G74: 181 | H74: Итоговая аттестация | I74: manual | N74: -
A75: 46230.016 | B75: 12 | C75: 726 | D75: 498651 | E75: Александр Коваленко | F75: sasha@kovalenko.net.ru | G75: 182 | H75: Кроссвалидация | I75: manual | N75: -
A76: 46230.016 | B76: 12 | C76: 726 | D76: 498651 | E76: Александр Коваленко | F76: sasha@kovalenko.net.ru | G76: 174 | H76: Посещение вебинаров | I76: mod | J76: attendance | M76: 100 | N76: 100 | P76: 46210.838
A77: 46230.016 | B77: 12 | C77: 726 | D77: 498651 | E77: Александр Коваленко | F77: sasha@kovalenko.net.ru | G77: 180 | H77: Промежуточная аттестация | I77: manual | N77: -
A78: 46230.016 | B78: 12 | C78: 726 | D78: 498651 | E78: Александр Коваленко | F78: sasha@kovalenko.net.ru | G78: 175 | H78: Тестирование по модулю 1 | I78: mod | J78: quiz | M78: 100 | N78: 100 | O78: 46228.597 | P78: 46228.597
A79: 46230.016 | B79: 12 | C79: 726 | D79: 498651 | E79: Александр Коваленко | F79: sasha@kovalenko.net.ru | G79: 177 | H79: Тестирование по модулю 4 | I79: mod | J79: quiz | N79: -
A80: 46230.016 | B80: 12 | C80: 726 | D80: 498651 | E80: Александр Коваленко | F80: sasha@kovalenko.net.ru | G80: 176 | H80: Тестирование по модулям 2 и 3 | I80: mod | J80: quiz | M80: 100 | N80: 100 | O80: 46229.451 | P80: 46229.451
A81: 46230.016 | B81: 12 | C81: 726 | D81: 498651 | E81: Александр Коваленко | F81: sasha@kovalenko.net.ru | G81: 168 | H81: Элемент 168 | I81: course | M81: 100 | N81: 100 | P81: 46210.838
A82: 46230.016 | B82: 12 | C82: 369 | E82: Александр Колотий | F82: kolotiy.ad@yandex.ru | G82: 181 | H82: Итоговая аттестация | I82: manual | N82: -
A83: 46230.016 | B83: 12 | C83: 369 | E83: Александр Колотий | F83: kolotiy.ad@yandex.ru | G83: 182 | H83: Кроссвалидация | I83: manual | N83: -
A84: 46230.016 | B84: 12 | C84: 369 | E84: Александр Колотий | F84: kolotiy.ad@yandex.ru | G84: 174 | H84: Посещение вебинаров | I84: mod | J84: attendance | M84: 100 | N84: 100 | P84: 46209.707
A85: 46230.016 | B85: 12 | C85: 369 | E85: Александр Колотий | F85: kolotiy.ad@yandex.ru | G85: 180 | H85: Промежуточная аттестация | I85: manual | N85: -
A86: 46230.016 | B86: 12 | C86: 369 | E86: Александр Колотий | F86: kolotiy.ad@yandex.ru | G86: 175 | H86: Тестирование по модулю 1 | I86: mod | J86: quiz | M86: 100 | N86: 100 | O86: 46214.621 | P86: 46214.621
A87: 46230.016 | B87: 12 | C87: 369 | E87: Александр Колотий | F87: kolotiy.ad@yandex.ru | G87: 177 | H87: Тестирование по модулю 4 | I87: mod | J87: quiz | N87: -
A88: 46230.016 | B88: 12 | C88: 369 | E88: Александр Колотий | F88: kolotiy.ad@yandex.ru | G88: 176 | H88: Тестирование по модулям 2 и 3 | I88: mod | J88: quiz | M88: 100 | N88: 100 | O88: 46226.43 | P88: 46226.43
A89: 46230.016 | B89: 12 | C89: 369 | E89: Александр Колотий | F89: kolotiy.ad@yandex.ru | G89: 168 | H89: Элемент 168 | I89: course | M89: 100 | N89: 100 | P89: 46209.707
A90: 46230.016 | B90: 12 | C90: 265 | E90: Александр Колупаев | F90: al_kolupaev@vyatsu.ru | G90: 181 | H90: Итоговая аттестация | I90: manual | N90: -
A91: 46230.016 | B91: 12 | C91: 265 | E91: Александр Колупаев | F91: al_kolupaev@vyatsu.ru | G91: 182 | H91: Кроссвалидация | I91: manual | N91: -
A92: 46230.016 | B92: 12 | C92: 265 | E92: Александр Колупаев | F92: al_kolupaev@vyatsu.ru | G92: 174 | H92: Посещение вебинаров | I92: mod | J92: attendance | M92: 100 | N92: 100 | P92: 46209.707
A93: 46230.016 | B93: 12 | C93: 265 | E93: Александр Колупаев | F93: al_kolupaev@vyatsu.ru | G93: 180 | H93: Промежуточная аттестация | I93: manual | N93: -
A94: 46230.016 | B94: 12 | C94: 265 | E94: Александр Колупаев | F94: al_kolupaev@vyatsu.ru | G94: 175 | H94: Тестирование по модулю 1 | I94: mod | J94: quiz | M94: 100 | N94: 100 | O94: 46215.976 | P94: 46215.976
A95: 46230.016 | B95: 12 | C95: 265 | E95: Александр Колупаев | F95: al_kolupaev@vyatsu.ru | G95: 177 | H95: Тестирование по модулю 4 | I95: mod | J95: quiz | N95: -
A96: 46230.016 | B96: 12 | C96: 265 | E96: Александр Колупаев | F96: al_kolupaev@vyatsu.ru | G96: 176 | H96: Тестирование по модулям 2 и 3 | I96: mod | J96: quiz | M96: 100 | N96: 100 | O96: 46223.906 | P96: 46223.906
A97: 46230.016 | B97: 12 | C97: 265 | E97: Александр Колупаев | F97: al_kolupaev@vyatsu.ru | G97: 168 | H97: Элемент 168 | I97: course | M97: 100 | N97: 100 | P97: 46209.707
A98: 46230.016 | B98: 12 | C98: 665 | E98: Александр Кревецкий | F98: krevetsk@mail.ru | G98: 181 | H98: Итоговая аттестация | I98: manual | N98: -
A99: 46230.016 | B99: 12 | C99: 665 | E99: Александр Кревецкий | F99: krevetsk@mail.ru | G99: 182 | H99: Кроссвалидация | I99: manual | N99: -
A100: 46230.016 | B100: 12 | C100: 665 | E100: Александр Кревецкий | F100: krevetsk@mail.ru | G100: 174 | H100: Посещение вебинаров | I100: mod | J100: attendance | M100: 100 | N100: 100 | P100: 46209.707
...

Sheet Входной тест
C1: Полное имя пользователя | E1: Адрес электронной почты | F1: Дата | G1: 1. Какие дисциплины Вы преподаете (или планируете преподавать) по образовательным программам топ-уровня? (Укажите конкретные названия курсов / дисциплин / модулей) | H1: 2. Какой у Вас базовый профиль образования? | I1: 3. Знакомы ли Вы с Компетентностно-ролевой моделью (КРМ) в сфере искусственного интеллекта? | J1: 4. Какие разделы КРМ Вам знакомы лучше всего? *(Выберите все подходящие варианты) | K1: 5. Если на предыдущий вопрс Вы ответили "другое", пожалуйста, поясните | L1: 6. Используете ли Вы КРМ при разработке или актуализации рабочих программ дисциплин (РПД)? | M1: 7. Оцените, насколько Вы умеете "переводить" требования КРМ в конкретные результаты обучения и оценочные средства: | N1: 8. Используете ли Вы КРМ при проектировании фонда оценочных средств (ФОС)? | O1: 9. Оцените от 0 до 4 Ваш практический навык «Проектирование информационных систем без программирования (в том числе с помощью графических языков UML/C4)» | P1: 10. Оцените от 0 до 4 Ваш практический навык «Разработка баз данных (SQL, Ключ-значение, документно-ориентированные…)» | Q1: 11. Оцените от 0 до 4 Ваш практический навык «Python (программирование)» | R1: 12. Оцените от 0 до 4 Ваш практический навык «Работа с библиотеками машинного обучения» | S1: 13. Оцените от 0 до 4 Ваш практический навык «Системы контроля версий (Git)» | T1: 14. Оцените от 0 до 4 Ваш практический навык «Контейнеризация (Docker) и облачные платформы» | U1: 15. Оцените от 0 до 4 Ваш практический навык «Работа с большими данными (обработка, хранение)» | V1: 16. Оцените от 0 до 4 Ваш практический навык «Владение большими языковыми моделями (от общего представления до использования программных интерфейсов)» | W1: 17. Оцените от 0 до 4 Ваш навык «Разработка рабочих программ дисциплин (РПД)» | X1: 18. Оцените от 0 до 4 Ваш навык «Создание фонда оценочных средств (ФОС)» | Y1: 19. Оцените от 0 до 4 Ваш навык «Проектирование практико-ориентированных занятий» | Z1: 20. Оцените от 0 до 4 Ваш навык «Организация проектной и командной работы студентов» | AA1: 21. Оцените от 0 до 4 Ваш навык «Опыт разработки средств автоматизации для учебных целей» | AB1: 22. Оцените от 0 до 4 Ваш опыт участия в совместных проектах с ИТ-компаниями | AC1: 23. Оцените от 0 до 4 вовлечение индустриальных партнеров в учебный процесс на Вашей образовательной программе | AD1: 24. Оцените от 0 до 4 насколько трансформированны реальные бизнес-задачи в Ваши учебные кейсы | AE1: 25. Организовывали ли вы проектную работу студентов? | AF1: 26. Какие роли вы выполняете / готовы выполнять в команде? (Выберите 1-2 основных варианта) | AG1: 27. Какой у вас опыт преподавания (в годах)? | AH1: 28. Каких результатов вы ожидаете от обучения? (Напишите 2-3 ключевых пункта) | AI1: 29. Есть ли у вас конкретные дисциплины / модули, которые вы хотите разработать или актуализировать в рамках проектной работы? Если да, укажите:
A2: TRUE | B2: {=_xlfn.XLOOKUP(E2,#REF!,#REF!)} -> #REF! | C2: Татьяна Синева | E2: t.sineva@g.nsu.ru | F2: 46206.703 | G2: Учебная практика (ознакомительная практика) Введение в проектную деятельность | H2: Информатика / Программирование | I2: Использую КРМ в своей профессиональной деятельности | J2: Компетенции в области машинного обучения (ML) | L2: Планирую начать использовать в ближайшее время | M2: Владею на базовом уровне | N2: Иногда, для отдельных дисциплин | O2: 2 | P2: 2 | Q2: 3 | R2: 2 | S2: 2 | T2: 2 | U2: 2 | V2: 2 | W2: 4 | X2: 4 | Y2: 4 | Z2: 4 | AA2: 3 | AB2: 4 | AC2: 4 | AD2: 3 | AE2: Да, регулярно | AF2: Методолог (проектирование образовательных результатов и ФОС) | AG2: 7–10 лет | AH2: Глубокое понимание КРМ | AI2: Нет
A3: TRUE | B3: {=_xlfn.XLOOKUP(E3,#REF!,#REF!)} -> #REF! | C3: Сергей Кузнецов | E3: sergodk@mail.ru | F3: 46206.71 | G3: Программирование на языке Python | H3: Компьютерные науки | I3: Использую КРМ в своей профессиональной деятельности | J3: Ни один из разделов не знаком | L3: Да, применяю как основу для проектирования | M3: Владею на базовом уровне | N3: Да, для всех дисциплин, которые разрабатываю | O3: 2 | P3: 1 | Q3: 4 | R3: 3 | S3: 4 | T3: 4 | U3: 1 | V3: 2 | W3: 2 | X3: 2 | Y3: 2 | Z3: 3 | AA3: 2 | AB3: 1 | AC3: 2 | AD3: 2 | AE3: Да, регулярно | AF3: Постановщик задач Методолог (проектирование образовательных результатов и ФОС) Практик-разработчик (код, инструменты, инфраструктура) | AG3: Более 10 лет | AH3: Ознакомиться с методологией разработки РПД для программ ТОП_ИИ Понять принципы устройства модели КРМ Научиться разработке актуальных и значимых РПД для программ ТОП_ИИ | AI3: Пока нет.
A4: TRUE | B4: {=_xlfn.XLOOKUP(E4,#REF!,#REF!)} -> #REF! | C4: Михаил Филиппов | E4: m.filippov@g.nsu.ru | F4: 46206.71 | G4: Императивное программирование, Основы ООП, УПРППО. | H4: Математика / Прикладная математика | I4: Слышал(а) о ней, но не изучал(а) подробно | J4: Компетенции в области математических основ ИИ (MF) Компетенции в области машинного обучения (ML) | L4: Нет, никогда не использовал(а) | M4: Владею на базовом уровне | N4: Нет, никогда | O4: 2 | P4: 3 | Q4: 3 | R4: 3 | S4: 3 | T4: 3 | U4: 3 | V4: 3 | W4: 3 | X4: 3 | Y4: 2 | Z4: 3 | AA4: 3 | AB4: 3 | AC4: 2 | AD4: 2 | AE4: Да, регулярно | AF4: Постановщик задач Эксперт по содержанию (глубокое знание предметной области ИИ) Методолог (проектирование образовательных результатов и ФОС) Практик-разработчик (код, инструменты, инфраструктура) Эксперт по КРМ (знание структуры, методик применения) | AG4: 3–6 лет | AH4: Методы обучения, которые вы применяете в своём университете. Организация процессов с бизнесом, как привлечь бизнес надолго. Как эффективно (быстро) сделать методические пособия к предмету. | AI4: Все: Основы ООП, УПРППО, Императивное программирование. Я каждое лето актуализирую.
A5: TRUE | B5: {=_xlfn.XLOOKUP(E5,#REF!,#REF!)} -> #REF! | C5: Irina Dvoretskaya | E5: idorogova@mail.ru | F5: 46206.711 | G5: Теория Вероятностей, прикладной ИИ. | H5: Математика / Прикладная математика | I5: Использую КРМ в своей профессиональной деятельности | J5: Компетенции в области больших языковых моделей (LLM) Компетенции в области жизненного цикла систем искусственного интеллекта (FC) | L5: Планирую начать использовать в ближайшее время | M5: Владею на базовом уровне | N5: Планирую использовать в будущем | O5: 2 | P5: 2 | Q5: 3 | R5: 3 | S5: 2 | T5: 1 | U5: 3 | V5: 2 | W5: 3 | X5: 4 | Y5: 4 | Z5: 4 | AA5: 4 | AB5: 4 | AC5: 4 | AD5: 3 | AE5: Да, регулярно | AF5: Постановщик задач Эксперт по содержанию (глубокое знание предметной области ИИ) Методолог (проектирование образовательных результатов и ФОС) | AG5: 3–6 лет | AH5: 1. Углубить свои знания о КРМ, связать их с знакомыми подходами проектирования обучения 2. Развить навыки постановки задач практического характера с спецификой программы. | AI5: нет
A6: TRUE | B6: {=_xlfn.XLOOKUP(E6,#REF!,#REF!)} -> #REF! | C6: Наталья Исупова | E6: natalyisupova@mail.ru | F6: 46206.712 | G6: Управление ИТ-проектами | H6: Математика / Прикладная математика | I6: Слышал(а) о ней, но не изучал(а) подробно | J6: Компетенции в области математических основ ИИ (MF) | L6: Нет, никогда не использовал(а) | M6: Не владею, не понимаю, как это делать | N6: Нет, никогда | O6: 0 | P6: 2 | Q6: 1 | R6: 0 | S6: 0 | T6: 0 | U6: 0 | V6: 1 | W6: 3 | X6: 3 | Y6: 3 | Z6: 2 | AA6: 1 | AB6: 0 | AC6: 0 | AD6: 1 | AE6: Нет, но планирую | AF6: Методолог (проектирование образовательных результатов и ФОС) | AG6: Более 10 лет | AH6: Прокачка навыков работы с большими данными и ии, крм | AI6: Пока нет
A7: TRUE | B7: {=_xlfn.XLOOKUP(E7,#REF!,#REF!)} -> #REF! | C7: Анастасия Котельникова | E7: usr11503@vyatsu.ru | F7: 46206.712 | G7: Обработка_естественного_языка_и_машинный_анализ_текстов | H7: Информатика / Программирование | I7: Изучал(а) структуру КРМ, но не применял(а) в работе | J7: Компетенции в области машинного обучения (ML) | L7: Да, применяю как основу для проектирования | M7: Владею на базовом уровне | N7: Планирую использовать в будущем | O7: 2 | P7: 1 | Q7: 4 | R7: 3 | S7: 1 | T7: 1 | U7: 2 | V7: 2 | W7: 2 | X7: 2 | Y7: 2 | Z7: 2 | AA7: 2 | AB7: 2 | AC7: 2 | AD7: 2 | AE7: Да, иногда | AF7: Практик-разработчик (код, инструменты, инфраструктура) | AG7: Более 10 лет | AH7: Проще будет оценить позже, когда детальнее узнаю о содержании обучения | AI7: Обработка_естественного_языка_и_машинный_анализ_текстов
A8: TRUE | B8: {=_xlfn.XLOOKUP(E8,#REF!,#REF!)} -> #REF! | C8: Ирина Юманова | E8: yuirfa@mail.ru | F8: 46206.715 | G8: Алгоритмы и методы машинного обучения, машинное обучение | H8: Математика / Прикладная математика | I8: Использую КРМ в своей профессиональной деятельности | J8: Компетенции в области математических основ ИИ (MF) Компетенции в области машинного обучения (ML) | L8: Да, применяю как основу для проектирования | M8: Владею на базовом уровне | N8: Да, для всех дисциплин, которые разрабатываю | O8: 2 | P8: 1 | Q8: 2 | R8: 4 | S8: 2 | T8: 1 | U8: 2 | V8: 2 | W8: 2 | X8: 2 | Y8: 2 | Z8: 2 | AA8: 2 | AB8: 2 | AC8: 3 | AD8: 2 | AE8: Да, иногда | AF8: Методолог (проектирование образовательных результатов и ФОС) | AG8: Более 10 лет | AH8: От обучения я жду прикладных инструментов, которые можно сразу интегрировать в рабочие процессы, а также освоения навыков декомпозиции для грамотной разбивки крупных задач. В совокупности это позволит мне существенно оптимизировать время разработки | AI8: Машинное обучение
A9: TRUE | B9: {=_xlfn.XLOOKUP(E9,#REF!,#REF!)} -> #REF! | C9: Ольга Караваева | E9: karavaeva@vyatsu.ru | F9: 46206.716 | G9: Архитектура операционных систем, Программные комплексы решения интеллектуальных задач. | H9: Компьютерные науки | I9: Слышал(а) о ней, но не изучал(а) подробно | J9: Ни один из разделов не знаком | L9: Планирую начать использовать в ближайшее время | M9: Не владею, не понимаю, как это делать | N9: Планирую использовать в будущем | O9: 2 | P9: 1 | Q9: 1 | R9: 0 | S9: 0 | T9: 0 | U9: 0 | V9: 0 | W9: 2 | X9: 2 | Y9: 1 | Z9: 0 | AA9: 2 | AB9: 0 | AC9: 0 | AD9: 1 | AE9: Нет, не планирую | AF9: Постановщик задач | AG9: Более 10 лет | AH9: Получить навык использования современных технологий в учебном процессе. | AI9: Многопроцессорные операционные системы.
A10: TRUE | B10: {=_xlfn.XLOOKUP(E10,#REF!,#REF!)} -> #REF! | C10: Эльмар Кулиев | E10: elmar_2005@mail.ru | F10: 46206.719 | G10: Архитектуры искусственного интеллекта | H10: Компьютерные науки | I10: Использую КРМ в своей профессиональной деятельности | J10: Компетенции в области машинного обучения (ML) | L10: Да, применяю как основу для проектирования | M10: Владею на базовом уровне | N10: Иногда, для отдельных дисциплин | O10: 1 | P10: 1 | Q10: 0 | R10: 2 | S10: 2 | T10: 0 | U10: 1 | V10: 1 | W10: 3 | X10: 3 | Y10: 3 | Z10: 4 | AA10: 3 | AB10: 3 | AC10: 3 | AD10: 3 | AE10: Да, регулярно | AF10: Постановщик задач Методолог (проектирование образовательных результатов и ФОС) | AG10: 7–10 лет | AH10: Получение навыков, которые можно применить на практике. | AI10: -
A11: TRUE | B11: {=_xlfn.XLOOKUP(E11,#REF!,#REF!)} -> #REF! | C11: Наталья Добровольская | E11: dnu10@mail.ru | F11: 46206.723 | G11: Язык Python, Объектно-ориентированное программирование, Обработка естественного языка | H11: Математика / Прикладная математика | I11: Использую КРМ в своей профессиональной деятельности | J11: Компетенции в области машинного обучения (ML) Компетенции в области больших языковых моделей (LLM) | L11: Да, применяю как основу для проектирования | M11: Владею на базовом уровне | N11: Да, для всех дисциплин, которые разрабатываю | O11: 4 | P11: 1 | Q11: 3 | R11: 1 | S11: 1 | T11: 0 | U11: 1 | V11: 2 | W11: 4 | X11: 4 | Y11: 3 | Z11: 4 | AA11: 4 | AB11: 2 | AC11: 1 | AD11: 1 | AE11: Да, регулярно | AF11: Постановщик задач Методолог (проектирование образовательных результатов и ФОС) | AG11: Более 10 лет | AH11: Приобретение новых навыков разработки ИИ-дисциплин, развитие навыков организации ИИ-проектов | AI11: Акуаоюлизация дисциплины:Обработка естественного языка, разработка модуля ИИ в Java
A12: TRUE | B12: {=_xlfn.XLOOKUP(E12,#REF!,#REF!)} -> #REF! | C12: Арсений Жук | E12: arseniyzhuck@mail.ru | F12: 46206.723 | G12: Технологии компьютерного зрения, Современные методы компьютерного зрения, паттерны проектирования | H12: Математика / Прикладная математика | I12: Использую КРМ в своей профессиональной деятельности | J12: Профессиональные роли Компетенции в области глубокого обучения (DL) | L12: Да, применяю как основу для проектирования | M12: Владею на базовом уровне | N12: Иногда, для отдельных дисциплин | O12: 3 | P12: 3 | Q12: 3 | R12: 3 | S12: 2 | T12: 1 | U12: 1 | V12: 1 | W12: 3 | X12: 3 | Y12: 4 | Z12: 3 | AA12: 3 | AB12: 4 | AC12: 3 | AD12: 3 | AE12: Да, регулярно | AF12: Постановщик задач Эксперт по содержанию (глубокое знание предметной области ИИ) Практик-разработчик (код, инструменты, инфраструктура) | AG12: Более 10 лет | AH12: 1. Повышение навыков использования инструментов обработки больших данных и инструментов работы с ML/DL моделями при проведении лабораторных занятий со студентами 2. Ознакомиться с практиками постановки задач студентам из бизнес-кейсов индустрии, то есть посмотреть, как на практике организовывается работа студентов с реальными задачами индустрии с учетом аспектов доступа, объема задач и времени на погружение, системности построения учебных дисциплин | AI12: 1. Современные методы компьютерного зрения
A13: TRUE | B13: {=_xlfn.XLOOKUP(E13,#REF!,#REF!)} -> #REF! | C13: Евгений Мартюшев | E13: martiushevev@susu.ru | F13: 46206.725 | G13: Математический анализ Специальные главы математики Методы оптимизации | H13: Математика / Прикладная математика | I13: Слышал(а) о ней, но не изучал(а) подробно | J13: Компетенции в области математических основ ИИ (MF) | L13: Нет, никогда не использовал(а) | M13: Не владею, не понимаю, как это делать | N13: Нет, никогда | O13: 0 | P13: 0 | Q13: 1 | R13: 0 | S13: 1 | T13: 0 | U13: 0 | V13: 2 | W13: 2 | X13: 2 | Y13: 0 | Z13: 1 | AA13: 2 | AB13: 1 | AC13: 0 | AD13: 0 | AE13: Нет, не планирую | AF13: Практик-разработчик (код, инструменты, инфраструктура) | AG13: Более 10 лет | AH13: Не знаю | AI13: Нет
... A75: TRUE | B75: {=_xlfn.XLOOKUP(E75,#REF!,#REF!)} -> #REF! | C75: Роман Гараев | E75: demo8916@gmail.com | F75: 46207.543 | G75: -Практическое машинное обучение и глубокое обучение -Обработка естественного языка | H75: Компьютерные науки | I75: Нет, совсем не знаком(а) | J75: Компетенции в области математических основ ИИ (MF) Компетенции в области машинного обучения (ML) Компетенции в области глубокого обучения (DL) Компетенции в области больших языковых моделей (LLM) Компетенции в области жизненного цикла систем искусственного интеллекта (FC) | L75: Нет, никогда не использовал(а) | M75: Не владею, не понимаю, как это делать | N75: Нет, никогда | O75: 1 | P75: 2 | Q75: 4 | R75: 4 | S75: 4 | T75: 4 | U75: 3 | V75: 4 | W75: 1 | X75: 0 | Y75: 3 | Z75: 3 | AA75: 3 | AB75: 4 | AC75: 1 | AD75: 2 | AE75: Да, регулярно | AF75: Постановщик задач Эксперт по содержанию (глубокое знание предметной области ИИ) | AG75: 3–6 лет | AH75: Познакомиться с вашей методологией составления курсов. Пока составление занятий и подача информации основывается на интуиции, опыте, и курсе ISW, интересно изучить более систематизированный подход | AI75: Хочу подготовить элективный курс по безопасным нейронным сетям
A76: TRUE | B76: {=_xlfn.XLOOKUP(E76,#REF!,#REF!)} -> #REF! | C76: Иван Конюхов | E76: i.konyukhov@innopolis.ru | F76: 46207.544 | G76: Математический анализ Аналитическая геометрия Линейная алгебра Дифференциальные уравнения Высокопроизводительные вычисления | H76: Математика / Прикладная математика | I76: Участвовал(а) в разработке или доработке КРМ | J76: Профессиональные роли Компетенции в области математических основ ИИ (MF) Компетенции в области машинного обучения (ML) | K76: Нет | L76: Да, применяю как основу для проектирования | M76: Владею на базовом уровне | N76: Да, для всех дисциплин, которые разрабатываю | O76: 4 | P76: 3 | Q76: 4 | R76: 4 | S76: 4 | T76: 3 | U76: 4 | V76: 4 | W76: 4 | X76: 3 | Y76: 4 | Z76: 4 | AA76: 3 | AB76: 4 | AC76: 3 | AD76: 2 | AE76: Да, регулярно | AF76: Постановщик задач Практик-разработчик (код, инструменты, инфраструктура) | AG76: Более 10 лет | AH76: Интересно посмотреть на автоматизацию создания учебных материалов, фосов с помощью llm, может быть какие-то анкетные истории | AI76: Можно посмотреть на то, как можно было бы трансформировать какую-то классическую дисциплину, вроде математического анализа, под КРМ и вещи, связанные с ИИ. Мы и сами делаем, но, может, что-то упускаем. Интересен взгляд со стороны.
A77: TRUE | B77: {=_xlfn.XLOOKUP(E77,#REF!,#REF!)} -> #REF! | C77: Алексей Забашта | E77: alex.zabashta@yandex.ru | F77: 46207.546 | G77: Автоматическое машинное обучение | H77: Компьютерные науки | I77: Нет, совсем не знаком(а) | J77: Компетенции в области математических основ ИИ (MF) Компетенции в области машинного обучения (ML) Компетенции в области глубокого обучения (DL) Компетенции в области больших языковых моделей (LLM) | L77: Нет, никогда не использовал(а) | M77: Не владею, не понимаю, как это делать | N77: Нет, никогда | O77: 2 | P77: 2 | Q77: 4 | R77: 4 | S77: 3 | T77: 2 | U77: 1 | V77: 4 | W77: 3 | X77: 3 | Y77: 2 | Z77: 4 | AA77: 4 | AB77: 2 | AC77: 4 | AD77: 4 | AE77: Да, иногда | AF77: Постановщик задач Эксперт по содержанию (глубокое знание предметной области ИИ) Методолог (проектирование образовательных результатов и ФОС) Практик-разработчик (код, инструменты, инфраструктура) | AG77: 7–10 лет | AH77: Узнать, что такое КРМ и как её применять | AI77: Автоматическое машинное обучение
A78: TRUE | B78: {=_xlfn.XLOOKUP(E78,#REF!,#REF!)} -> #REF! | C78: Алексей Брюховецкий | E78: a.alexir@mail.ru | F78: 46207.549 | G78: Технологии интеллектуальной защиты информации | H78: Математика / Прикладная математика | I78: Использую КРМ в своей профессиональной деятельности | J78: Компетенции в области математических основ ИИ (MF) Компетенции в области машинного обучения (ML) | L78: Да, применяю как основу для проектирования | M78: Владею на базовом уровне | N78: Иногда, для отдельных дисциплин | O78: 3 | P78: 3 | Q78: 1 | R78: 3 | S78: 1 | T78: 1 | U78: 1 | V78: 1 | W78: 3 | X78: 2 | Y78: 2 | Z78: 1 | AA78: 1 | AB78: 1 | AC78: 2 | AD78: 2 | AE78: Нет, но планирую | AF78: Методолог (проектирование образовательных результатов и ФОС) | AG78: Более 10 лет | AH78: Приобрести навыки практической работы | AI78: В будущем планируется курс по обеспечению безопасности БТС в сетях Vanet
A79: TRUE | B79: {=_xlfn.XLOOKUP(E79,#REF!,#REF!)} -> #REF! | C79: Ольга Иванова | E79: onivanova@susu.ru | F79: 46207.563 | G79: 1. Базы данных 2. Базы данных NoSQL 3. Введение в проектную деятельность 4. Программирование на Python 5. Проектирование человеко-машинного интерфейса 6. Сбор, анализ и предобработка данных в машинном обучении 7. Трек индустриального партнера 8. Учебная практика 9. Машинное обучение 10. Основы DevOps 11. Современные языки программирования высокого уровня 12. Тестирование программного обеспечения 13. Функциональное и логическое программирование 14. Экспертные системы 15. Программная инженерия | H79: Информатика / Программирование | I79: Участвовал(а) в разработке или доработке КРМ | J79: Профессиональные роли Компетенции в области машинного обучения (ML) Компетенции в области глубокого обучения (DL) Компетенции в области жизненного цикла систем искусственного интеллекта (FC) | L79: Да, применяю как основу для проектирования | M79: Владею хорошо, могу обучить коллег | N79: Да, для всех дисциплин, которые разрабатываю | O79: 4 | P79: 4 | Q79: 4 | R79: 4 | S79: 4 | T79: 4 | U79: 4 | V79: 4 | W79: 3 | X79: 3 | Y79: 3 | Z79: 3 | AA79: 3 | AB79: 4 | AC79: 4 | AD79: 3 | AE79: Да, регулярно | AF79: Методолог (проектирование образовательных результатов и ФОС) Эксперт по КРМ (знание структуры, методик применения) | AG79: Более 10 лет | AH79: Я хотела бы актуализировать учебно-методический комплект (рабочую программу, ФОСы, методические материалы и т.д.) по одной из дисциплин таким образом, чтобы она не только соответствовала передовым российским и мировым научным достижениям, но и стала бы целостной образовательной системой от целей и результатов обучения до практических заданий, критериев оценивания, цифровой среды, проектной работы и регулярного обновления содержания с прозрачными, прослеживаемыми результатами освоения компетенций; а также чтобы такая система была адаптирована под новый портрет слушателя - учащийся поколения Z в новых реалиях мира (информационная эра, технологический суверенитет, критические информационные технологии, новые экономические вызовы, ориентация на запрос регионального рынка). | AI79: Если проектная работа будет командная, то я хотела бы актуализировать дисциплину &quot;Сбор, анализ и предобработка данных в машинном обучении&quot;. Если проектная работа будет индивидуальной, то я хотела бы актуализировать дисциплине &quot;Современные языки программирования высокого уровня&quot;
A80: TRUE | B80: {=_xlfn.XLOOKUP(E80,#REF!,#REF!)} -> #REF! | C80: Ирина Сафроненкова | E80: safronenkova050788@yandex.ru | F80: 46207.571 | G80: Представление и использование знаний в интеллектуальных системах Учебная практика | H80: Информатика / Программирование | I80: Слышал(а) о ней, но не изучал(а) подробно | J80: Ни один из разделов не знаком | L80: Нет, никогда не использовал(а) | M80: Не владею, не понимаю, как это делать | N80: Нет, никогда | O80: 1 | P80: 0 | Q80: 1 | R80: 0 | S80: 0 | T80: 0 | U80: 1 | V80: 2 | W80: 2 | X80: 2 | Y80: 2 | Z80: 2 | AA80: 1 | AB80: 0 | AC80: 1 | AD80: 1 | AE80: Да, иногда | AF80: Методолог (проектирование образовательных результатов и ФОС) | AG80: Менее 3 лет | AH80: Усовершенствовать знания в области ИИ | AI80: Представление и использование знаний в интеллектуальных системах
A81: TRUE | B81: {=_xlfn.XLOOKUP(E81,#REF!,#REF!)} -> #REF! | C81: Олег Расин | E81: rasin.oleg@k66.ru | F81: 46207.581 | G81: преподаю: Алгебра и геометрия, Дискретная математика | H81: Математика / Прикладная математика | I81: Слышал(а) о ней, но не изучал(а) подробно | J81: Компетенции в области математических основ ИИ (MF) | L81: Планирую начать использовать в ближайшее время | M81: Владею на базовом уровне | N81: Нет, никогда | O81: 0 | P81: 0 | Q81: 2 | R81: 2 | S81: 1 | T81: 0 | U81: 0 | V81: 1 | W81: 2 | X81: 3 | Y81: 3 | Z81: 3 | AA81: 1 | AB81: 1 | AC81: 3 | AD81: 2 | AE81: Да, иногда | AF81: Методолог (проектирование образовательных результатов и ФОС) | AG81: Более 10 лет | AH81: Познакомиться получше с КРМ Узнать как эффективно использовать в работе | AI81: Хотелось бы предварительно получше понять суть дела
A82: TRUE | B82: {=_xlfn.XLOOKUP(E82,#REF!,#REF!)} -> #REF! | C82: Мария Москаленко | E82: moskalenko.mary@gmail.com | F82: 46207.582 | G82: Линейная алгебра и обработка данных Методы оптимизации Численные методы | H82: Математика / Прикладная математика | I82: Участвовал(а) в разработке или доработке КРМ | J82: Профессиональные роли Компетенции в области математических основ ИИ (MF) Компетенции в области машинного обучения (ML) | L82: Да, применяю как основу для проектирования | M82: Владею хорошо, могу обучить коллег | N82: Да, для всех дисциплин, которые разрабатываю | O82: 2 | P82: 3 | Q82: 2 | R82: 2 | S82: 3 | T82: 1 | U82: 2 | V82: 3 | W82: 4 | X82: 4 | Y82: 3 | Z82: 3 | AA82: 4 | AB82: 2 | AC82: 2 | AD82: 1 | AE82: Да, иногда | AF82: Постановщик задач Методолог (проектирование образовательных результатов и ФОС) Эксперт по КРМ (знание структуры, методик применения) | AG82: Более 10 лет | AH82: Хочу познакомиться со взглядом коллег и экспертов на современное ИИ-образование. | AI82: Теория игр Методы оптимизации
A83: TRUE | B83: {=_xlfn.XLOOKUP(E83,#REF!,#REF!)} -> #REF! | C83: Светлана Турлакова | E83: turlakovasu@susu.ru | F83: 46207.582 | G83: Дискретная математика, Теория вероятностей, Математическая статистика и байесовские модели, Проектно-исследовательский семинар | H83: Математика / Прикладная математика | I83: Использую КРМ в своей профессиональной деятельности | J83: Компетенции в области математических основ ИИ (MF) | L83: Да, применяю как основу для проектирования | M83: Владею на базовом уровне | N83: Да, для всех дисциплин, которые разрабатываю | O83: 0 | P83: 0 | Q83: 2 | R83: 2 | S83: 0 | T83: 0 | U83: 0 | V83: 0 | W83: 4 | X83: 4 | Y83: 4 | Z83: 4 | AA83: 3 | AB83: 1 | AC83: 0 | AD83: 2 | AE83: Нет, но планирую | AF83: Методолог (проектирование образовательных результатов и ФОС) | AG83: Более 10 лет | AH83: Изучить опыт коллег и расширить представление о том, как методически грамотно связывать разделы фундаментальной математики с конкретными механизмами современных нейросетей (трансформеры, диффузионные модели, байесовские подходы) с учетом того, что подробно последние будут изучаться позже на старших курсах. Изучить методический опыт обучения студентов построению полного цикла исследовательского проекта от постановки задачи к реализации простейшего пайплайна, экспериментам с байесовской оптимизацией и получению готового продукта | AI83: Проектно-исследовательский семинар
A84: TRUE | B84: {=_xlfn.XLOOKUP(E84,#REF!,#REF!)} -> #REF! | C84: Александр Трифанов | E84: alextrifanov@gmail.com | F84: 46207.584 | G84: Дифференциальная геометрия, Численные методы линейной алгебры | H84: Математика / Прикладная математика | I84: Использую КРМ в своей профессиональной деятельности | J84: Профессиональные роли Компетенции в области математических основ ИИ (MF) Компетенции в области машинного обучения (ML) | L84: Да, применяю как основу для проектирования | M84: Владею хорошо, могу обучить коллег | N84: Да, для всех дисциплин, которые разрабатываю | O84: 2 | P84: 1 | Q84: 2 | R84: 2 | S84: 3 | T84: 1 | U84: 2 | V84: 3 | W84: 3 | X84: 3 | Y84: 3 | Z84: 3 | AA84: 3 | AB84: 2 | AC84: 2 | AD84: 1 | AE84: Да, иногда | AF84: Постановщик задач Методолог (проектирование образовательных результатов и ФОС) Практик-разработчик (код, инструменты, инфраструктура) | AG84: Более 10 лет | AH84: Получить современные представления об образовании в области ИИ. Практические навыки по проектированию УММ в области ИИ. | AI84: 1. Дифференциальная геометрия 2. Продвинутые методы оптимизации
A85: TRUE | B85: {=_xlfn.XLOOKUP(E85,#REF!,#REF!)} -> #REF! | C85: Светлана Силинская | E85: silinskaya1@mail.ru | F85: 46207.59 | G85: Математические методы и модели исследования операций; Дискретное программирование; Теория вероятностей и математическая статистика; Математический анализ; Функциональный анализ; | H85: Математика / Прикладная математика | I85: Изучал(а) структуру КРМ, но не применял(а) в работе | J85: Профессиональные роли Компетенции в области математических основ ИИ (MF) Компетенции в области машинного обучения (ML) Компетенции в области глубокого обучения (DL) Компетенции в области больших языковых моделей (LLM) | L85: Планирую начать использовать в ближайшее время | M85: Владею на базовом уровне | N85: Иногда, для отдельных дисциплин | O85: 4 | P85: 4 | Q85: 4 | R85: 4 | S85: 4 | T85: 4 | U85: 4 | V85: 4 | W85: 3 | X85: 3 | Y85: 4 | Z85: 3 | AA85: 3 | AB85: 2 | AC85: 2 | AD85: 2 | AE85: Да, регулярно | AF85: Эксперт по содержанию (глубокое знание предметной области ИИ) Практик-разработчик (код, инструменты, инфраструктура) | AG85: Более 10 лет | AH85: Сформировать целостное, системное видение: хочу перейти от фрагментарных знаний об ИИ к стройной картине, чтобы понимать, как логично выстраивать архитектуру образовательных программ. Освоить передовые методики преподавания: научиться объяснять сложные концепции ИИ доступно, но без потери академической или технической глубины. Получить лучшие практики: узнать, как адаптировать учебные материалы под стремительно меняющиеся реалии рынка и технологий. | AI85: Нет
A86: TRUE | B86: {=_xlfn.XLOOKUP(E86,#REF!,#REF!)} -> #REF! | C86: Екатерина Мочалина | E86: mochalina.ep@rea.ru | F86: 46207.594 | G86: Математический анализ, Теория вероятности и математическая статистика, Дискретная математика, Дифференциальные уравнения, Модели временных рядов, | H86: Математика / Прикладная математика | I86: Изучал(а) структуру КРМ, но не применял(а) в работе | J86: Профессиональные роли Компетенции в области математических основ ИИ (MF) | L86: Да, применяю как основу для проектирования | M86: Владею на базовом уровне | N86: Иногда, для отдельных дисциплин | O86: 0 | P86: 0 | Q86: 1 | R86: 1 | S86: 0 | T86: 0 | U86: 1 | V86: 1 | W86: 4 | X86: 4 | Y86: 3 | Z86: 4 | AA86: 2 | AB86: 2 | AC86: 3 | AD86: 1 | AE86: Да, иногда | AF86: Постановщик задач Методолог (проектирование образовательных результатов и ФОС) | AG86: Более 10 лет | AH86: Углубление знаний о КРМ в ИИ, обучение использованию КРМ в работе, идеи проектного обучения с ИИ | AI86: Модели временных рядов и, возможно, остальные тоже
A87: TRUE | B87: {=_xlfn.XLOOKUP(E87,#REF!,#REF!)} -> #REF! | C87: Екатерина Напеденина | E87: napedenina.ey@rea.ru | F87: 46207.594 | G87: Математический анализ, Теория вероятностей и математическая статистика, Дифференциальные уравнения, Дискретная математика, Математическая логика и теория алгоритмов | H87: Математика / Прикладная математика | I87: Изучал(а) структуру КРМ, но не применял(а) в работе | J87: Профессиональные роли Компетенции в области математических основ ИИ (MF) | L87: Планирую начать использовать в ближайшее время | M87: Не владею, не понимаю, как это делать | N87: Планирую использовать в будущем | O87: 0 | P87: 0 | Q87: 1 | R87: 1 | S87: 0 | T87: 0 | U87: 1 | V87: 1 | W87: 4 | X87: 4 | Y87: 1 | Z87: 2 | AA87: 1 | AB87: 2 | AC87: 3 | AD87: 1 | AE87: Да, иногда | AF87: Методолог (проектирование образовательных результатов и ФОС) | AG87: Более 10 лет | AH87: Углубление знаний о КРМ в ИИ, обучение использованию КРМ в преподавательской деятельности, идеи для проектной работы со студентами, использовании ИИ в преподавательской деятельности | AI87: Пока не решила
A88: TRUE | B88: {=_xlfn.XLOOKUP(E88,#REF!,#REF!)} -> #REF! | C88: Ольга Агарева | E88: oyagareva@mephi.ru | F88: 46207.6 | G88: Теория вероятностей и мат. статистика, Случайные процессы, Дифференциальные уравнения и др. | H88: Математика / Прикладная математика | I88: Слышал(а) о ней, но не изучал(а) подробно | J88: Ни один из разделов не знаком | L88: Нет, никогда не использовал(а) | M88: Владею на базовом уровне | N88: Нет, никогда | O88: 0 | P88: 0 | Q88: 0 | R88: 0 | S88: 0 | T88: 0 | U88: 1 | V88: 1 | W88: 3 | X88: 3 | Y88: 3 | Z88: 2 | AA88: 1 | AB88: 0 | AC88: 0 | AD88: 0 | AE88: Нет, не планирую | AF88: Методолог (проектирование образовательных результатов и ФОС) | AG88: Более 10 лет | AH88: Использование ИИ при подготовке к работе | AI88: Нет
... A91: TRUE | B91: {=_xlfn.XLOOKUP(E91,#REF!,#REF!)} -> #REF! | C91: Анна Матохина | E91: matohina.a.v@yandex.ru | F91: 46207.637 | G91: Компьютерная графика, 2D и 3D моделирование, Нарративный геймдизайн | H91: Информатика / Программирование | I91: Изучал(а) структуру КРМ, но не применял(а) в работе | J91: Профессиональные роли Компетенции в области машинного обучения (ML) Компетенции в области больших языковых моделей (LLM) | L91: Да, применяю как основу для проектирования | M91: Владею на базовом уровне | N91: Да, для всех дисциплин, которые разрабатываю | O91: 2 | P91: 3 | Q91: 3 | R91: 2 | S91: 2 | T91: 2 | U91: 2 | V91: 2 | W91: 3 | X91: 3 | Y91: 3 | Z91: 4 | AA91: 3 | AB91: 3 | AC91: 2 | AD91: 2 | AE91: Да, регулярно | AF91: Постановщик задач Эксперт по содержанию (глубокое знание предметной области ИИ) Методолог (проектирование образовательных результатов и ФОС) | AG91: Более 10 лет | AH91: Изучение инструментов для редизайна дисциплин и актуализация содержания с учетом трансформации ролей, новые форматы оценивания и преподавания, варианты решения проблемы поверхностных знаний (вследствие использовании LLM) | AI91: Компьютерная графика, Нарративный геймдизайн
A92: TRUE | B92: {=_xlfn.XLOOKUP(E92,#REF!,#REF!)} -> #REF! | C92: Наталья Паршукова | E92: parshukovanb@susu.ru | F92: 46207.656 | G92: Программирование на Python программирование на C++ Web-программирование для систем искусственного интеллекта Алгоритмы и структуры данных Основы распределенных и облачных вычислений | H92: Информатика / Программирование | I92: Использую КРМ в своей профессиональной деятельности | J92: Профессиональные роли Компетенции в области машинного обучения (ML) Компетенции в области больших языковых моделей (LLM) Другое | K92: компетенции в области программирования и развертывания систем машинного обучения | L92: Да, применяю как основу для проектирования | M92: Владею на базовом уровне | N92: Да, для всех дисциплин, которые разрабатываю | O92: 2 | P92: 4 | Q92: 4 | R92: 2 | S92: 3 | T92: 2 | U92: 3 | V92: 2 | W92: 4 | X92: 4 | Y92: 3 | Z92: 3 | AA92: 3 | AB92: 2 | AC92: 3 | AD92: 3 | AE92: Да, регулярно | AF92: Постановщик задач Практик-разработчик (код, инструменты, инфраструктура) | AG92: Более 10 лет | AH92: освоение новых компетенций в сфере LLM, глубокого обучения, облачных сервисов по работе с ML моделями. обмен опытом с коллегами по организации проектной работы в связке индустриальный партнер - преподаватель - команда студентов | AI92: Web-программирование для систем искусственного интеллекта
A93: TRUE | B93: {=_xlfn.XLOOKUP(E93,#REF!,#REF!)} -> #REF! | C93: Сергей Девятовский | E93: seregadev86@gmail.com | F93: 46207.664 | G93: Линейная алгебра и обработка данных, Математический анализ, методы оптимизации | H93: Математика / Прикладная математика | I93: Слышал(а) о ней, но не изучал(а) подробно | J93: Компетенции в области математических основ ИИ (MF) Компетенции в области машинного обучения (ML) Компетенции в области глубокого обучения (DL) | L93: Планирую начать использовать в ближайшее время | M93: Владею на базовом уровне | N93: Планирую использовать в будущем | O93: 2 | P93: 4 | Q93: 4 | R93: 3 | S93: 3 | T93: 1 | U93: 2 | V93: 3 | W93: 2 | X93: 2 | Y93: 4 | Z93: 3 | AA93: 4 | AB93: 4 | AC93: 3 | AD93: 3 | AE93: Да, иногда | AF93: Постановщик задач Эксперт по содержанию (глубокое знание предметной области ИИ) Методолог (проектирование образовательных результатов и ФОС) Практик-разработчик (код, инструменты, инфраструктура) Эксперт по КРМ (знание структуры, методик применения) | AG93: Менее 3 лет | AH93: Планирую в результате обучения повысить свои компетенции и навыки в области преподавания предметов, связанных с ИИ. | AI93: Пока что затрудняюсь ответить.
A94: TRUE | B94: {=_xlfn.XLOOKUP(E94,#REF!,#REF!)} -> #REF! | C94: Светлана Артемова | E94: seartemova@fa.ru | F94: 46207.676 | G94: Прикладной Data Science в финтехе, Машинное обучение, Технологии обработки данных | H94: Математика / Прикладная математика | I94: Использую КРМ в своей профессиональной деятельности | J94: Профессиональные роли Компетенции в области математических основ ИИ (MF) Компетенции в области машинного обучения (ML) Компетенции в области больших языковых моделей (LLM) Компетенции в области жизненного цикла систем искусственного интеллекта (FC) | L94: Да, применяю как основу для проектирования | M94: Владею хорошо, могу обучить коллег | N94: Да, для всех дисциплин, которые разрабатываю | O94: 4 | P94: 4 | Q94: 4 | R94: 4 | S94: 4 | T94: 4 | U94: 4 | V94: 4 | W94: 4 | X94: 4 | Y94: 4 | Z94: 4 | AA94: 4 | AB94: 4 | AC94: 4 | AD94: 4 | AE94: Да, регулярно | AF94: Постановщик задач Эксперт по содержанию (глубокое знание предметной области ИИ) Методолог (проектирование образовательных результатов и ФОС) Эксперт по КРМ (знание структуры, методик применения) | AG94: Более 10 лет | AH94: Освоить навыки топ-преподавания ИИ Внедрять КРМ в учебный процесс | AI94: Прикладной Data Science Машинное обучение
A95: TRUE | B95: {=_xlfn.XLOOKUP(E95,#REF!,#REF!)} -> #REF! | C95: Никита Гончаров | E95: goncharov.ns.krm@yandex.ru | F95: 46207.681 | G95: Сбор, анализ и предобработка данных в машинном обучении Базы данных Машинное обучение | H95: Математика / Прикладная математика | I95: Слышал(а) о ней, но не изучал(а) подробно | J95: Компетенции в области математических основ ИИ (MF) Компетенции в области машинного обучения (ML) | L95: Планирую начать использовать в ближайшее время | M95: Владею на базовом уровне | N95: Иногда, для отдельных дисциплин | O95: 3 | P95: 4 | Q95: 4 | R95: 3 | S95: 3 | T95: 3 | U95: 3 | V95: 2 | W95: 3 | X95: 2 | Y95: 2 | Z95: 3 | AA95: 2 | AB95: 4 | AC95: 3 | AD95: 2 | AE95: Нет, но планирую | AF95: Постановщик задач | AG95: 3–6 лет | AH95: 1. Хотелось бы ознакомиться с новыми компетенциями при изучении ИИ для студентов. 2. Разобраться с LLM | AI95: Затрудняюсь ответить.
A96: TRUE | B96: {=_xlfn.XLOOKUP(E96,#REF!,#REF!)} -> #REF! | C96: Станислав Драгунов | E96: dragun.se@yandex.ru | F96: 46207.682 | G96: Робототехника Киберфизические системы Системы автоматизированного проектирования Разработка компьютерных игр | H96: Информатика / Программирование | I96: Слышал(а) о ней, но не изучал(а) подробно | J96: Ни один из разделов не знаком | L96: Планирую начать использовать в ближайшее время | M96: Не владею, не понимаю, как это делать | N96: Иногда, для отдельных дисциплин | O96: 3 | P96: 1 | Q96: 2 | R96: 3 | S96: 2 | T96: 2 | U96: 2 | V96: 3 | W96: 4 | X96: 4 | Y96: 4 | Z96: 4 | AA96: 4 | AB96: 3 | AC96: 2 | AD96: 2 | AE96: Да, регулярно | AF96: Постановщик задач Эксперт по содержанию (глубокое знание предметной области ИИ) Методолог (проектирование образовательных результатов и ФОС) Практик-разработчик (код, инструменты, инфраструктура) | AG96: 7–10 лет | AH96: познакомится ближе с КРМ | AI96: Технологии быстрого прототипирование, Разработка игровых механик, технический геймдизайн.
A97: TRUE | B97: {=_xlfn.XLOOKUP(E97,#REF!,#REF!)} -> #REF! | C97: Виталий Кудинов | E97: v.kudinov@g.nsu.ru | F97: 46207.713 | G97: Введение в проектную деятельность | H97: Компьютерные науки | I97: Слышал(а) о ней, но не изучал(а) подробно | J97: Компетенции в области глубокого обучения (DL) | L97: Планирую начать использовать в ближайшее время | M97: Не владею, не понимаю, как это делать | N97: Нет, никогда | O97: 1 | P97: 1 | Q97: 3 | R97: 2 | S97: 3 | T97: 3 | U97: 2 | V97: 2 | W97: 1 | X97: 0 | Y97: 2 | Z97: 2 | AA97: 2 | AB97: 2 | AC97: 2 | AD97: 3 | AE97: Да, регулярно | AF97: Практик-разработчик (код, инструменты, инфраструктура) | AG97: 3–6 лет | AH97: Повышение квалификации и опыта в разработке программ дисциплин | AI97: -
A98: TRUE | B98: {=_xlfn.XLOOKUP(E98,#REF!,#REF!)} -> #REF! | C98: Надежда Могилевская | E98: broshka2011@yandex.ru | F98: 46207.724 | G98: Теория кодирования (сжатие, помехоустойчивое хранение, распределенное отказоустойчивое хранение) Теория автоматов и формальных языков. | H98: Информатика / Программирование | I98: Нет, совсем не знаком(а) | J98: Ни один из разделов не знаком | L98: Нет, никогда не использовал(а) | M98: Не владею, не понимаю, как это делать | N98: Иногда, для отдельных дисциплин | O98: 2 | P98: 1 | Q98: 1 | R98: 0 | S98: 0 | T98: 0 | U98: 2 | V98: 0 | W98: 2 | X98: 2 | Y98: 1 | Z98: 0 | AA98: 1 | AB98: 2 | AC98: 1 | AD98: 0 | AE98: Нет, но планирую | AF98: Методолог (проектирование образовательных результатов и ФОС) Эксперт по КРМ (знание структуры, методик применения) | AG98: Более 10 лет | AH98: Сменить учебные курсы, которые преподаю на более актуальные и востребованные. Хочется проводить занятия по дисциплинам, необходимость знания которых очевидна для студентов. | AI98: нет
A99: TRUE | B99: {=_xlfn.XLOOKUP(E99,#REF!,#REF!)} -> #REF! | C99: Светлана Крошилина | E99: kroshilina_rzn@mail.ru | F99: 46207.742 | G99: Управление проектами в сфере ИИ | H99: Компьютерные науки | I99: Использую КРМ в своей профессиональной деятельности | J99: Профессиональные роли | L99: Да, применяю как основу для проектирования | M99: Владею на базовом уровне | N99: Да, для всех дисциплин, которые разрабатываю | O99: 4 | P99: 4 | Q99: 0 | R99: 0 | S99: 0 | T99: 0 | U99: 0 | V99: 0 | W99: 4 | X99: 4 | Y99: 4 | Z99: 4 | AA99: 4 | AB99: 4 | AC99: 4 | AD99: 4 | AE99: Да, регулярно | AF99: Постановщик задач Методолог (проектирование образовательных результатов и ФОС) | AG99: Более 10 лет | AH99: 1. Структурированный и готовый к применению документ 2. Практическая применимость 3. Гибкость и вариативность | AI99: Управление проектами в сфере ИИ
A100: TRUE | B100: {=_xlfn.XLOOKUP(E100,#REF!,#REF!)} -> #REF! | C100: Садыков Тимур | E100: sadykov.tm@rea.ru | F100: 46207.747 | G100: Преподавал дисциплину &quot;Математический анализ&quot; в 1 семестре. Планирую преподавать дисциплину &quot;Дифференциальные уравнения&quot; в 4 семестре. | H100: Математика / Прикладная математика | I100: Использую КРМ в своей профессиональной деятельности | J100: Компетенции в области математических основ ИИ (MF) | L100: Да, применяю как основу для проектирования | M100: Владею на базовом уровне | N100: Да, для всех дисциплин, которые разрабатываю | O100: 0 | P100: 2 | Q100: 2 | R100: 1 | S100: 1 | T100: 1 | U100: 1 | V100: 1 | W100: 2 | X100: 2 | Y100: 1 | Z100: 1 | AA100: 0 | AB100: 1 | AC100: 4 | AD100: 1 | AE100: Да, иногда | AF100: Методолог (проектирование образовательных результатов и ФОС) | AG100: Более 10 лет | AH100: Овладеть практическими навыками и применить их для создания учебных материалов, которые я смогу применить в ходе преподавания дисциплины &quot;Дифференциальные уравнения&quot; в следующем учебном году. | AI100: Да. Дисциплина &quot;Дифференциальные уравнения&quot;.
A101: TRUE | B101: {=_xlfn.XLOOKUP(E101,#REF!,#REF!)} -> #REF! | C101: Алексей Прутский | E101: prutskiyalex@yandex.ru | F101: 46207.749 | G101: Технологии компьютерного зрения Администрирование информационных сетей ИИ в робототехнике | H101: Математика / Прикладная математика | I101: Использую КРМ в своей профессиональной деятельности | J101: Компетенции в области жизненного цикла систем искусственного интеллекта (FC) | L101: Планирую начать использовать в ближайшее время | M101: Владею на базовом уровне | N101: Иногда, для отдельных дисциплин | O101: 2 | P101: 2 | Q101: 2 | R101: 2 | S101: 3 | T101: 4 | U101: 2 | V101: 2 | W101: 3 | X101: 3 | Y101: 4 | Z101: 4 | AA101: 3 | AB101: 3 | AC101: 3 | AD101: 2 | AE101: Да, регулярно | AF101: Постановщик задач Методолог (проектирование образовательных результатов и ФОС) | AG101: 7–10 лет | AH101: 1 Познакомиться с опытными педагогами 2 Получить опыт в администрировании систем ИИ современных (серверные решения, MLOPS) 3 Научиться применять современные ИИ инструменты в образовании (как применять правильно) | AI101: ИИ в робототехнике
A102: TRUE | B102: {=_xlfn.XLOOKUP(E102,#REF!,#REF!)} -> #REF! | C102: Александр Крошилин | E102: av_kroshilin@mail.ru | F102: 46207.749 | G102: Рекомендательные системы и системы поддержки принятия решений | H102: Компьютерные науки | I102: Использую КРМ в своей профессиональной деятельности | J102: Профессиональные роли | L102: Да, применяю как основу для проектирования | M102: Владею на базовом уровне | N102: Да, для всех дисциплин, которые разрабатываю | O102: 4 | P102: 4 | Q102: 0 | R102: 0 | S102: 0 | T102: 0 | U102: 0 | V102: 0 | W102: 4 | X102: 4 | Y102: 4 | Z102: 4 | AA102: 4 | AB102: 4 | AC102: 4 | AD102: 4 | AE102: Да, регулярно | AF102: Постановщик задач Методолог (проектирование образовательных результатов и ФОС) | AG102: Более 10 лет | AH102: 1. Полная готовность РПД к использованию. 2. Наличие четких критериев оценки и диагностических материалов | AI102: Рекомендательные системы и системы поддержки принятия решений
A103: TRUE | B103: {=_xlfn.XLOOKUP(E103,#REF!,#REF!)} -> #REF! | C103: Владимир Белов | E103: vvbeloff@yandex.ru | F103: 46207.756 | G103: Проектирование интеллектуальных программных систем Математическая статистика для систем искусственного интеллекта | H103: Компьютерные науки | I103: Использую КРМ в своей профессиональной деятельности | J103: Профессиональные роли Компетенции в области математических основ ИИ (MF) | L103: Да, применяю как основу для проектирования | M103: Владею на базовом уровне | N103: Да, для всех дисциплин, которые разрабатываю | O103: 4 | P103: 3 | Q103: 2 | R103: 2 | S103: 1 | T103: 1 | U103: 1 | V103: 1 | W103: 3 | X103: 3 | Y103: 3 | Z103: 2 | AA103: 1 | AB103: 1 | AC103: 1 | AD103: 0 | AE103: Да, регулярно | AF103: Постановщик задач | AG103: Более 10 лет | AH103: 1. Продвижение компетентности в тех позициях, по которым поставил оценку 0, 1 или 2. 2. Увидеть примеры и получить навык трансформации реальных бизнес-задач в учебные кейсы. 3. Углубить навык «Опыт разработки средств автоматизации для учебных целей» | AI103: Проектирование интеллектуальных программных систем Математическая статистика для систем искусственного интеллекта
A104: TRUE | B104: {=_xlfn.XLOOKUP(E104,#REF!,#REF!)} -> #REF! | C104: Николай Чапкин | E104: nic-ch-work@yandex.ru | F104: 46207.758 | G104: пока не знаю | H104: Математика / Прикладная математика | I104: Нет, совсем не знаком(а) | J104: Ни один из разделов не знаком | L104: Планирую начать использовать в ближайшее время | M104: Не владею, не понимаю, как это делать | N104: Нет, никогда | O104: 4 | P104: 4 | Q104: 2 | R104: 0 | S104: 4 | T104: 4 | U104: 1 | V104: 1 | W104: 4 | X104: 4 | Y104: 4 | Z104: 4 | AA104: 4 | AB104: 2 | AC104: 0 | AD104: 2 | AE104: Да, регулярно | AF104: Постановщик задач Эксперт по содержанию (глубокое знание предметной области ИИ) Методолог (проектирование образовательных результатов и ФОС) Практик-разработчик (код, инструменты, инфраструктура) Эксперт по КРМ (знание структуры, методик применения) | AG104: Более 10 лет | AH104: сложно сказать | AI104: сложно сказать
... A133: TRUE | B133: {=_xlfn.XLOOKUP(E133,#REF!,#REF!)} -> #REF! | C133: Баев Алексей | E133: baevaa@volgatech.net | F133: 46208.509 | G133: Машинно-зависимые языки программирования, Основы машинного обучения | H133: Информатика / Программирование | I133: Использую КРМ в своей профессиональной деятельности | J133: Компетенции в области машинного обучения (ML) Компетенции в области глубокого обучения (DL) Компетенции в области больших языковых моделей (LLM) | L133: Планирую начать использовать в ближайшее время | M133: Владею на базовом уровне | N133: Иногда, для отдельных дисциплин | O133: 3 | P133: 2 | Q133: 3 | R133: 4 | S133: 4 | T133: 3 | U133: 3 | V133: 3 | W133: 4 | X133: 4 | Y133: 4 | Z133: 4 | AA133: 4 | AB133: 4 | AC133: 4 | AD133: 4 | AE133: Да, регулярно | AF133: Постановщик задач Методолог (проектирование образовательных результатов и ФОС) | AG133: Более 10 лет | AH133: Примеры разработки РПД | AI133: Основы машинного обучения
A134: TRUE | B134: {=_xlfn.XLOOKUP(E134,#REF!,#REF!)} -> #REF! | C134: Виктория Шевченко | E134: vishevchenko@sevsu.ru | F134: 46208.515 | G134: 1. Цифровые технологии и медиабезопасность 2. Прикладная математика в ИИ 3. Мультиагентное моделирование | H134: Компьютерные науки | I134: Использую КРМ в своей профессиональной деятельности | J134: Профессиональные роли Компетенции в области математических основ ИИ (MF) | K134: - | L134: Да, применяю как основу для проектирования | M134: Владею хорошо, могу обучить коллег | N134: Да, для всех дисциплин, которые разрабатываю | O134: 4 | P134: 3 | Q134: 3 | R134: 3 | S134: 3 | T134: 2 | U134: 3 | V134: 3 | W134: 4 | X134: 4 | Y134: 4 | Z134: 4 | AA134: 4 | AB134: 3 | AC134: 3 | AD134: 3 | AE134: Да, регулярно | AF134: Постановщик задач Методолог (проектирование образовательных результатов и ФОС) | AG134: Более 10 лет | AH134: - новые технологии использования ИИ в образовательном процессе - новые технологи поддержки преподавателей разработчиков РПД, УМК, ФОС - практикоориентированность | AI134: Мультиагентные системы и ИИ
A135: TRUE | B135: {=_xlfn.XLOOKUP(E135,#REF!,#REF!)} -> #REF! | C135: Максим Калинин | E135: max@ibks.spbstu.ru | F135: 46208.524 | G135: Технологии машинного обучения в кибербезопасности | H135: Компьютерные науки | I135: Слышал(а) о ней, но не изучал(а) подробно | J135: Профессиональные роли | L135: Нет, никогда не использовал(а) | M135: Не владею, не понимаю, как это делать | N135: Нет, никогда | O135: 4 | P135: 1 | Q135: 1 | R135: 1 | S135: 1 | T135: 1 | U135: 1 | V135: 1 | W135: 4 | X135: 4 | Y135: 4 | Z135: 4 | AA135: 4 | AB135: 4 | AC135: 4 | AD135: 4 | AE135: Да, регулярно | AF135: Постановщик задач Методолог (проектирование образовательных результатов и ФОС) | AG135: Более 10 лет | AH135: Приобретение новых знаний. | AI135: --
A136: TRUE | B136: {=_xlfn.XLOOKUP(E136,#REF!,#REF!)} -> #REF! | C136: Андрей Фролов | E136: a.frolov.kpfu@gmail.com | F136: 46208.528 | G136: Введение в комбинаторику и дискретную математику | H136: Математика / Прикладная математика | I136: Слышал(а) о ней, но не изучал(а) подробно | J136: Компетенции в области математических основ ИИ (MF) | L136: Нет, никогда не использовал(а) | M136: Владею на базовом уровне | N136: Нет, никогда | O136: 1 | P136: 3 | Q136: 3 | R136: 0 | S136: 0 | T136: 0 | U136: 0 | V136: 2 | W136: 4 | X136: 4 | Y136: 1 | Z136: 1 | AA136: 3 | AB136: 0 | AC136: 0 | AD136: 0 | AE136: Нет, не планирую | AF136: Постановщик задач Методолог (проектирование образовательных результатов и ФОС) | AG136: Более 10 лет | AH136: Ничего жду | AI136: нет, ничего не хочу
A137: TRUE | B137: {=_xlfn.XLOOKUP(E137,#REF!,#REF!)} -> #REF! | C137: Анастасия Горбунова | E137: avgorbunova@bk.ru | F137: 46208.532 | G137: Теория вероятностей и математическая статистика | H137: Математика / Прикладная математика | I137: Слышал(а) о ней, но не изучал(а) подробно | J137: Ни один из разделов не знаком | L137: Нет, никогда не использовал(а) | M137: Не владею, не понимаю, как это делать | N137: Нет, никогда | O137: 0 | P137: 0 | Q137: 3 | R137: 2 | S137: 0 | T137: 0 | U137: 3 | V137: 1 | W137: 4 | X137: 4 | Y137: 0 | Z137: 2 | AA137: 0 | AB137: 0 | AC137: 0 | AD137: 0 | AE137: Нет, но планирую | AF137: Постановщик задач | AG137: Более 10 лет | AH137: Разработка средств автоматизации для учебных целей | AI137: Теория вероятностей и математическая статистика
A138: TRUE | B138: {=_xlfn.XLOOKUP(E138,#REF!,#REF!)} -> #REF! | C138: Станислав Кирпиченко | E138: stasychbr@mail.ru | F138: 46208.54 | G138: Структуры данных, Алгоритмы и программирование, Объектно-ориентированное программирование | H138: Математика / Прикладная математика | I138: Нет, совсем не знаком(а) | J138: Ни один из разделов не знаком | L138: Нет, никогда не использовал(а) | M138: Не владею, не понимаю, как это делать | N138: Нет, никогда | O138: 2 | P138: 3 | Q138: 4 | R138: 4 | S138: 4 | T138: 3 | U138: 2 | V138: 3 | W138: 0 | X138: 0 | Y138: 2 | Z138: 2 | AA138: 1 | AB138: 2 | AC138: 0 | AD138: 0 | AE138: Нет, не планирую | AF138: Эксперт по содержанию (глубокое знание предметной области ИИ) Практик-разработчик (код, инструменты, инфраструктура) | AG138: Менее 3 лет | AH138: Получить опыт применения ИИ в преподавании классических курсов по программированию; сформировать представление о нормативных и организационных аспектах использования ИИ в высшем образовании. | AI138: Алгоритмы и программирование, Объектно-ориентированное программирование
A139: TRUE | B139: {=_xlfn.XLOOKUP(E139,#REF!,#REF!)} -> #REF! | C139: Вера Акиньшина | E139: ak-vera@yandex.ru | F139: 46208.551 | G139: Интеллектуальные методы оптимизации, ИИ ФинТех, Современные методы фронтирных исследований ИИ | H139: Математика / Прикладная математика | I139: Использую КРМ в своей профессиональной деятельности | J139: Профессиональные роли Компетенции в области математических основ ИИ (MF) Компетенции в области машинного обучения (ML) Компетенции в области больших языковых моделей (LLM) | L139: Да, применяю как основу для проектирования | M139: Владею на базовом уровне | N139: Иногда, для отдельных дисциплин | O139: 3 | P139: 4 | Q139: 2 | R139: 2 | S139: 2 | T139: 0 | U139: 4 | V139: 3 | W139: 4 | X139: 3 | Y139: 4 | Z139: 3 | AA139: 2 | AB139: 0 | AC139: 2 | AD139: 3 | AE139: Да, регулярно | AF139: Постановщик задач Эксперт по КРМ (знание структуры, методик применения) | AG139: Более 10 лет | AH139: Увидеть примеры реализации кейсов от индустриальных партнеров на практике, улучшить компетенции в области больших языковых моделей (LLM) и в области глубокого обучения | AI139: Интеллектуальные методы оптимизации, ИИ ФинТех, Современные методы фронтирных исследований ИИ
A140: TRUE | B140: {=_xlfn.XLOOKUP(E140,#REF!,#REF!)} -> #REF! | C140: Николай Шенец | E140: shenets_nn@ibks.spbstu.ru | F140: 46208.553 | G140: Дискретная математика Криптографические методы защиты информации Быстрые вычислительные алгоритмы | H140: Математика / Прикладная математика | I140: Слышал(а) о ней, но не изучал(а) подробно | J140: Компетенции в области математических основ ИИ (MF) Компетенции в области машинного обучения (ML) | L140: Нет, никогда не использовал(а) | M140: Не владею, не понимаю, как это делать | N140: Нет, никогда | O140: 1 | P140: 1 | Q140: 0 | R140: 0 | S140: 0 | T140: 0 | U140: 0 | V140: 0 | W140: 4 | X140: 3 | Y140: 3 | Z140: 3 | AA140: 2 | AB140: 0 | AC140: 0 | AD140: 3 | AE140: Да, иногда | AF140: Постановщик задач Методолог (проектирование образовательных результатов и ФОС) | AG140: Более 10 лет | AH140: 1. Понимание и практические навыки использования ИИ, в том числе, для целей образовательного процесса. 2. Опыт работы в команде для конкретных прикладных задач (не НИР/НИОКР). | AI140: Возможно, для магистров дисциплину &quot;Криптографическая защита информации&quot;, но не уверен, что ИИ там необходимо.
A141: TRUE | B141: {=_xlfn.XLOOKUP(E141,#REF!,#REF!)} -> #REF! | C141: Ярослав Холодов | E141: kholodov@crec.mipt.ru | F141: 46208.572 | G141: Вычислительная линейная алгебра, вычислительная математика, Многомерный анализ данных. | H141: Математика / Прикладная математика | I141: Слышал(а) о ней, но не изучал(а) подробно | J141: Компетенции в области математических основ ИИ (MF) Компетенции в области машинного обучения (ML) | L141: Нет, никогда не использовал(а) | M141: Не владею, не понимаю, как это делать | N141: Нет, никогда | O141: 0 | P141: 0 | Q141: 2 | R141: 1 | S141: 0 | T141: 0 | U141: 2 | V141: 1 | W141: 3 | X141: 2 | Y141: 2 | Z141: 3 | AA141: 2 | AB141: 2 | AC141: 0 | AD141: 0 | AE141: Да, регулярно | AF141: Постановщик задач Методолог (проектирование образовательных результатов и ФОС) | AG141: Более 10 лет | AH141: Автоматизация разрабатываемых учебных материалов. | AI141: Вычислительная математика
A142: TRUE | B142: {=_xlfn.XLOOKUP(E142,#REF!,#REF!)} -> #REF! | C142: Надежда Муравьева | E142: muravevanv@susu.ru | F142: 46208.582 | G142: Методы оптимизации | H142: Математика / Прикладная математика | I142: Слышал(а) о ней, но не изучал(а) подробно | J142: Компетенции в области математических основ ИИ (MF) | L142: Планирую начать использовать в ближайшее время | M142: Не владею, не понимаю, как это делать | N142: Иногда, для отдельных дисциплин | O142: 0 | P142: 0 | Q142: 0 | R142: 0 | S142: 0 | T142: 0 | U142: 0 | V142: 0 | W142: 3 | X142: 3 | Y142: 2 | Z142: 2 | AA142: 0 | AB142: 0 | AC142: 0 | AD142: 0 | AE142: Нет, но планирую | AF142: Эксперт по КРМ (знание структуры, методик применения) | AG142: Более 10 лет | AH142: Научиться проектировать программы на основе КРМ, внедрять проектные и соревновательные программы в учебную деятельность студентов. | AI142: Хотела разработать и актуализировать в рамках проектной работы дисциплину методы оптимизации.
A143: TRUE | B143: {=_xlfn.XLOOKUP(E143,#REF!,#REF!)} -> #REF! | C143: Дина Стягун | E143: dina2011@mail.ru | F143: 46208.584 | G143: Векторная алгебра | H143: Математика / Прикладная математика | I143: Слышал(а) о ней, но не изучал(а) подробно | J143: Ни один из разделов не знаком | L143: Планирую начать использовать в ближайшее время | M143: Владею на базовом уровне | N143: Планирую использовать в будущем | O143: 0 | P143: 0 | Q143: 2 | R143: 2 | S143: 0 | T143: 0 | U143: 0 | V143: 1 | W143: 2 | X143: 2 | Y143: 1 | Z143: 1 | AA143: 0 | AB143: 0 | AC143: 0 | AD143: 1 | AE143: Нет, но планирую | AF143: Постановщик задач Методолог (проектирование образовательных результатов и ФОС) | AG143: Более 10 лет | AH143: Получиьь большее представление о работе с большими данными | AI143: Системы искусственного интеллекта и анализ данных в профессиональной среде
A144: TRUE | B144: {=_xlfn.XLOOKUP(E144,#REF!,#REF!)} -> #REF! | C144: Елена Сафонова | E144: safonova_h@mail.ru | F144: 46208.594 | G144: Промпт-инжиниринг, Машинное обучение, Компьютерная лингвистика, Диалоговые системы, Системы искусственного интеллекта | H144: Компьютерные науки | I144: Изучал(а) структуру КРМ, но не применял(а) в работе | J144: Профессиональные роли Компетенции в области машинного обучения (ML) Компетенции в области больших языковых моделей (LLM) | L144: Планирую начать использовать в ближайшее время | M144: Владею на базовом уровне | N144: Планирую использовать в будущем | O144: 3 | P144: 1 | Q144: 2 | R144: 2 | S144: 2 | T144: 2 | U144: 2 | V144: 3 | W144: 4 | X144: 4 | Y144: 3 | Z144: 3 | AA144: 2 | AB144: 2 | AC144: 4 | AD144: 3 | AE144: Да, иногда | AF144: Методолог (проектирование образовательных результатов и ФОС) | AG144: 3–6 лет | AH144: 1. Навых разработкк структуры и содержания РПД с учетом проф. ролей. 2. Навык разработки ФОС с учетом проф. ролей. | AI144: Машинное обучение, Промпт-инжиниринг
A145: TRUE | B145: {=_xlfn.XLOOKUP(E145,#REF!,#REF!)} -> #REF! | C145: Александр Бастрычкин | E145: a_s_bas@mail.ru | F145: 46208.606 | G145: Основы алгоритмизации и объектно-ориентированное программирование Промышленная разработка программного обеспечения на Java Промышленное программирование на Java | H145: Компьютерные науки | I145: Изучал(а) структуру КРМ, но не применял(а) в работе | J145: Другое | K145: Компетенции в области языков программирования (PL) | L145: Да, применяю как основу для проектирования | M145: Владею на базовом уровне | N145: Иногда, для отдельных дисциплин | O145: 2 | P145: 2 | Q145: 4 | R145: 1 | S145: 3 | T145: 2 | U145: 1 | V145: 1 | W145: 3 | X145: 3 | Y145: 2 | Z145: 3 | AA145: 2 | AB145: 3 | AC145: 3 | AD145: 2 | AE145: Да, регулярно | AF145: Методолог (проектирование образовательных результатов и ФОС) Практик-разработчик (код, инструменты, инфраструктура) | AG145: 7–10 лет | AH145: Получение знаний в области ИИ Получение знаний и опыта в преподавании ИИ-дисциплин | AI145: Промышленная разработка программного обеспечения на Java Промышленное программирование на Java Учебная практика
A146: TRUE | B146: {=_xlfn.XLOOKUP(E146,#REF!,#REF!)} -> #REF! | C146: Артем Титов | E146: a.titov@rgau-msha.ru | F146: 46208.612 | G146: Алгоритмизация и программирование Технологии хранения и управления данными в АПК Компьютерное зрение в сельском хозяйстве Программирование на языке С++ | H146: Информатика / Программирование | I146: Использую КРМ в своей профессиональной деятельности | J146: Компетенции в области математических основ ИИ (MF) Компетенции в области машинного обучения (ML) Компетенции в области глубокого обучения (DL) Компетенции в области жизненного цикла систем искусственного интеллекта (FC) | L146: Да, применяю как основу для проектирования | M146: Владею на базовом уровне | N146: Да, для всех дисциплин, которые разрабатываю | O146: 2 | P146: 3 | Q146: 3 | R146: 2 | S146: 0 | T146: 0 | U146: 1 | V146: 1 | W146: 3 | X146: 3 | Y146: 2 | Z146: 2 | AA146: 1 | AB146: 0 | AC146: 2 | AD146: 3 | AE146: Да, иногда | AF146: Постановщик задач Эксперт по содержанию (глубокое знание предметной области ИИ) | AG146: 3–6 лет | AH146: Углубление навыков составления и адаптации под дисциплину кейс-задач Изучение современных технологий автоматизации проверки практических работ | AI146: Компьютерное зрение в сельском хозяйстве Технологии хранения и управления данными в АПК Программирование на языке С++
A147: TRUE | B147: {=_xlfn.XLOOKUP(E147,#REF!,#REF!)} -> #REF! | C147: Дарья Титова | E147: d.gorshkova@rgau-msha.ru | F147: 46208.612 | G147: Технологии хранения и управления данными в АПК, Операционные системы, | H147: Информатика / Программирование | I147: Использую КРМ в своей профессиональной деятельности | J147: Профессиональные роли Компетенции в области машинного обучения (ML) Компетенции в области больших языковых моделей (LLM) | L147: Да, применяю как основу для проектирования | M147: Владею на базовом уровне | N147: Да, для всех дисциплин, которые разрабатываю | O147: 2 | P147: 3 | Q147: 2 | R147: 2 | S147: 0 | T147: 0 | U147: 1 | V147: 1 | W147: 3 | X147: 3 | Y147: 2 | Z147: 1 | AA147: 1 | AB147: 0 | AC147: 2 | AD147: 3 | AE147: Нет, но планирую | AF147: Постановщик задач | AG147: 3–6 лет | AH147: Углубить знания в области применения современных практик преподавания дисциплин, направленных на развитие компетенций топ-уровня. Изучение современных технологий автоматизации проверки практических работ. | AI147: Технологии хранения и управления данными в АПК
A148: TRUE | B148: {=_xlfn.XLOOKUP(E148,#REF!,#REF!)} -> #REF! | C148: Станислав Ким | E148: codeilece@gmail.com | F148: 46208.613 | G148: Методы оптимизации; Машинное обучение; Алгоритмы и структуры данных; Временные ряды; Теория вероятностей; Математическая статистика; | H148: Математика / Прикладная математика | I148: Нет, совсем не знаком(а) | J148: Компетенции в области математических основ ИИ (MF) Компетенции в области машинного обучения (ML) | L148: Нет, никогда не использовал(а) | M148: Владею на базовом уровне | N148: Нет, никогда | O148: 2 | P148: 3 | Q148: 4 | R148: 4 | S148: 4 | T148: 3 | U148: 3 | V148: 3 | W148: 1 | X148: 0 | Y148: 3 | Z148: 3 | AA148: 4 | AB148: 1 | AC148: 1 | AD148: 1 | AE148: Да, иногда | AF148: Постановщик задач Практик-разработчик (код, инструменты, инфраструктура) | AG148: 3–6 лет | AH148: Понять что такое КРМ и зачем это нужно Лучше разобраться в темах, понять где мои знания не корректны/не полные Попробовать что-то новое | AI148: Не знаю :( Методы оптимизации может быть
A149: TRUE | B149: {=_xlfn.XLOOKUP(E149,#REF!,#REF!)} -> #REF! | C149: Александр Золотарев | E149: amzolotarev@mephi.ru | F149: 46208.619 | G149: Компьютерное зрение | H149: Математика / Прикладная математика | I149: Нет, совсем не знаком(а) | J149: Компетенции в области математических основ ИИ (MF) Компетенции в области машинного обучения (ML) Компетенции в области глубокого обучения (DL) | L149: Нет, никогда не использовал(а) | M149: Не владею, не понимаю, как это делать | N149: Нет, никогда | O149: 0 | P149: 0 | Q149: 3 | R149: 4 | S149: 4 | T149: 3 | U149: 3 | V149: 2 | W149: 3 | X149: 3 | Y149: 3 | Z149: 3 | AA149: 3 | AB149: 4 | AC149: 4 | AD149: 4 | AE149: Да, регулярно | AF149: Постановщик задач Эксперт по содержанию (глубокое знание предметной области ИИ) | AG149: 3–6 лет | AH149: - | AI149: Компьютерное зрение
A150: TRUE | B150: {=_xlfn.XLOOKUP(E150,#REF!,#REF!)} -> #REF! | C150: Наталья Трачева | E150: n.tracheva@g.nsu.ru | F150: 46208.636 | G150: Теория вероятностей и математическая статистика, Методы Монте-Карло. | H150: Математика / Прикладная математика | I150: Нет, совсем не знаком(а) | J150: Ни один из разделов не знаком | L150: Нет, никогда не использовал(а) | M150: Не владею, не понимаю, как это делать | N150: Нет, никогда | O150: 0 | P150: 0 | Q150: 1 | R150: 0 | S150: 0 | T150: 0 | U150: 1 | V150: 0 | W150: 2 | X150: 2 | Y150: 1 | Z150: 2 | AA150: 0 | AB150: 0 | AC150: 0 | AD150: 0 | AE150: Да, регулярно | AF150: Постановщик задач | AG150: 7–10 лет | AH150: Понять как можно связать фундаментальные математические дисциплины с ИИ. Освоить методологию КРМ. Найти практические задачи для применения методов Монте-Карло в реальных задачах машинного обучения для их интеграции в учебный процесс. | AI150: Методы Монте-Карло в машинном обучении
A151: TRUE | B151: {=_xlfn.XLOOKUP(E151,#REF!,#REF!)} -> #REF! | C151: Софья Семенова | E151: s.semenova@rgau-msha.ru | F151: 46208.637 | G151: Математическая статистика Программирование на языке Python Операционные системы | H151: Компьютерные науки | I151: Изучал(а) структуру КРМ, но не применял(а) в работе | J151: Профессиональные роли Компетенции в области математических основ ИИ (MF) Компетенции в области машинного обучения (ML) | L151: Да, применяю как основу для проектирования | M151: Владею на базовом уровне | N151: Иногда, для отдельных дисциплин | O151: 3 | P151: 1 | Q151: 3 | R151: 3 | S151: 1 | T151: 1 | U151: 3 | V151: 3 | W151: 4 | X151: 4 | Y151: 3 | Z151: 4 | AA151: 2 | AB151: 2 | AC151: 4 | AD151: 3 | AE151: Да, регулярно | AF151: Постановщик задач Методолог (проектирование образовательных результатов и ФОС) | AG151: Менее 3 лет | AH151: Совершенствование навыков разработки и проектирования образовательных программ топ-ИИ уровня | AI151: Программирование на языке Python
A152: TRUE | B152: {=_xlfn.XLOOKUP(E152,#REF!,#REF!)} -> #REF! | C152: Артем Ветошкин | E152: vetoshkin@rgau-msha.ru | F152: 46208.637 | G152: Программирование на языке Python, Основы ИИ в АПК, Математическая статистика | H152: Компьютерные науки | I152: Участвовал(а) в разработке или доработке КРМ | J152: Профессиональные роли Компетенции в области математических основ ИИ (MF) Компетенции в области машинного обучения (ML) | L152: Да, применяю как основу для проектирования | M152: Владею на базовом уровне | N152: Иногда, для отдельных дисциплин | O152: 2 | P152: 2 | Q152: 4 | R152: 4 | S152: 1 | T152: 1 | U152: 4 | V152: 3 | W152: 4 | X152: 4 | Y152: 3 | Z152: 4 | AA152: 2 | AB152: 2 | AC152: 4 | AD152: 3 | AE152: Да, регулярно | AF152: Методолог (проектирование образовательных результатов и ФОС) | AG152: Менее 3 лет | AH152: Совершенствование навыков разработки и проектирования образовательных программ топ-ИИ уровня | AI152: Программирование на языке Python
A153: TRUE | B153: {=_xlfn.XLOOKUP(E153,#REF!,#REF!)} -> #REF! | C153: Константин Жуйков | E153: zhuykov-kn@rudn.ru | F153: 46208.649 | G153: Линейная алгебра и аналитическая геометрия, математический анализ, теория вероятностей, дифференциальные уравнения, методы оптимизации | H153: Математика / Прикладная математика | I153: Слышал(а) о ней, но не изучал(а) подробно | J153: Компетенции в области математических основ ИИ (MF) Компетенции в области машинного обучения (ML) Компетенции в области глубокого обучения (DL) | L153: Нет, никогда не использовал(а) | M153: Не владею, не понимаю, как это делать | N153: Нет, никогда | O153: 0 | P153: 0 | Q153: 3 | R153: 2 | S153: 2 | T153: 1 | U153: 0 | V153: 2 | W153: 1 | X153: 1 | Y153: 1 | Z153: 1 | AA153: 1 | AB153: 1 | AC153: 1 | AD153: 0 | AE153: Нет, не планирую | AF153: Эксперт по содержанию (глубокое знание предметной области ИИ) Практик-разработчик (код, инструменты, инфраструктура) | AG153: 3–6 лет | AH153: Получить опыт использования КРМ в разработке образовательных программ. Улучшить практические навыки | AI153: нет
A154: TRUE | B154: {=_xlfn.XLOOKUP(E154,#REF!,#REF!)} -> #REF! | C154: Игорь Козулин | E154: i.kozulin@g.nsu.ru | F154: 46208.653 | G154: Цифровая обработка сигналов. | H154: Математика / Прикладная математика | I154: Нет, совсем не знаком(а) | J154: Ни один из разделов не знаком | L154: Нет, никогда не использовал(а) | M154: Не владею, не понимаю, как это делать | N154: Иногда, для отдельных дисциплин | O154: 2 | P154: 0 | Q154: 2 | R154: 2 | S154: 1 | T154: 1 | U154: 1 | V154: 2 | W154: 3 | X154: 3 | Y154: 2 | Z154: 2 | AA154: 1 | AB154: 1 | AC154: 3 | AD154: 2 | AE154: Нет, не планирую | AF154: Эксперт по содержанию (глубокое знание предметной области ИИ) | AG154: 7–10 лет | AH154: Освоить методы использования ИИ в преподавании | AI154: нет
A155: TRUE | B155: {=_xlfn.XLOOKUP(E155,#REF!,#REF!)} -> #REF! | C155: Замира Холматова | E155: z.kholmatova@innopolis.university | F155: 46208.659 | G155: - Теория вероятностей - Математическая статистика - Прикладная статистика в анализе данных | H155: Математика / Прикладная математика | I155: Слышал(а) о ней, но не изучал(а) подробно | J155: Компетенции в области математических основ ИИ (MF) Компетенции в области больших языковых моделей (LLM) | L155: Планирую начать использовать в ближайшее время | M155: Владею на базовом уровне | N155: Планирую использовать в будущем | O155: 0 | P155: 2 | Q155: 3 | R155: 4 | S155: 3 | T155: 2 | U155: 2 | V155: 3 | W155: 3 | X155: 3 | Y155: 3 | Z155: 4 | AA155: 3 | AB155: 3 | AC155: 2 | AD155: 3 | AE155: Да, иногда | AF155: Постановщик задач Эксперт по содержанию (глубокое знание предметной области ИИ) Практик-разработчик (код, инструменты, инфраструктура) | AG155: 3–6 лет | AH155: - формирование целостной структуры курса - освоение методик преподавания на ИИ на топ-уровне | AI155: - Прикладная статистика в анализе данных
A156: TRUE | B156: {=_xlfn.XLOOKUP(E156,#REF!,#REF!)} -> #REF! | C156: Екатерина Казаковцева | E156: vivkaterina@mail.ru | F156: 46208.665 | G156: Введение в специальность, Технологии компьютерного зрения, Математические модели нейронных сетей | H156: Математика / Прикладная математика | I156: Использую КРМ в своей профессиональной деятельности | J156: Профессиональные роли Компетенции в области машинного обучения (ML) Компетенции в области глубокого обучения (DL) | L156: Да, применяю как основу для проектирования | M156: Владею на базовом уровне | N156: Да, для всех дисциплин, которые разрабатываю | O156: 1 | P156: 2 | Q156: 3 | R156: 3 | S156: 2 | T156: 0 | U156: 1 | V156: 3 | W156: 3 | X156: 3 | Y156: 2 | Z156: 1 | AA156: 1 | AB156: 1 | AC156: 3 | AD156: 2 | AE156: Да, иногда | AF156: Эксперт по содержанию (глубокое знание предметной области ИИ) Эксперт по КРМ (знание структуры, методик применения) | AG156: Более 10 лет | AH156: Прокачать навыки работы с КРМ, актуализировать знания в сфере ии | AI156: Нет
A157: TRUE | B157: {=_xlfn.XLOOKUP(E157,#REF!,#REF!)} -> #REF! | C157: Виталий Емельянов | E157: v.yemelyanov@gmail.com | F157: 46208.676 | G157: Технологии обработки данных | H157: Информатика / Программирование | I157: Слышал(а) о ней, но не изучал(а) подробно | J157: Компетенции в области машинного обучения (ML) Компетенции в области жизненного цикла систем искусственного интеллекта (FC) | L157: Планирую начать использовать в ближайшее время | M157: Владею на базовом уровне | N157: Иногда, для отдельных дисциплин | O157: 4 | P157: 2 | Q157: 2 | R157: 3 | S157: 1 | T157: 1 | U157: 1 | V157: 1 | W157: 4 | X157: 4 | Y157: 4 | Z157: 3 | AA157: 2 | AB157: 1 | AC157: 4 | AD157: 2 | AE157: Да, иногда | AF157: Постановщик задач Методолог (проектирование образовательных результатов и ФОС) | AG157: Более 10 лет | AH157: - | AI157: -
... A163: TRUE | B163: {=_xlfn.XLOOKUP(E163,#REF!,#REF!)} -> #REF! | C163: Василий Борисов | E163: funkyvas@ya.ru | F163: 46208.774 | G163: Введение в инженерную деятельность Современные цифровые инструменты научного исследования Научный семинар | H163: Компьютерные науки | I163: Изучал(а) структуру КРМ, но не применял(а) в работе | J163: Профессиональные роли | L163: Да, применяю как основу для проектирования | M163: Владею на базовом уровне | N163: Иногда, для отдельных дисциплин | O163: 1 | P163: 1 | Q163: 2 | R163: 2 | S163: 2 | T163: 1 | U163: 2 | V163: 2 | W163: 3 | X163: 3 | Y163: 3 | Z163: 4 | AA163: 2 | AB163: 3 | AC163: 3 | AD163: 2 | AE163: Да, регулярно | AF163: Постановщик задач Методолог (проектирование образовательных результатов и ФОС) | AG163: Более 10 лет | AH163: Узнать новое о КРМ Получить опыт командной работы Разработать задел для образовательных материалов в новом семестре | AI163: Современные цифровые инструменты научного исследования
A164: TRUE | B164: {=_xlfn.XLOOKUP(E164,#REF!,#REF!)} -> #REF! | C164: Nikita Andriyanov | E164: naandriyanov@fa.ru | F164: 46208.774 | G164: а) Математика искусственного интеллекта б) Введение в искусственный интеллект | H164: Компьютерные науки | I164: Использую КРМ в своей профессиональной деятельности | J164: Компетенции в области машинного обучения (ML) Компетенции в области глубокого обучения (DL) | K164: Составлял РПД с компетенциями ML и DL | L164: Да, применяю как основу для проектирования | M164: Владею на базовом уровне | N164: Планирую использовать в будущем | O164: 1 | P164: 2 | Q164: 3 | R164: 4 | S164: 2 | T164: 1 | U164: 1 | V164: 3 | W164: 4 | X164: 3 | Y164: 2 | Z164: 3 | AA164: 3 | AB164: 2 | AC164: 2 | AD164: 1 | AE164: Да, иногда | AF164: Эксперт по содержанию (глубокое знание предметной области ИИ) Методолог (проектирование образовательных результатов и ФОС) Практик-разработчик (код, инструменты, инфраструктура) | AG164: Более 10 лет | AH164: А) Актуализация тематик РПД в соответствии с КРМ Б) Получение навыков разработки проектных заданий В) Знакомство с экспертами и коллегами, в том числе с практиками | AI164: А) Математические основы ML (переход от регрессии к классификации и кластеризационные задачи с точки зрения математики) Б) Математические основы DL (моделирование перспетронов, сверток и трансформеров)
A165: TRUE | B165: {=_xlfn.XLOOKUP(E165,#REF!,#REF!)} -> #REF! | C165: Михаил Сухов | E165: sukhovm@susu.ru | F165: 46208.783 | G165: Социальные, правовые и этические вопросы искусственного интеллекта; Программная инженерия; Управление ИТ проектами; Тестирование ПО | H165: Информатика / Программирование | I165: Слышал(а) о ней, но не изучал(а) подробно | J165: Компетенции в области машинного обучения (ML) Компетенции в области жизненного цикла систем искусственного интеллекта (FC) | L165: Да, применяю как основу для проектирования | M165: Владею на базовом уровне | N165: Да, для всех дисциплин, которые разрабатываю | O165: 2 | P165: 2 | Q165: 3 | R165: 3 | S165: 1 | T165: 1 | U165: 1 | V165: 1 | W165: 3 | X165: 3 | Y165: 2 | Z165: 2 | AA165: 1 | AB165: 2 | AC165: 3 | AD165: 2 | AE165: Нет, но планирую | AF165: Постановщик задач Эксперт по КРМ (знание структуры, методик применения) | AG165: Более 10 лет | AH165: Умение проектировать рабочие программы с применением компетентностно-ролевой модели | AI165: Программная инженерия; Управление ИТ проектами.
A166: TRUE | B166: {=_xlfn.XLOOKUP(E166,#REF!,#REF!)} -> #REF! | C166: Римма Горохова | E166: rigorokhova@fa.ru | F166: 46208.786 | G166: Практикум по программированию Алгоритмы и структуры данных | H166: Информатика / Программирование | I166: Использую КРМ в своей профессиональной деятельности | J166: Профессиональные роли Компетенции в области математических основ ИИ (MF) | L166: Да, применяю как основу для проектирования | M166: Владею на базовом уровне | N166: Да, для всех дисциплин, которые разрабатываю | O166: 1 | P166: 1 | Q166: 4 | R166: 1 | S166: 0 | T166: 0 | U166: 1 | V166: 0 | W166: 3 | X166: 3 | Y166: 3 | Z166: 3 | AA166: 1 | AB166: 1 | AC166: 1 | AD166: 1 | AE166: Да, регулярно | AF166: Методолог (проектирование образовательных результатов и ФОС) | AG166: Более 10 лет | AH166: Формирование целостной архитектуры курса «под ключ». Внедрение актуальных индустриальных кейсов и стеков в учебный процесс. Разработка системы оценки проектно-исследовательских компетенций. | AI166: Практикум по программированию Алгоритмы и структуры данных Введение в искусственный интеллект Математика искусственного интеллекта
A167: TRUE | B167: {=_xlfn.XLOOKUP(E167,#REF!,#REF!)} -> #REF! | C167: Александр Свиридов | E167: asviridov@sfedu.ru | F167: 46208.79 | G167: Объектно-ориентированное программирование Инструменты и инженерные практики разработки систем ИИ | H167: Информатика / Программирование | I167: Использую КРМ в своей профессиональной деятельности | J167: Компетенции в области машинного обучения (ML) | L167: Да, применяю как основу для проектирования | M167: Владею на базовом уровне | N167: Иногда, для отдельных дисциплин | O167: 3 | P167: 3 | Q167: 3 | R167: 1 | S167: 2 | T167: 2 | U167: 1 | V167: 1 | W167: 3 | X167: 3 | Y167: 2 | Z167: 3 | AA167: 2 | AB167: 2 | AC167: 2 | AD167: 1 | AE167: Да, иногда | AF167: Постановщик задач Методолог (проектирование образовательных результатов и ФОС) | AG167: Более 10 лет | AH167: Получение навыков по использованию КРМ при разработке или актуализации рабочих программ дисциплин. Ознакомление с методологией внедрения практических кейсов в области ИИ в учебные дисциплины. | AI167: Объектно-ориентированное программирование Инструменты и инженерные практики разработки систем ИИ
A168: TRUE | B168: {=_xlfn.XLOOKUP(E168,#REF!,#REF!)} -> #REF! | C168: Ирина Шумейко | E168: shumeyko-irina-74@yandex.ru | F168: 46208.803 | G168: Теория вероятностей; Математическая статистика; Интеллектуальный анализ данных | H168: Математика / Прикладная математика | I168: Использую КРМ в своей профессиональной деятельности | J168: Профессиональные роли Компетенции в области математических основ ИИ (MF) Компетенции в области машинного обучения (ML) Другое | K168: Работа с данными (BD) - частично (BD-1,2) | L168: Да, применяю как основу для проектирования | M168: Владею на базовом уровне | N168: Иногда, для отдельных дисциплин | O168: 1 | P168: 1 | Q168: 0 | R168: 0 | S168: 0 | T168: 0 | U168: 1 | V168: 1 | W168: 3 | X168: 3 | Y168: 2 | Z168: 2 | AA168: 2 | AB168: 2 | AC168: 2 | AD168: 2 | AE168: Да, иногда | AF168: Методолог (проектирование образовательных результатов и ФОС) | AG168: Более 10 лет | AH168: Надеюсь изучить новые инструменты и получить практические навыки для актуализации компетентностно-ролевой матрицы дисциплины с ранжированием математического аппарата по позициям в ИИ-команде с учетом профиля (в данном случае: «Геоинформационные технологии и 3D-моделирование»). Также планирую в дальнейшем освоить методологию организации сквозного цикла ИИ-проекта (от сбора данных до оценки устойчивости моделей) с опорой на кейсы индустриальных партнеров. В результате предполагаю систематизировать содержание курса и обновить рабочую программу дисциплины, включая тематический план, лабораторный практикум, фонд оценочных средств и проектные задания. | AI168: Интеллектуальный анализ данных (для студентов 3 курса)
A169: TRUE | B169: {=_xlfn.XLOOKUP(E169,#REF!,#REF!)} -> #REF! | C169: Виталий Егунов | E169: vegunov@mail.ru | F169: 46208.812 | G169: Архитектура вычислительных систем Основы системного программного обеспечения Технологии больших данных | H169: Информатика / Программирование | I169: Изучал(а) структуру КРМ, но не применял(а) в работе | J169: Профессиональные роли Компетенции в области машинного обучения (ML) | L169: Да, применяю как основу для проектирования | M169: Владею на базовом уровне | N169: Да, для всех дисциплин, которые разрабатываю | O169: 2 | P169: 3 | Q169: 3 | R169: 2 | S169: 1 | T169: 1 | U169: 2 | V169: 1 | W169: 2 | X169: 2 | Y169: 1 | Z169: 1 | AA169: 0 | AB169: 2 | AC169: 1 | AD169: 2 | AE169: Да, иногда | AF169: Постановщик задач Методолог (проектирование образовательных результатов и ФОС) | AG169: Более 10 лет | AH169: - рабочая программа дисциплины по современному ИИ, пригодная для утверждения и запуска; - набор методических приёмов для объяснения нетривиальных тем и работы с разнородной аудиторией; - опыт командной разработки образовательного продукта и навыки согласования содержания между участниками. | AI169: нет
A170: TRUE | B170: {=_xlfn.XLOOKUP(E170,#REF!,#REF!)} -> #REF! | C170: Артем Сорока | E170: 40aaa@mail.ru | F170: 46208.817 | G170: Анализ данных, Машинное обучение, Нейронные сети, Компьютерное зрение | H170: Компьютерные науки | I170: Слышал(а) о ней, но не изучал(а) подробно | J170: Компетенции в области математических основ ИИ (MF) Компетенции в области машинного обучения (ML) Компетенции в области глубокого обучения (DL) | L170: Нет, никогда не использовал(а) | M170: Не владею, не понимаю, как это делать | N170: Нет, никогда | O170: 2 | P170: 2 | Q170: 4 | R170: 4 | S170: 3 | T170: 3 | U170: 3 | V170: 4 | W170: 3 | X170: 2 | Y170: 3 | Z170: 2 | AA170: 3 | AB170: 4 | AC170: 2 | AD170: 2 | AE170: Да, регулярно | AF170: Постановщик задач Эксперт по содержанию (глубокое знание предметной области ИИ) Практик-разработчик (код, инструменты, инфраструктура) | AG170: 3–6 лет | AH170: Актуализировать знания о современных подходах и тенденциях в области ИИ; Освоить best practices преподавания ИИ и проектного обучения; Обновить учебные материалы с учетом актуальных технологий и инструментов. | AI170: Планирую актуализировать следующие дисциплины: - Введение в нейронные сети; - Компьютерное зрение.
A171: TRUE | B171: {=_xlfn.XLOOKUP(E171,#REF!,#REF!)} -> #REF! | C171: Александр Лут | E171: lutav@susu.ru | F171: 46208.833 | G171: Базы данных, программирование на языке C++, C# и Python, объектно-ориентированное программирование, функциональное и логическое программирование, алгоритмы и структуры данных | H171: Математика / Прикладная математика | I171: Использую КРМ в своей профессиональной деятельности | J171: Компетенции в области математических основ ИИ (MF) Компетенции в области машинного обучения (ML) | L171: Да, применяю как основу для проектирования | M171: Владею на базовом уровне | N171: Да, для всех дисциплин, которые разрабатываю | O171: 2 | P171: 4 | Q171: 3 | R171: 2 | S171: 2 | T171: 1 | U171: 2 | V171: 1 | W171: 3 | X171: 3 | Y171: 3 | Z171: 3 | AA171: 3 | AB171: 2 | AC171: 2 | AD171: 2 | AE171: Да, иногда | AF171: Практик-разработчик (код, инструменты, инфраструктура) | AG171: 7–10 лет | AH171: повышение квалификации и уровня командной работы | AI171: -
A172: TRUE | B172: {=_xlfn.XLOOKUP(E172,#REF!,#REF!)} -> #REF! | C172: Юрий Чернышов | E172: yura_ch@mail.ru | F172: 46208.833 | G172: &quot;Безопасность генеративного искусственного интеллекта&quot; &quot;Эффективность вычислений в нейронных сетях&quot; | H172: Математика / Прикладная математика | I172: Изучал(а) структуру КРМ, но не применял(а) в работе | J172: Компетенции в области машинного обучения (ML) Компетенции в области глубокого обучения (DL) Компетенции в области больших языковых моделей (LLM) | L172: Нет, никогда не использовал(а) | M172: Не владею, не понимаю, как это делать | N172: Нет, никогда | O172: 2 | P172: 1 | Q172: 4 | R172: 3 | S172: 4 | T172: 3 | U172: 3 | V172: 4 | W172: 2 | X172: 2 | Y172: 2 | Z172: 4 | AA172: 2 | AB172: 4 | AC172: 4 | AD172: 2 | AE172: Да, регулярно | AF172: Постановщик задач Эксперт по содержанию (глубокое знание предметной области ИИ) Методолог (проектирование образовательных результатов и ФОС) Практик-разработчик (код, инструменты, инфраструктура) | AG172: Более 10 лет | AH172: Познакомиться с лучшими практическими методами преподавания ИИ (структуры теоретических материалов, практические задачи), особенно по новым перспективным направлениям - безопасность ИИ агентов, объяснимый ИИ, мультимодальные системы. Обсудить практический опыт взаимодействия с индустрией. Наладить полезные контакты (полезно для конференций, публикаций, перекрестного рецензирования диссертаций и пр.) | AI172: Все темы, связанные с безопасностью и объяснимостью генеративного ИИ, в том числе ИИ агентов. Эффективные вычисления для ИИ (специальные алгоритмы для обучения и инференса, оптимизация вычислений для кластеров GPU) Применение методов обучения с подкреплением (reinforcement learning) для обучения ИИ моделей (включая мультимодальные).
A173: TRUE | B173: {=_xlfn.XLOOKUP(E173,#REF!,#REF!)} -> #REF! | C173: Михаил Городничев | E173: gorodnichev89@yandex.ru | F173: 46208.852 | G173: Системы машинного зрения Проектный практикум Технологии ИИ в интеллектуальных транспортных системах | H173: Математика / Прикладная математика | I173: Использую КРМ в своей профессиональной деятельности | J173: Профессиональные роли Компетенции в области машинного обучения (ML) Компетенции в области глубокого обучения (DL) Компетенции в области жизненного цикла систем искусственного интеллекта (FC) | L173: Да, применяю как основу для проектирования | M173: Владею хорошо, могу обучить коллег | N173: Да, для всех дисциплин, которые разрабатываю | O173: 2 | P173: 4 | Q173: 4 | R173: 4 | S173: 4 | T173: 2 | U173: 3 | V173: 3 | W173: 4 | X173: 4 | Y173: 2 | Z173: 3 | AA173: 3 | AB173: 3 | AC173: 3 | AD173: 4 | AE173: Да, регулярно | AF173: Постановщик задач Эксперт по содержанию (глубокое знание предметной области ИИ) | AG173: Более 10 лет | AH173: Узнать лучшие практики применения ИИ в учебном процессе Систематизация знаний в области разработки РПД и ФОС Повышение навыков взаимодействия с ИП и внедрения практико-ориентированных занятий | AI173: Технологии ИИ в интеллектуальных транспортных системах
A174: TRUE | B174: {=_xlfn.XLOOKUP(E174,#REF!,#REF!)} -> #REF! | C174: Роман Борзин | E174: roma.borzin@mail.ru | F174: 46208.852 | G174: Основы промт-инжениринга | H174: Информатика / Программирование | I174: Слышал(а) о ней, но не изучал(а) подробно | J174: Компетенции в области больших языковых моделей (LLM) | L174: Планирую начать использовать в ближайшее время | M174: Владею на базовом уровне | N174: Планирую использовать в будущем | O174: 3 | P174: 3 | Q174: 1 | R174: 2 | S174: 3 | T174: 3 | U174: 3 | V174: 3 | W174: 2 | X174: 2 | Y174: 3 | Z174: 3 | AA174: 3 | AB174: 2 | AC174: 4 | AD174: 3 | AE174: Да, иногда | AF174: Постановщик задач Практик-разработчик (код, инструменты, инфраструктура) | AG174: 3–6 лет | AH174: 1. Системное понимание архитектуры ИИ‑моделей. 2. Интеграция ИИ в учебный процесс с учётом этических норм. 3. Критическая оценка результатов ИИ и обучение этому студентов. | AI174: На данный момент нет.
A175: TRUE | B175: {=_xlfn.XLOOKUP(E175,#REF!,#REF!)} -> #REF! | C175: Марина Храмова | E175: mhramova@gmail.com | F175: 46208.863 | G175: Введение в профессию (преподавала) | H175: Математика / Прикладная математика | I175: Изучал(а) структуру КРМ, но не применял(а) в работе | J175: Профессиональные роли | L175: Планирую начать использовать в ближайшее время | M175: Владею на базовом уровне | N175: Планирую использовать в будущем | O175: 0 | P175: 0 | Q175: 0 | R175: 0 | S175: 0 | T175: 0 | U175: 0 | V175: 2 | W175: 4 | X175: 4 | Y175: 4 | Z175: 4 | AA175: 4 | AB175: 2 | AC175: 1 | AD175: 3 | AE175: Да, регулярно | AF175: Методолог (проектирование образовательных результатов и ФОС) | AG175: Более 10 лет | AH175: Любое повышение квалификации интересно | AI175: нет
A176: TRUE | B176: {=_xlfn.XLOOKUP(E176,#REF!,#REF!)} -> #REF! | C176: Лилия Демидова | E176: liliya.demidova@rambler.ru | F176: 46208.874 | G176: Введение в машинное обучение. Автоматизированное машинное обучение. | H176: Математика / Прикладная математика | I176: Слышал(а) о ней, но не изучал(а) подробно | J176: Компетенции в области математических основ ИИ (MF) Компетенции в области машинного обучения (ML) Компетенции в области глубокого обучения (DL) Компетенции в области больших языковых моделей (LLM) | L176: Да, применяю как основу для проектирования | M176: Владею на базовом уровне | N176: Да, для всех дисциплин, которые разрабатываю | O176: 4 | P176: 4 | Q176: 4 | R176: 4 | S176: 3 | T176: 2 | U176: 4 | V176: 4 | W176: 4 | X176: 4 | Y176: 3 | Z176: 4 | AA176: 3 | AB176: 1 | AC176: 1 | AD176: 2 | AE176: Да, регулярно | AF176: Постановщик задач Эксперт по содержанию (глубокое знание предметной области ИИ) Методолог (проектирование образовательных результатов и ФОС) Практик-разработчик (код, инструменты, инфраструктура) Эксперт по КРМ (знание структуры, методик применения) | AG176: Более 10 лет | AH176: Совершенствование знаний по преподаванию дисциплин в сфере ИИ. | AI176: Введение в машинное обучение
A177: TRUE | B177: {=_xlfn.XLOOKUP(E177,#REF!,#REF!)} -> #REF! | C177: Андрей Сопов | E177: saa020403@gmail.com | F177: 46208.902 | G177: Основы MLOps | H177: Информатика / Программирование | I177: Слышал(а) о ней, но не изучал(а) подробно | J177: Профессиональные роли | L177: Да, применяю как основу для проектирования | M177: Владею на базовом уровне | N177: Да, для всех дисциплин, которые разрабатываю | O177: 3 | P177: 3 | Q177: 4 | R177: 3 | S177: 4 | T177: 4 | U177: 2 | V177: 3 | W177: 3 | X177: 2 | Y177: 3 | Z177: 2 | AA177: 2 | AB177: 3 | AC177: 3 | AD177: 3 | AE177: Да, регулярно | AF177: Практик-разработчик (код, инструменты, инфраструктура) Эксперт по КРМ (знание структуры, методик применения) | AG177: Менее 3 лет | AH177: Обмен опытом Нетворкинг | AI177: Основы MLOps
A178: TRUE | B178: {=_xlfn.XLOOKUP(E178,#REF!,#REF!)} -> #REF! | C178: Павел Кравченя | E178: kpd_@mail.ru | F178: 46208.909 | G178: Моделирование систем Машинное обучение и анализ данных Машинное обучение и искусственные нейронные сети Нейронные сети MLOps инженерия | H178: Математика / Прикладная математика | I178: Использую КРМ в своей профессиональной деятельности | J178: Компетенции в области математических основ ИИ (MF) Компетенции в области машинного обучения (ML) Компетенции в области глубокого обучения (DL) Компетенции в области больших языковых моделей (LLM) | L178: Да, применяю как основу для проектирования | M178: Владею на базовом уровне | N178: Иногда, для отдельных дисциплин | O178: 2 | P178: 3 | Q178: 3 | R178: 3 | S178: 2 | T178: 3 | U178: 3 | V178: 3 | W178: 1 | X178: 1 | Y178: 1 | Z178: 1 | AA178: 1 | AB178: 0 | AC178: 1 | AD178: 1 | AE178: Нет, не планирую | AF178: Эксперт по содержанию (глубокое знание предметной области ИИ) Практик-разработчик (код, инструменты, инфраструктура) | AG178: Более 10 лет | AH178: - Освоить методику применения КРМ для проектирования РПД и ФОС в области ИИ. - Систематизировать собственные курсы и привести их в соответствие с актуальными требованиями к компетенциям. - Обменяться практиками с коллегами и получить готовые инструменты для проектной работы студентов. | AI178: Пока не определился, готов выбрать в процессе.
A179: TRUE | B179: {=_xlfn.XLOOKUP(E179,#REF!,#REF!)} -> #REF! | C179: Ирина Тюжина | E179: dojdlivaia@bk.ru | F179: 46208.912 | G179: Основы глубокого обучения, технологии обработки данных, системы искусственного интеллекта | H179: Информатика / Программирование | I179: Слышал(а) о ней, но не изучал(а) подробно | J179: Компетенции в области машинного обучения (ML) Компетенции в области глубокого обучения (DL) | L179: Нет, никогда не использовал(а) | M179: Не владею, не понимаю, как это делать | N179: Иногда, для отдельных дисциплин | O179: 0 | P179: 1 | Q179: 3 | R179: 3 | S179: 1 | T179: 0 | U179: 1 | V179: 2 | W179: 3 | X179: 3 | Y179: 3 | Z179: 1 | AA179: 1 | AB179: 0 | AC179: 3 | AD179: 2 | AE179: Нет, но планирую | AF179: Эксперт по содержанию (глубокое знание предметной области ИИ) Методолог (проектирование образовательных результатов и ФОС) | AG179: 3–6 лет | AH179: Улучшение разрабатываемых дисциплин, лучшее понимание логике, что за каким пунктом должно идти, в конечном итоге польза для студентов. | AI179: Затрудняюсь ответить, но впереди работа с большим набором новых дисциплин.
A180: TRUE | B180: {=_xlfn.XLOOKUP(E180,#REF!,#REF!)} -> #REF! | C180: Наталья Чубырь | E180: chubyr-natalja@mail.ru | F180: 46208.912 | G180: Математический анализ 2, промпт-инжиниринг в профессиональной деятельности | H180: Математика / Прикладная математика | I180: Изучал(а) структуру КРМ, но не применял(а) в работе | J180: Компетенции в области математических основ ИИ (MF) Компетенции в области машинного обучения (ML) | L180: Да, применяю как основу для проектирования | M180: Владею на базовом уровне | N180: Иногда, для отдельных дисциплин | O180: 0 | P180: 0 | Q180: 1 | R180: 1 | S180: 0 | T180: 0 | U180: 0 | V180: 3 | W180: 3 | X180: 2 | Y180: 1 | Z180: 2 | AA180: 1 | AB180: 0 | AC180: 0 | AD180: 2 | AE180: Да, регулярно | AF180: Постановщик задач Эксперт по КРМ (знание структуры, методик применения) | AG180: Более 10 лет | AH180: Результаты обучения планирую использовать в работе | AI180: нет
... A272: TRUE | B272: {=_xlfn.XLOOKUP(E272,#REF!,#REF!)} -> #REF! | C272: Arhtur Zagidullin | E272: arhtur.zagidullin@yandex.ru | F272: 46209.69 | G272: Небесная мехника, гравиметрия, физика, математический анализ, линейнная алгебра, дифференциальные уравнения | H272: Математика / Прикладная математика | I272: Нет, совсем не знаком(а) | J272: Компетенции в области машинного обучения (ML) | L272: Нет, никогда не использовал(а) | M272: Не владею, не понимаю, как это делать | N272: Нет, никогда | O272: 0 | P272: 0 | Q272: 2 | R272: 1 | S272: 1 | T272: 0 | U272: 0 | V272: 0 | W272: 3 | X272: 0 | Y272: 0 | Z272: 0 | AA272: 0 | AB272: 0 | AC272: 0 | AD272: 0 | AE272: Нет, но планирую | AF272: Постановщик задач | AG272: 3–6 лет | AH272: Пока так и не понял о чем будет программа...будут учить новому или будут показывать связку ИИ с ФОС | AI272: нет
A273: TRUE | B273: {=_xlfn.XLOOKUP(E273,#REF!,#REF!)} -> #REF! | C273: Компаниец Виталий | E273: kompaniets@sfedu.ru | F273: 46209.718 | G273: Проектирование сложных пользовательских интерфейсов Проектирование и разработка информационных систем | H273: Информатика / Программирование | I273: Изучал(а) структуру КРМ, но не применял(а) в работе | J273: Компетенции в области больших языковых моделей (LLM) Компетенции в области жизненного цикла систем искусственного интеллекта (FC) | L273: Планирую начать использовать в ближайшее время | M273: Владею на базовом уровне | N273: Иногда, для отдельных дисциплин | O273: 2 | P273: 3 | Q273: 2 | R273: 0 | S273: 1 | T273: 1 | U273: 1 | V273: 2 | W273: 3 | X273: 3 | Y273: 3 | Z273: 3 | AA273: 2 | AB273: 3 | AC273: 2 | AD273: 2 | AE273: Да, регулярно | AF273: Методолог (проектирование образовательных результатов и ФОС) | AG273: Более 10 лет | AH273: Готовность к разработке и реализации дисциплин по КРМ Познакомиться с опытом коллег Нетворкинг | AI273: Проектирование и разработка информационных систем | AJ273: Проектирование и разработка информационных систем
A274: TRUE | B274: {=_xlfn.XLOOKUP(E274,#REF!,#REF!)} -> #REF! | C274: Тимур Яновский | E274: janovsky@yandex.ru | F274: 46209.724 | G274: Методы оптимизации, Теория вероятностей и математическая статистика | H274: Математика / Прикладная математика | I274: Слышал(а) о ней, но не изучал(а) подробно | J274: Компетенции в области математических основ ИИ (MF) Компетенции в области машинного обучения (ML) | L274: Да, применяю как основу для проектирования | M274: Владею на базовом уровне | N274: Иногда, для отдельных дисциплин | O274: 3 | P274: 1 | Q274: 1 | R274: 1 | S274: 1 | T274: 0 | U274: 1 | V274: 2 | W274: 2 | X274: 2 | Y274: 3 | Z274: 3 | AA274: 1 | AB274: 4 | AC274: 4 | AD274: 3 | AE274: Да, иногда | AF274: Постановщик задач | AG274: Более 10 лет | AH274: Я в первую очередь представитель индустриального партнера. Жду от обучения актуализацию своих знаний по тематике ИИ, расширение кругозора. Понимание принципов трансформации потребностей бизнеса в учебные практики. | AI274: Да, есть. Методы оптимизации
A275: TRUE | B275: {=_xlfn.XLOOKUP(E275,#REF!,#REF!)} -> #REF! | C275: Марина Бакулева | E275: m.a.bakuleva@yandex.ru | F275: 46209.974 | G275: Дискретная математика | H275: Компьютерные науки | I275: Использую КРМ в своей профессиональной деятельности | J275: Компетенции в области математических основ ИИ (MF) | L275: Да, применяю как основу для проектирования | M275: Владею на базовом уровне | N275: Иногда, для отдельных дисциплин | O275: 1 | P275: 0 | Q275: 1 | R275: 0 | S275: 0 | T275: 0 | U275: 0 | V275: 0 | W275: 2 | X275: 1 | Y275: 1 | Z275: 2 | AA275: 1 | AB275: 1 | AC275: 1 | AD275: 1 | AE275: Да, иногда | AF275: Методолог (проектирование образовательных результатов и ФОС) | AG275: Более 10 лет | AH275: Повышение квалификации в современных подходах использования и разработки ИИ | AI275: Дискретная математика, нейроинформатика
A276: TRUE | B276: {=_xlfn.XLOOKUP(E276,#REF!,#REF!)} -> #REF! | C276: Александр Бакулев | E276: contact-bav@mail.ru | F276: 46209.995 | G276: Архитектуры промышленных программных систем | H276: Информатика / Программирование | I276: Слышал(а) о ней, но не изучал(а) подробно | J276: Ни один из разделов не знаком | L276: Планирую начать использовать в ближайшее время | M276: Не владею, не понимаю, как это делать | N276: Нет, никогда | O276: 2 | P276: 2 | Q276: 2 | R276: 0 | S276: 4 | T276: 2 | U276: 1 | V276: 0 | W276: 1 | X276: 0 | Y276: 0 | Z276: 1 | AA276: 2 | AB276: 4 | AC276: 2 | AD276: 0 | AE276: Да, иногда | AF276: Практик-разработчик (код, инструменты, инфраструктура) | AG276: Более 10 лет | AH276: Систематизация знаний в области ИИ, практика применения ИИ в образовательной деятельности, трансформация традиционной преподавания в ИИ-ориентированную | AI276: Модули дисциплины &quot;Архитектура промышленных программных систем&quot;
A277: TRUE | B277: {=_xlfn.XLOOKUP(E277,#REF!,#REF!)} -> #REF! | C277: Залина Русинова | E277: z.gilvanova@yandex.ru | F277: 46210.131 | G277: Обработка естественного языка | H277: Информатика / Программирование | I277: Слышал(а) о ней, но не изучал(а) подробно | J277: Ни один из разделов не знаком | L277: Планирую начать использовать в ближайшее время | M277: Не владею, не понимаю, как это делать | N277: Нет, никогда | O277: 0 | P277: 4 | Q277: 4 | R277: 4 | S277: 4 | T277: 4 | U277: 3 | V277: 4 | W277: 1 | X277: 1 | Y277: 3 | Z277: 2 | AA277: 3 | AB277: 4 | AC277: 3 | AD277: 3 | AE277: Да, иногда | AF277: Эксперт по содержанию (глубокое знание предметной области ИИ) | AG277: Менее 3 лет | AH277: Научиться проектировать и реализовывать ОП | AI277: - Искусственный интеллект в информационной безопасности
A278: TRUE | B278: {=_xlfn.XLOOKUP(E278,#REF!,#REF!)} -> #REF! | C278: Дмитрий Ворожцов | E278: dimka_vor3@mail.ru | F278: 46210.338 | G278: Информационные технологии | H278: Информатика / Программирование | I278: Использую КРМ в своей профессиональной деятельности | J278: Компетенции в области машинного обучения (ML) Компетенции в области глубокого обучения (DL) | L278: Да, применяю как основу для проектирования | M278: Владею на базовом уровне | N278: Иногда, для отдельных дисциплин | O278: 0 | P278: 2 | Q278: 2 | R278: 2 | S278: 0 | T278: 0 | U278: 1 | V278: 0 | W278: 3 | X278: 3 | Y278: 3 | Z278: 3 | AA278: 1 | AB278: 1 | AC278: 1 | AD278: 2 | AE278: Да, регулярно | AF278: Постановщик задач Эксперт по содержанию (глубокое знание предметной области ИИ) Практик-разработчик (код, инструменты, инфраструктура) | AG278: Более 10 лет | AH278: Овладеть новыми компетенциями в области ИИ | AI278: Информационные технологии, Программирование ГИС, Дистанционное зондирование земли
A279: TRUE | B279: {=_xlfn.XLOOKUP(E279,#REF!,#REF!)} -> #REF! | C279: Владимир Кулагин | E279: v.p.kulagin@mtuci.ru | F279: 46210.392 | G279: Мультиагентные системы | H279: Математика / Прикладная математика | I279: Изучал(а) структуру КРМ, но не применял(а) в работе | J279: Компетенции в области жизненного цикла систем искусственного интеллекта (FC) | L279: Планирую начать использовать в ближайшее время | M279: Владею на базовом уровне | N279: Иногда, для отдельных дисциплин | O279: 2 | P279: 3 | Q279: 2 | R279: 2 | S279: 3 | T279: 2 | U279: 2 | V279: 2 | W279: 3 | X279: 3 | Y279: 3 | Z279: 3 | AA279: 3 | AB279: 3 | AC279: 3 | AD279: 3 | AE279: Да, иногда | AF279: Постановщик задач | AG279: Более 10 лет | AH279: Выстроить более практикоориентированный курс на основе КРМ | AI279: -
A280: TRUE | B280: {=_xlfn.XLOOKUP(E280,#REF!,#REF!)} -> #REF! | C280: Святослав Солодушкин | E280: solodushkin_s@mail.ru | F280: 46210.424 | G280: Математические основы искусственного интеллекта | H280: Математика / Прикладная математика | I280: Слышал(а) о ней, но не изучал(а) подробно | J280: Ни один из разделов не знаком | L280: Планирую начать использовать в ближайшее время | M280: Не владею, не понимаю, как это делать | N280: Нет, никогда | O280: 1 | P280: 2 | Q280: 3 | R280: 3 | S280: 1 | T280: 1 | U280: 1 | V280: 3 | W280: 4 | X280: 4 | Y280: 4 | Z280: 4 | AA280: 4 | AB280: 3 | AC280: 3 | AD280: 3 | AE280: Да, регулярно | AF280: Постановщик задач | AG280: Более 10 лет | AH280: 1. Фактические знания по обучению, доучиванию, тонкой настройке и практическому использованию больших языковых моделей. 2. Фактические знания по обучению, доучиванию, тонкой настройке и практическому использованию нейросетей для совместной обработки разнородных изображений (фотография в видимом спектре + компьютерная томография). | AI280: Проектный практикум
A281: TRUE | B281: {=_xlfn.XLOOKUP(E281,#REF!,#REF!)} -> #REF! | C281: Виктория Голубева | E281: usr23939@vyatsu.ru | F281: 46210.44 | G281: Языки программирование, основы нейронных сетей, машинное обучение | H281: Информатика / Программирование | I281: Изучал(а) структуру КРМ, но не применял(а) в работе | J281: Профессиональные роли Компетенции в области математических основ ИИ (MF) Компетенции в области машинного обучения (ML) | L281: Планирую начать использовать в ближайшее время | M281: Не владею, не понимаю, как это делать | N281: Иногда, для отдельных дисциплин | O281: 2 | P281: 2 | Q281: 3 | R281: 3 | S281: 2 | T281: 3 | U281: 2 | V281: 2 | W281: 1 | X281: 1 | Y281: 1 | Z281: 3 | AA281: 3 | AB281: 0 | AC281: 1 | AD281: 3 | AE281: Да, иногда | AF281: Постановщик задач Практик-разработчик (код, инструменты, инфраструктура) | AG281: Менее 3 лет | AH281: Погрузить в преподавание дисциплин, связанных с ии Узнать про разработку рпд | AI281: языки программирования
A282: TRUE | B282: {=_xlfn.XLOOKUP(E282,#REF!,#REF!)} -> #REF! | C282: Сергей Гапоненко | E282: ggserongg@gmail.com | F282: 46210.525 | G282: Машинное обучение, разработка мобильных приложений | H282: Информатика / Программирование | I282: Слышал(а) о ней, но не изучал(а) подробно | J282: Компетенции в области машинного обучения (ML) Компетенции в области больших языковых моделей (LLM) | L282: Планирую начать использовать в ближайшее время | M282: Не владею, не понимаю, как это делать | N282: Иногда, для отдельных дисциплин | O282: 2 | P282: 3 | Q282: 4 | R282: 4 | S282: 4 | T282: 4 | U282: 4 | V282: 3 | W282: 3 | X282: 2 | Y282: 3 | Z282: 3 | AA282: 3 | AB282: 2 | AC282: 2 | AD282: 3 | AE282: Нет, но планирую | AF282: Практик-разработчик (код, инструменты, инфраструктура) | AG282: Менее 3 лет | AH282: Практические навыки проектирования современных образовательных программ с применением передовых технологий ИИ Развитие компетенций в области организации проектной и командной работы студентов с применением современных подходов | AI282: Нет
A283: TRUE | B283: {=_xlfn.XLOOKUP(E283,#REF!,#REF!)} -> #REF! | C283: Андрей Матвеев | E283: matveev.nsu@mail.ru | F283: 46210.562 | G283: Основы машинного обучения. Учебная практика. | H283: Информатика / Программирование | I283: Слышал(а) о ней, но не изучал(а) подробно | J283: Профессиональные роли | L283: Планирую начать использовать в ближайшее время | M283: Владею на базовом уровне | N283: Иногда, для отдельных дисциплин | O283: 0 | P283: 0 | Q283: 3 | R283: 0 | S283: 0 | T283: 0 | U283: 0 | V283: 0 | W283: 1 | X283: 1 | Y283: 1 | Z283: 3 | AA283: 0 | AB283: 1 | AC283: 0 | AD283: 2 | AE283: Да, иногда | AF283: Постановщик задач | AG283: Менее 3 лет | AH283: Глубже понимать и преподавать по тематике &quot;Современный ИИ&quot;. Я пришел в тему со стороны. По образованию физико-химик. | AI283: -
A284: TRUE | B284: {=_xlfn.XLOOKUP(E284,#REF!,#REF!)} -> #REF! | C284: Олег Сычев | E284: oasychev@gmail.com | F284: 46210.559 | G284: Языки программирования, Тестирование систем ИИ, Рефакторинг баз данных и приложений | H284: Информатика / Программирование | I284: Использую КРМ в своей профессиональной деятельности | J284: Профессиональные роли Другое | K284: Компетенции серий PL, DB | L284: Да, применяю как основу для проектирования | M284: Владею на базовом уровне | N284: Да, для всех дисциплин, которые разрабатываю | O284: 3 | P284: 3 | Q284: 3 | R284: 1 | S284: 4 | T284: 2 | U284: 2 | V284: 2 | W284: 3 | X284: 3 | Y284: 3 | Z284: 2 | AA284: 4 | AB284: 2 | AC284: 4 | AD284: 4 | AE284: Да, регулярно | AF284: Постановщик задач Практик-разработчик (код, инструменты, инфраструктура) | AG284: Более 10 лет | AH284: - Углубленное понимание тенденций в развитии современных систем ИИ - Понимание роли дисциплин связанных с программированием и DevOps в цикле обучения ИИ - Новые тренды в разработке и использовании средств автоматизации обучения | AI284: Языки программирования
A285: TRUE | B285: {=_xlfn.XLOOKUP(E285,#REF!,#REF!)} -> #REF! | C285: Виктор Зенков | E285: v1i9z52@mail.ru | F285: 46210.61 | G285: Математика | H285: Математика / Прикладная математика | I285: Нет, совсем не знаком(а) | J285: Профессиональные роли | L285: Нет, никогда не использовал(а) | M285: Не владею, не понимаю, как это делать | N285: Нет, никогда | O285: 0 | P285: 0 | Q285: 0 | R285: 0 | S285: 0 | T285: 0 | U285: 0 | V285: 0 | W285: 0 | X285: 0 | Y285: 0 | Z285: 0 | AA285: 0 | AB285: 0 | AC285: 0 | AD285: 0 | AE285: Да, иногда | AF285: Постановщик задач | AG285: Более 10 лет | AH285: Получить представление о предмете обучения. Освоить работу с библиотеками программ. | AI285: Математика.
A286: TRUE | B286: {=_xlfn.XLOOKUP(E286,#REF!,#REF!)} -> #REF! | C286: Александрова Ирина | E286: ialeksandrova@fa.ru | F286: 46210.596 | G286: Дифференциальные уравнения | H286: Математика / Прикладная математика | I286: Нет, совсем не знаком(а) | J286: Ни один из разделов не знаком | L286: Планирую начать использовать в ближайшее время | M286: Не владею, не понимаю, как это делать | N286: Планирую использовать в будущем | O286: 0 | P286: 0 | Q286: 0 | R286: 0 | S286: 0 | T286: 0 | U286: 0 | V286: 0 | W286: 4 | X286: 4 | Y286: 4 | Z286: 4 | AA286: 3 | AB286: 4 | AC286: 3 | AD286: 0 | AE286: Да, иногда | AF286: Методолог (проектирование образовательных результатов и ФОС) | AG286: Более 10 лет | AH286: Овладение компетентностно-ролевой моделью Повышение уровня компетенций в области математических основ ИИ | AI286: Дифференциальные уравнения
A287: TRUE | B287: {=_xlfn.XLOOKUP(E287,#REF!,#REF!)} -> #REF! | C287: Леонид Сердаков | E287: l.serdakov@g.nsu.ru | F287: 46210.585 | G287: Компьютерная инженерная графика | H287: Компьютерные науки | I287: Нет, совсем не знаком(а) | J287: Ни один из разделов не знаком | L287: Нет, никогда не использовал(а) | M287: Не владею, не понимаю, как это делать | N287: Нет, никогда | O287: 0 | P287: 0 | Q287: 0 | R287: 0 | S287: 0 | T287: 0 | U287: 0 | V287: 0 | W287: 3 | X287: 3 | Y287: 3 | Z287: 3 | AA287: 3 | AB287: 0 | AC287: 0 | AD287: 0 | AE287: Да, иногда | AF287: Методолог (проектирование образовательных результатов и ФОС) | AG287: 3–6 лет | AH287: Ознакомиться с основами использования ИИ для использования в учебном процессе; обучение современными методами преподавания | AI287: нет
...

Sheet _Moodle_лог
A1: Время | B1: Статус | C1: Сообщение
A2: 46197.808 | B2: ERROR | C2: Ошибка Moodle: invalidparameter. Сообщение: Обнаружено неверное значение параметра..
A3: 46197.809 | B3: DIAGNOSTIC | C3: Токен принят. Пользователь: Учитель ИТМО; логин: sheets.sync; ID: 586. Ошибка запроса журнала: Ошибка Moodle: invalidparameter. Сообщение: Обнаружено неверное значение параметра..
A4: 46197.812 | B4: OK | C4: Курс: 12; Студентов: 1; Оценочных элементов: 6
A5: 46197.813 | B5: OK | C5: Курс: 12; Студентов: 1; Оценочных элементов: 6
A6: 46197.814 | B6: OK | C6: Курс: 12; Студентов: 1; Оценочных элементов: 6
A7: 46197.834 | B7: OK | C7: Курс: 12; Пользователей: 1; Оценочных элементов: 6
A8: 46197.835 | B8: ERROR | C8: Функция: gradereport_user_get_grade_items. Параметры: {"courseid":"10"}. Ошибка Moodle: requireloginerror. Сообщение: Курс или элемент курса не доступны..
A9: 46197.835 | B9: OK | C9: Курс: 10; Пользователей: 240; Оценочных элементов: 6
A10: 46198.013 | B10: OK | C10: Курс: 10; Пользователей: 240; Оценочных элементов: 6
A11: 46198.262 | B11: OK | C11: Курс: 10; Пользователей: 240; Оценочных элементов: 6
A12: 46198.512 | B12: OK | C12: Курс: 10; Пользователей: 240; Оценочных элементов: 6
A13: 46198.762 | B13: OK | C13: Курс: 10; Пользователей: 240; Оценочных элементов: 6
... A201: 46230.016 | B201: FEEDBACK_OK | C201: cmid 673, feedbackid 8, лист «ОС1», ответов 280; cmid 675, feedbackid 10, лист «ОС2», ответов 172; cmid 676, feedbackid 11, лист «ОС3», ответов 49; cmid 688, feedbackid 12, лист «ОС4», ответов 0

Sheet Связь со спикерами
A2: Дата | B2: Время | C2: Формат | D2: Мероприятие | E2: Согласование времени | F2: статус
A3: 46209 | B3: 15:30 - 16:00 | C3: Онлайн | D3: Анастасия Казанцева Заместитель директора Департамента развития цифровых компетенций и образования, Министерство цифрового развития, связи и массовых коммуникаций Российской Федерации Сергей Астахов Руководитель Центра экспертизы образовательных программ автономной некоммерческой организации «Аналитический центр при Правительстве Российской Федерации» Александр Бухановский Д.т.н., научный руководитель исследовательского центра «Сильный ИИ в промышленности» Университета ИТМО Приветственные слова | E3: Да
B4: 16:00 - 17:30 | C4: Онлайн | D4: Александр Бухановский Д.т.н., научный руководитель исследовательского центра «Сильный ИИ в промышленности» Университета ИТМО Конструирование и разработка учебных дисциплин в сфере ИИ на основе КРМ | E4: Да
B5: 17:30 - 18:00 | C5: Онлайн | D5: Александра Климова К.т.н., директор учебно-методического центра «Искусственный интеллект» Университета ИТМО Особенности организации программы ДПО | E5: Да
A6: 46210 | B6: 10:00 - 11:30 | C6: Онлайн | D6: Александр Хватов К.ф.-м..н., старший научный сотрудник, центр «Сильный искусственный интеллект в промышленности» Университета ИТМО Преподавание современного ИИ: архитектуры, математика, оптимизация (компетенции КРМ MF1-MF6, O2-O3, FC1) | E6: Да
B7: 11:40 - 13:10 | C7: Онлайн | D7: Петр Гладилин К.т.н., инженер ключевых проектов ООО «Техкампания Хуавей» Преподавание современного ИИ: машинное обучение (компетенции КРМ ML2-ML8) | E7: Да
A8: 46211 | B8: 10:00 - 11:30 | C8: Онлайн | D8: Али Аммар К.т.н., Разработчик-эксперт ООО «Центр искусственного интеллекта МВС» Преподавание современного ИИ: глубокое обучение (компетенции КРМ DL1-DL5) | E8: Да
B9: 11:40 - 13:10 | C9: Онлайн | D9: Анна Калюжная К.т.н., Старший менеджер программы продвинутой аналитики и ИИ, управление цифровых технологий и ИИ, департамент по цифровой трансформации ПАО «Газпром нефть» Преподавание современного ИИ: большие языковые модели, агенты и ГенИИ (компетенции КРМ LLM1-LLM5, FC2-FC3) | E9: Да
A10: 46212 | B10: 10:00 - 11:30 | C10: Онлайн | D10: Алексей Духанов Д.т.н., ведущий научный сотрудник, центр «Сильный искусственный интеллект в промышленности», доцент ФТИИ Университета ИТМО Практики создания учебно-методических материалов в сфере ИИ на основе КРМ с использованием агентных технологий ИИ | E10: Да
B11: 11:40 - 13:10 | C11: Онлайн | D11: Александр Бухановский Д.т.н., научный руководитель исследовательского центра «Сильный ИИ в промышленности» Университета ИТМО Разработка РПД и комплексного фонда оценочных средств на основе КРМ: установочная сессия | E11: Да
A12: 46213 | B12: 10:00 - 13:00 | C12: Онлайн | D12: День проектной работы, в том числе 2 а.ч. консультация с куратором (РПД)
A13: 46216 | B13: 10:00 - 11:30 | C13: Онлайн | D13: Денис Кустов Руководитель направления развития образовательных программ бакалавриата; Операционный руководитель Образовательного центра по ИИ МФТИ Оценка учебных дисциплин и ассесмент результатов обучения в сфере ИИ на основе КРМ | E13: Да
B14: 11:40 - 13:10 | C14: Онлайн | D14: Нурышева Меруерт Старший менеджер ООО «ИТМО.ИСКИН» Формы и практические кейсы взаимодействия вуза и компании в рамках приказа Минцифры №270 от 31.03.2026 (об ИТ-льготах) | E14: Да
B15: ассинхрон | C15: Онлайн | D15: Александр Бухановский Д.т.н., научный руководитель исследовательского центра «Сильный искусственный интеллект в промышленности» Университета ИТМО Привлечение финансирования от бизнеса и государства в сфере ИИ в вуз | E15: согласование не нужно, ассинхрон
B16: ассинхрон | C16: Онлайн | D16: Денис Насонов К.т.н., старший научный сотрудник, центр «Сильный искусственный интеллект в промышленности», доцент ФТИИ Университета ИТМО Практики выполнения заказных НИОКТР в сфере ИИ по заказу индустрии: трансформация в учебные кейсы на основе КРМ | E16: согласование не нужно, ассинхрон
A17: 46217 | B17: 10:00 - 13:10 | C17: Онлайн | D17: Взаимодействие бизнеса с вузами в сфере ИИ: взгляд от индустрии и сессия «вопрос-ответ» | E17: Нет, ждем
B18: 14:00 - 15:00 | C18: Онлайн | D18: День проектной работы, в том числе 2 а.ч. консультация с куратором (РПД)
A19: 46218 | B19: 11:00 - 13:00 | C19: Онлайн | D19: Промежуточная аттестация результатов обучения: представление концепции РПД перед экспертами
B20: 13:15 - 15:15 | C20: Онлайн | D20: Промежуточная аттестация результатов обучения: представление концепции РПД перед экспертами
A21: 46219 | B21: 10:00 - 11:30 | C21: Онлайн | D21: Сергей Иванов К.т.н., старший научный сотрудник, центр «Сильный искусственный интеллект в промышленности», доцент ФТИИ Университета ИТМО ИИ-разработка ПО: основные подходы и доступный инструментарий | E21: Да
B22: 11:45 - 13:15 | C22: Онлайн | D22: Иван Ходненко К.т.н., старший научный сотрудник, «Национальный центр когнитивных разработок», старший преподаватель ФТИИ Университета ИТМО ИИ-разработка ПО: применение в учебном процессе для подготовки ИИ специалистов | E22: Да
B23: ассинхрон | C23: Онлайн | D23: Илья Ревин К.т.н., руководитель группы разработки ООО «ИТМО.ИСКИН» Создание инфраструктуры для аппаратного воплощения ИИ | E23: согласование не нужно, ассинхрон | F23: рендеринг
A24: 46220 | B24: ассинхрон | C24: Онлайн | D24: Николай Никитин К.т.н., старший научный сотрудник, центр «Сильный искусственный интеллект в промышленности», доцент ФТИИ Университета ИТМО Культура и экосистема отрытого кода в сфере ИИ в вузе | E24: согласование не нужно, ассинхрон
B25: 11:00 - 16:00 | C25: Онлайн | D25: День проектной работы, в том числе 2 а.ч. консультация с куратором (ФОС)
A26: 46223 | B26: ассинхрон | C26: Онлайн | D26: Артем Береснев К.т.н., старший преподаватель, заместитель декана факультета прикладной информатики Университета ИТМО Особенности использования суперкомпьютерных, распределенных, облачных инфраструктур для обучения в сфере ИИ | E26: согласование не нужно, ассинхрон | F26: рендеринг
B27: 11:40 - 13:10 | C27: Онлайн | D27: ИИ-ассистенты в образовании: демонстрация практических кейсов и сессия «вопрос-ответ»
A28: 46224 | B28: 10:00 - 10:45 | C28: Онлайн | D28: Юлия Борисова К.т.н., младший научный сотрудник, центр «Сильный искусственный интеллект в промышленности», ассистент ФТИИ Университета ИТМО Организация молодежных учебно-научных лаборатории в сфере ИИ | E28: Да
B29: 10:55 - 12:25 | C29: Онлайн | D29: Борисова Юлия Ивановна К.т.н., младший научный сотрудник, центр «Сильный искусственный интеллект в промышленности», ассистент ФТИИ Университета ИТМО Климова Александра Сергеевна К.т.н., директор УМЦ искусственный интеллект, доцент ФТИИ Университета ИТМО Вовлечение обучаемых в сфере ИИ в подготовку публикаций уровня А*/Q1 | E29: Да
B30: ассинхрон | C30: Онлайн | D30: Михаил Граденко Директор департамента технологий искусственного интеллекта Современные образовательные практики в ИИ: взгляд от индустрии | E30: согласование не нужно, ассинхрон | F30: рендеринг
A31: 46225 | B31: 10:00 - 10:45 | C31: Онлайн | D31: Толстиков Выездные мероприятия для обучаемых в сфере ИИ: конференции, школы, визиты к индустриальным партнерам | E31: Нет, ждем
B32: 10:55 - 11:40 | C32: Онлайн | D32: Нурышева Меруерт Старший менеджер ООО «ИТМО.ИСКИН» Организация проектно-соревновательной деятельности обучаемых в форме хакатонов | E32: Да
B33: 14:00 - 18:00 | C33: Онлайн | D33: День консультаций с куратором (2 а.ч. консультация с куратором (ФОС))
A34: 46226 | B34: 11:40 - 13:10 | C34: Онлайн | D34: ВСЕ Нестандартные практики обучения в сфере ИИ: кейсы вузов и сессия «вопрос-ответ» | E34: Нет, ждем
A35: 46227 | B35: 10:00 - 11:30 | C35: Онлайн | D35: Кросс-валидация | E35: Нет, ждем
A36: 46230 | B36: 10:00 - 10:30 | C36: Очно: Ломоносова | D36: Приветственный кофе
B37: 10:30 - 12:00 | C37: Очно: Ломоносова Трансляция | D37: Юрий Визильтер Ключевые направления и основные тренды развития ИИ | E37: Да
B38: 12:10 - 13:40 | C38: Очно: Ломоносова Трансляция | D38: Александр Бухановский Д.т.н., научный руководитель исследовательского центра «Сильный ИИ в промышленности» Современный ИИ в образовании | E38: Да
B39: 14:00 - 15:00 | D39: Кофе-брейк
B40: 15:00 - 16:30 | D40: Подготовка к защите результатов на основе ИИ-симулятора
A41: 46231 | B41: 10:00 - 10:30 | D41: Кофе
B42: 10:30 - 12:00 | D42: Консультации и групповая работа с куратором, подготовка к аттестации
B43: 13:00 - 14:00 | D43: Кофе-брейк / обед
B44: 14:00 - 16:00 | C44: Очно | D44: Визит в компанию? / групповая работа
A45: 46232 | B45: 10:00 - 10:30 | D45: Кофе
B46: 10:30 - 12:00 | D46: Консультации и групповая работа с куратором, подготовка к аттестации
B47: 13:00 - 14:00 | D47: Кофе-брейк / обед
B48: 14:00 - 16:00 | C48: Очно | D48: Визит в компанию? / групповая работа
A49: 46233 | B49: 09:30 - 10:00 | D49: Кофе
B50: 10:00 - 13:00 | C50: Очно: Ломоносова Трансляция | D50: Круглый стол: Публичная защита результатов проектной работ
B51: 13:00 - 14:00 | D51: Кофе-брейк / обед
B52: 14:00 - 17:00 | C52: Очно: Ломоносова Трансляция | D52: Круглый стол: Публичная защита результатов проектной работ
A53: 46234 | B53: 09:30 - 10:00 | D53: Кофе
B54: 10:00 - 13:00 | C54: Очно: Ломоносова Трансляция | D54: Круглый стол: Публичная защита результатов проектной работ
B55: 13:00 - 14:00 | D55: Кофе-брейк / обед
B56: 14:00 - 17:00 | C56: Очно: Ломоносова Трансляция | D56: Круглый стол: Публичная защита результатов проектной работ
B57: 18:30 - 21:00 | C57: Очно | D57: Нетворкинг (в лофте)

Sheet Кураторы
D1: число команд | G1: Мудл | H1: ФИО | I1: почта мудл | J1: линк | K1: Слоты на 10.07 | L1: Слоты на 14.07 | M1: Слоты на 17.07
B2: 1 | C2: Добренко | D2: 4 | E2: @NataliDobrenko | G2: TRUE | H2: Добренко | I2: dobrenkonv@itmo.ru | J2: https://itmo.ktalk.ru/vn8h7mt8m174 | K2: TRUE | L2: TRUE
B3: 2 | C3: Монахов | D3: 4 | E3: @MonakhovIurii | G3: TRUE | H3: Монахов | I3: monakhov@itmo.ru | J3: https://itmo.ktalk.ru/x0s9b05l71rw | K3: TRUE | L3: TRUE
B4: 3 | C4: Хлопотов | D4: 2 | E4: @mkhlopotov | G4: TRUE | H4: Хлопотов | I4: kinomant@gmail.com | J4: https://itmo.ktalk.ru/nq2cy2g39qxx | K4: TRUE | L4: TRUE
B5: 4 | C5: Краев | D5: 4 | E5: @simon_kraev | G5: TRUE | H5: Краев | I5: simon.kraev@gmail.com | J5: https://itmo.ktalk.ru/ufn5wfs8r22i | K5: TRUE | L5: TRUE
B6: 5 | C6: Авдюшина | D6: 1 | E6: @sunnysubmarines | G6: TRUE | H6: Авдюшина | I6: avdushina98@gmail.com | J6: https://itmo.ktalk.ru/bevjuflkmffi | K6: TRUE | L6: TRUE
B7: 6 | C7: Натиг Аминов | D7: 4 | E7: @natigaminov | G7: TRUE | H7: Натиг Аминов | I7: natig.aminov@gmail.com | J7: https://itmo.ktalk.ru/wyhhoyid6wyg | K7: TRUE | L7: TRUE
B8: 7 | C8: Влад Терещенко | D8: 2 | E8: @Vl_Tershch | G8: TRUE | H8: Влад Терещенко | I8: vlad-tershch@yandex.ru | J8: https://itmo.ktalk.ru/j0em6gr9pi2x | K8: TRUE | L8: TRUE
B9: 8 | C9: Москаленко | D9: 3 | E9: @moskalenkomary | G9: TRUE | H9: Москаленко | I9: moskalenko.mary@gmail.com | J9: https://itmo.ktalk.ru/tgu4qk52q0ww | K9: TRUE | L9: TRUE
B10: 9 | C10: Береснев | D10: 1 | E10: @ArtemBeresnev | G10: TRUE | H10: Береснев | I10: open.look@gmail.com | J10: https://itmo.ktalk.ru/o9p0mahrj6xe | K10: TRUE | L10: TRUE
B11: 10 | C11: Ходненко | D11: 1 | E11: @Ivan_hod | G11: TRUE | H11: Ходненко | I11: khodnenko.ivan@gmail.com | J11: https://itmo.ktalk.ru/wc7d4c2adsgo | K11: TRUE | L11: TRUE
B12: 11 | C12: Вершинин | D12: 1 | E12: @Kerysfel | G12: TRUE | H12: Вершинин | I12: newerasowwor@gmail.com | J12: https://itmo.ktalk.ru/mtdrmok5cepk | K12: TRUE | L12: TRUE
B13: 12 | C13: Попков | D13: 3 | E13: @rmn_p | G13: TRUE | H13: Попков | I13: rpopkov@itmo.ru | J13: https://itmo.ktalk.ru/xgms7jw2v2d6 | K13: TRUE | L13: TRUE
... B15: 14 | C15: Бабушкин | D15: 3 | E15: @mvbabushkin | G15: TRUE | H15: Бабушкин | I15: hitmaxd11@mail.ru | J15: https://itmo.ktalk.ru/ecvk4d3diq1r | K15: TRUE | L15: TRUE
B16: 15 | C16: Волков | D16: 2 | E16: @alexandrr_volkov | F16: Х | G16: TRUE | H16: Волков | I16: volkovra@yahoo.com | J16: https://itmo.ktalk.ru/gvrf909x1iti | K16: TRUE | L16: TRUE
B17: 16 | C17: Волчек | D17: 3 | E17: @dvolchek | F17: Х | G17: TRUE | H17: Волчек | I17: dvolchek@itmo.ru | J17: https://itmo.ktalk.ru/g2n1ajjgcmo8 | K17: TRUE | L17: TRUE
B18: 17 | C18: Романов | D18: 3 | E18: @gorumo | F18: Х | G18: TRUE | H18: Романов | I18: romanov@itmo.ru | J18: https://itmo.ktalk.ru/mll9gj2ploqd | K18: TRUE | L18: TRUE
B19: 18 | C19: Иванова | D19: 3 | E19: @unoivansson | F19: Х | G19: TRUE | H19: Иванова | I19: kristina.uno.ivanova@gmail.com | J19: https://itmo.ktalk.ru/qadnah1l6cog | K19: TRUE | L19: TRUE
B20: 19 | C20: Бойцев | D20: 3 | E20: @boitsev | F20: Х | G20: TRUE | H20: Бойцев | I20: boitsevanton@gmail.com | J20: https://itmo.ktalk.ru/it0t4l816cv1 | K20: TRUE | L20: TRUE
B21: 20 | C21: Духанов | D21: 4 | G21: TRUE | H21: Духанов | I21: dukhanov@itmo.ru | J21: https://itmo.ktalk.ru/yudk74vchoqv | K21: TRUE | L21: TRUE
D22: 54 | E22: =SUM(D1:D21) -> 54 | H22: =C22 -> 0
D24: =D22-E22 -> 0
D25: 9

Sheet Аудитории очная часть
H1: всего в командах | I1: онлайн | J1: очно | K1: Ссылка
A2: Добренко, Хлопотов | B2: =4+2 -> 6 | C2: 8 аудиторий-4 команды церковь | D2: 2202 | E2: церковь | G2: проектор + доска | H2: =6+6+5+7+11 -> 35 | I2: =5+1+2 -> 8 | J2: =H2-I2 -> 27 | K2: https://itmo.ktalk.ru/vn8h7mt8m174 | L2: Команде Хлопотова надо написать что другая ссыль
A3: Монахов | B3: 4 | C3: 8 аудиторий-4 команды 1226 | D3: 1226 | E3: 1 корпус | G3: проектор + доска | H3: =6+6+7+6 -> 25 | I3: =4+2+4 -> 10 | J3: =H3-I3 -> 15 | K3: https://itmo.ktalk.ru/x0s9b05l71rw
A4: Краев | B4: 4 | C4: 8 аудиторий-4 команды 1224 | D4: 1224 | G4: проектор + доска | H4: =5+6*3 -> 23 | I4: =2+1 -> 3 | J4: =H4-I4 -> 20 | K4: https://itmo.ktalk.ru/ufn5wfs8r22i
A5: Натиг Аминов | B5: 4 | C5: 8 аудиторий-4 команды 4307 | D5: 4307 | E5: 4 корпус | G5: проектор + доска | H5: =7+6+6+6 -> 25 | I5: =2+2+3+1 -> 8 | J5: =H5-8 -> 17 | K5: https://itmo.ktalk.ru/wyhhoyid6wyg
A6: Духанов | B6: 4 | C6: 8 аудиторий-4 команды 4208 | D6: 4208 | G6: проектор + доска | H6: =6+7+6+6 -> 25 | I6: =1+1+1+2 -> 5 | J6: =H6-I6 -> 20 | K6: https://itmo.ktalk.ru/yudk74vchoqv
A7: Москаленко, Бабушкин | B7: 6 | C7: 8 аудиторий-4 команды 4306 | D7: 4306 | G7: проектор + доска | H7: =6*6 -> 36 | I7: =1+2+2 -> 5 | J7: =H7-I7 -> 31 | K7: https://itmo.ktalk.ru/tgu4qk52q0ww | L7: Команде Бабушкина надо написать что другая ссыль
A8: Трифанов, Попков | B8: 6 | C8: 8 аудиторий-4 команды 4210 | D8: 4210 | G8: проектор + доска | H8: 37 | I8: =2+1+1+2 -> 6 | J8: =H8-I8 -> 31 | K8: https://itmo.ktalk.ru/em8yolj5ysiw | L8: Команде Попкова надо написать что другая ссыль
A9: Волчек | B9: 3 | C9: 3 аудитории-3-4 команды 4202 | D9: 4202 | G9: проектор + доска | H9: =3*7 -> 21 | I9: =1+1+2 -> 4 | J9: =H9-I9 -> 17 | K9: https://itmo.ktalk.ru/g2n1ajjgcmo8
A10: Романов | B10: 3 | C10: 3 аудитории-3-4 команды 4207 | D10: 4207 | G10: проектор + доска | H10: =3*6 -> 18 | I10: =2+1+1 -> 4 | J10: =H10-I10 -> 14 | K10: https://itmo.ktalk.ru/mll9gj2ploqd
A11: Иванова | B11: 3 | C11: 1 ауд. - 2-3 команды 1604 | D11: 1303/8 | E11: медиа зона коворкинг | G11: проектор + доска | H11: 18 | I11: 4 | J11: =H11-I11 -> 14 | K11: https://itmo.ktalk.ru/qadnah1l6cog
A12: Бойцев | B12: 3 | C12: 4 аудитории - 2-3 команды (только проектор и доска) 1315 | D12: 1315 | E12: 1 корпус | G12: проектор + доска | H12: =5+7+7 -> 19 | I12: =1+1+1 -> 3 | J12: =H12-I12 -> 16 | K12: https://itmo.ktalk.ru/it0t4l816cv1
A13: Влад Терещенко | B13: 2 | C13: 4 аудитории - 2-3 команды (только проектор и доска) 4213 | D13: 4213 | E13: 4 корпус | G13: проектор + доска | H13: =10 -> 10 | I13: =1+2 -> 3 | J13: =H13-I13 -> 7 | K13: https://itmo.ktalk.ru/j0em6gr9pi2x
A14: Волков | B14: 2 | C14: 4 аудитории - 2-3 команды (только проектор и доска) 4103 | D14: 4103 | G14: проектор + доска | H14: =7+6 -> 13 | I14: =2+1 -> 3 | J14: =H14-I14 -> 10 | K14: https://itmo.ktalk.ru/gvrf909x1iti
A15: Авдюшина | B15: 1 | C15: 1 ауд. - 2 команды (только проектор и доска) 4206 | D15: 4206 | G15: проектор + доска | H15: =6 -> 6 | I15: =2 -> 2 | J15: =6-2 -> 4 | K15: https://itmo.ktalk.ru/bevjuflkmffi
A16: Береснев | B16: 1 | C16: 4 ауд. - 1 команда без техники с ноутбуком циия 3202 | D16: 1303/7 | E16: коворкинг | G16: только ноут, нужно флипчарт | H16: =7 -> 7 | I16: 1 | J16: =H16-I16 -> 6 | K16: https://itmo.ktalk.ru/o9p0mahrj6xe
A17: Ходненко | B17: 1 | C17: 4 ауд. - 1 команда без техники с ноутбуком циия 3210 | D17: 1303/3 | G17: только ноут, нужно флипчарт | H17: 6 | I17: =1 -> 1 | J17: =H17-I17 -> 5 | K17: https://itmo.ktalk.ru/wc7d4c2adsgo
A18: Вершинин | B18: 1 | C18: 4 ауд. - 1 команда без техники с ноутбуком циия 3229 | D18: 1303/2 | G18: только ноут, нужно флипчарт | H18: 6 | I18: 2 | J18: =H18-I18 -> 4 | K18: https://itmo.ktalk.ru/mtdrmok5cepk
L27: Куратор | M27: Ссылка
L28: Добренко Н.В., Хлопотов М.В. | M28: https://itmo.ktalk.ru/vn8h7mt8m174
L29: Монахов Ю.С. | M29: https://itmo.ktalk.ru/x0s9b05l71rw
L30: Краев С.В. | M30: https://itmo.ktalk.ru/ufn5wfs8r22i
L31: Аминов Н.С. | M31: https://itmo.ktalk.ru/wyhhoyid6wyg
L32: Духанов А.В. | M32: https://itmo.ktalk.ru/yudk74vchoqv
L33: Москаленко М.А., Бабушкин М.В. | M33: https://itmo.ktalk.ru/tgu4qk52q0ww
L34: Трифанов А.И., Попков Р.А. | M34: https://itmo.ktalk.ru/em8yolj5ysiw
L35: Волчек Д.Г. | M35: https://itmo.ktalk.ru/g2n1ajjgcmo8
L36: Романов А.А. | M36: https://itmo.ktalk.ru/mll9gj2ploqd
L37: Иванова К.Ю. | M37: https://itmo.ktalk.ru/qadnah1l6cog
L38: Бойцев А.А. | M38: https://itmo.ktalk.ru/it0t4l816cv1
... L44: Вершинин В.К. | M44: https://itmo.ktalk.ru/mtdrmok5cepk

Sheet Преподаватели
A1: ФИО | B1: Должность | C1: Тема | D1: Дата | E1: Время | F1: Формат | G1: Ссылка на встречу отправлена | H1: Презентация | I1: ТГ | J1: Список лит-ры | K1: Тесты
A2: Александр Валерьевич Бухановский | B2: Д.т.н., научный руководитель исследовательского центра «Сильный ИИ в промышленности» | C2: Установочная встреча | D2: 46209 | E2: 15:30 - 16:00 | F2: Онлайн | G2: FALSE | H2: FALSE | J2: FALSE | K2: FALSE
C3: Конструирование и разработка учебных дисциплин в сфере ИИ на основе КРМ | D3: 46209 | E3: 16:00 - 17:30 | F3: Онлайн | G3: FALSE | H3: FALSE | J3: FALSE | K3: FALSE
A4: Александр Александрович Хватов | B4: к.ф.-м..н, старший научный сотрудник, центр «Сильный искусственный интеллект в промышленности» | C4: Преподавание современного ИИ: архитектуры, математика, оптимизация (компетенции КРМ MF1-MF6, O2-O3, FC1) | D4: 46210 | E4: 10:00 - 11:30 | F4: Онлайн | G4: TRUE | H4: FALSE | I4: https://t.me/sasha_hvat | J4: TRUE | K4: FALSE
A5: Петр Евгеньевич Гладилин | B5: к.т.н., Инженер ключевых проектов, ООО «Техкампания Хуавей» | C5: Преподавание современного ИИ: машинное обучение (компетенции КРМ ML2-ML8) | D5: 46210 | E5: 11:40 - 13:10 | F5: Онлайн | G5: TRUE | H5: FALSE | I5: https://t.me/petrgl | J5: TRUE | K5: FALSE
A6: Али Аммар | B6: к.т.н., Разработчик-эксперт, ООО «Центр искусственного интеллекта МВС» | C6: Преподавание современного ИИ: глубокое обучение (компетенции КРМ DL1-DL5) | D6: 46211 | E6: 10:00 - 11:30 | F6: Онлайн | G6: TRUE | H6: FALSE | I6: https://t.me/thekon3232 | J6: TRUE | K6: FALSE
A7: Анна Владимировна Калюжная | B7: к.т.н., Старший менеджер программы продвинутой аналитики и ИИ, управление цифровых технологий и ИИ, Департамент по цифровой трансформации, ПАО "Газпромнефть" | C7: Преподавание современного ИИ: большие языковые модели, агенты и ГенИИ (компетенции КРМ LLM1-LLM5, FC2-FC3) | D7: 46211 | E7: 11:40 - 13:10 | F7: Онлайн | G7: TRUE | H7: FALSE | I7: https://t.me/kalyuzhnaya | J7: FALSE | K7: FALSE
A8: Алексей Валентинович Духанов | B8: Д.т.н., Ведущий научный сотрудник, центр «Сильный искусственный интеллект в промышленности, доцент ФТИИ | C8: Практики создания учебно-методических материалов в сфере ИИ на основе КРМ с использованием агентных технологий ИИ | D8: 46212 | E8: 10:00 - 11:30 | F8: Онлайн | G8: FALSE | H8: FALSE | I8: https://t.me/alexeid77 | J8: FALSE | K8: FALSE
A9: Александр Валерьевич Бухановский | B9: Д.т.н., научный руководитель исследовательского центра «Сильный ИИ в промышленности» | C9: Разработка РПД и комплексного фонда оценочных средств на основее КРМ: установочная сессия | D9: 46212 | E9: 11:40 - 13:10 | F9: Онлайн | G9: FALSE | H9: FALSE | J9: FALSE | K9: FALSE
A10: Нурышева Меруерт | B10: старший менеджер, ООО «ИТМО.ИСКИН» | C10: Формы и практические кейсы взаимодействия вуза и компании в рамках приказа Минцифры №270 от 31.03.2026 (об ИТ-льготах) | D10: 46216 | E10: 11:40 - 13:10 | F10: Онлайн | G10: FALSE | H10: FALSE | I10: https://t.me/Meruyert_nurysheva | J10: FALSE | K10: FALSE
A11: Радух Анна Евгеньевна, | B11: к.т.н., Генеральный директор, ООО «ИТМО.ИСКИН» | G11: FALSE | H11: FALSE | I11: https://t.me/anna_lutsenko | J11: FALSE | K11: FALSE
A12: Климова Александра Сергеевна | B12: к.т.н., Директор УМЦ Искусственный интеллект, Доцент ФТИИ Университет ИТМО | G12: FALSE | H12: FALSE | I12: https://t.me/caledonia_09 | J12: FALSE | K12: FALSE
A13: Александр Валерьевич Бухановский | B13: Д.т.н., научный руководитель исследовательского центра «Сильный ИИ в промышленности» | C13: Привлечение финансирования от бизнеса и государства в сфере ИИ в вуз | E13: ассинхрон | F13: Онлайн | G13: FALSE | H13: FALSE | J13: FALSE | K13: FALSE
A14: Насонов Денис Александрович | B14: к.т.н., старший научный сотрудник, центр «Сильный искусственный интеллект в промышленности, доцент ФТИИ | C14: Практики выполнения заказных НИОКТР в сфере ИИ по заказу индустрии: трансформация в учебные кейсы на основе КРМ | E14: ассинхрон | F14: Онлайн | G14: FALSE | H14: TRUE | J14: FALSE | K14: FALSE
A15: Иванов Сергей Владимирович | B15: к.т.н., С.н.с., центр «Сильный искусственный интеллект в промышленности, доцент ФТИИ | C15: ИИ-разработка ПО: основные подходы и доступный инструментарий - | D15: 46219 | E15: 10:00 - 11:30 | F15: Онлайн | G15: FALSE | H15: FALSE | J15: FALSE | K15: FALSE
A16: Ходненко Иван Владимирович | B16: к.т.н., старший научный сотрудник., «Национальный центр когнитивных разработок», старший преподаватель ФТИИ | C16: ИИ-разработка ПО: применение в учебном процессе для подготовки ИИспециалистов - | D16: 46219 | E16: 11:45 - 13:15 | F16: Онлайн | G16: FALSE | H16: FALSE | I16: https://t.me/Ivan_hod | J16: FALSE | K16: FALSE
A17: Ревин Илья Евгеньевич | B17: к.т.н., Руководитель группы разработки, ООО «ИТМО.ИСКИН» | C17: Создание инфраструктуры для аппаратного воплощения ИИ | E17: ассинхрон | F17: Онлайн | G17: FALSE | H17: TRUE | J17: FALSE | K17: FALSE
A18: Никитин Николай Олегович | B18: к.т.н., старший научный сотрудник, Исследовательский центр в сфере искусственного интеллекта «Сильный искусственный интеллект в промышленности, доцент ФТИИ | C18: Культура и экосистема отрытого кода в сфере ИИ в вузе | D18: 46220 | E18: 10:00 - 10:45 | F18: Онлайн | G18: FALSE | H18: FALSE | I18: https://t.me/nicl_nno | J18: FALSE | K18: FALSE
A19: Береснев Артем Дмитриевич | B19: к.т.н., Старший преподаватель, заместитель декана Факультета прикладной информатики (ФПИн) | C19: Особенности использования суперкомпьютерных, распределенных, облачных инфраструктур для обучения в сфере ИИ | D19: 46223 | E19: ассинхрон | F19: Онлайн | G19: FALSE | H19: TRUE | J19: FALSE | K19: FALSE
A20: Борисова Юлия Ивановна | B20: к.т.н., Младший научный сотрудник, исследовательский центр “Сильный ИИ в пром-ти”, ассистент факультета технологий ИИ | C20: Организация молодежных учебно-научных лаборатории в сфере ИИ | D20: 46224 | E20: 10:00 - 10:45 | F20: Онлайн | G20: FALSE | H20: FALSE | I20: https://t.me/ChrisLisbon | J20: FALSE | K20: FALSE
A21: Борисова Юлия Ивановна, Климова Александра Сергеевна | B21: Юлия - к.т.н., Младший научный сотрудник, исследовательский центр “Сильный ИИ в пром-ти”, ассистент факультета технологий ИИ; Александра - "к.т.н., Директор УМЦ Искусственный интеллект, Доцент ФТИИ Университет ИТМО" | C21: Вовлечение обучаемых в сфере ИИ в подготовку публикаций уровня А*/Q1 | D21: 46224 | E21: 10:55 - 12:25 | F21: Онлайн | G21: FALSE | H21: FALSE | I21: https://t.me/ChrisLisbon, https://t.me/caledonia_09 | J21: FALSE | K21: FALSE
A22: Толстиков | C22: Выездные мероприятия для обучаемых в сфере ИИ: конференции, школы, визиты к индустриальным партнерам | D22: 46225 | E22: 10:00 - 10:45 | F22: Онлайн | G22: FALSE | H22: FALSE | J22: FALSE | K22: FALSE
A23: Нурышева Меруерт | C23: Организация проектносоревновательной деятельности обучаемых в форме хакатонов | D23: 46225 | E23: 10:55 - 11:40 | F23: Онлайн | G23: FALSE | H23: FALSE | I23: https://t.me/Meruyert_nurysheva | J23: FALSE | K23: FALSE
A24: Юрий Валентинович Визильтер | B24: д.ф.-м.н., Директор по направлению "Технологии искусственного интеллекта" ГосНИИАС | C24: Ключевые направления и основные тренды развития ИИ | D24: 46230 | E24: 10:30 - 12:00 | F24: Очно: Ломоносова Трансляция | G24: FALSE | H24: TRUE | J24: FALSE | K24: FALSE
A25: Александр Валерьевич Бухановский | B25: Д.т.н., научный руководитель исследовательского центра «Сильный ИИ в промышленности» Современный ИИ в образовании | D25: 46230 | E25: 12:10 - 13:40 | F25: Очно: Ломоносова Трансляция | G25: FALSE | H25: FALSE | J25: FALSE | K25: FALSE

Sheet ОС4
B1: Moodle Feedback: Обратная связь по четвертой неделе обучения | cmid 688 | feedbackid 12 | обновлено 2026-07-27 00:23:08
B2: Тип ответа | C2: Completed ID | D2: Номер анонимного ответа | E2: Moodle user ID | F2: ФИО | G2: Почта | H2: Moodle ID number | I2: Course ID | J2: Дата изменения | K2: label | L2: 1. Оцените по шкале 1–10 уровень организации программы | M2: 2. Оцените по шкале 1–10 качество поддержки слушателей со стороны менеджеров | N2: 3. Насколько по шкале 1–10 удобен формат реализации программы ДПО по подготовке ППС? | O2: 4. Оцените качество лекции курса «Конструирование и разработка учебных дисциплин в сфере ИИ на основе КРМ» (лектор – Бухановский А.) по шкале 1–10 | P2: 5. Оцените качество лекции курса «Особенности организации программы ДПО» (лектор – Климова А.) по шкале 1–10 | Q2: 6. Оцените качество лекции курса «Преподавание современного ИИ: архитектуры, математика, оптимизация» (лектор – Хватов А.) по шкале 1–10 | R2: 7. Оцените качество лекции курса «Преподавание современного ИИ: машинное обучение» (лектор – Гладилин П.) по шкале 1–10 | S2: 8. Оцените качество лекции курса «Преподавание современного ИИ: глубокое обучение» (лектор – Аммар А.) по шкале 1–10 | T2: 9. Оцените качество лекции курса «Преподавание современного ИИ: большие языковые модели, агенты и генеративный ИИ» (лектор – Калюжная А.) по шкале 1–10 | U2: 10. Оцените качество лекции курса «Практики создания учебно-методических материалов в сфере ИИ на основе КРМ с использованием агентных технологий ИИ» (лектор – Духанов А.) по шкале 1–10 | V2: 11. Оцените качество лекции курса «Разработка РПД и комплексного фонда оценочных средств на основе КРМ: установочная сессия» (лектор – Бухановский А.) по шкале 1–10 | W2: 12. Оцените по шкале 1–10 качество работы трекера команды | X2: 13. Что конкретно вам понравилось в работе трекера? | Y2: 14. Что можно улучшить в работе трекера | Z2: 15. Оцените по шкале 1–10 доступность постановки практической задачи | AA2: 16. Оцените по шкале 1–10 удобство работы с платформой | AB2: 17. Что конкретно вам понравилось в работе платформы | AC2: 18. Что можно улучшить в работе платформы? | AD2: label

Sheet Кроссвалидация
A1: Проверяемая команда | B1: Куратор проверяемой команды | C1: Статус формы | D1: Отзыв отправлен | E1: Сумма баллов | F1: Максимум баллов | G1: Результат, % | H1: 1. Характеристики учебной дисциплины (оцениваются по рабочей программе дисциплины из Git-репозитория): Оригинальность: насколько необычной (редкой) является учебная дисциплина — Оценка (0–10) | I1: 1. Характеристики учебной дисциплины (оцениваются по рабочей программе дисциплины из Git-репозитория): Оригинальность: насколько необычной (редкой) является учебная дисциплина — Комментарий | J1: 2. Характеристики учебной дисциплины (оцениваются по рабочей программе дисциплины из Git-репозитория): Актуальность: насколько современным для выбранной области знания является содержание дисциплины — Оценка (0–10) | K1: 2. Характеристики учебной дисциплины (оцениваются по рабочей программе дисциплины из Git-репозитория): Актуальность: насколько современным для выбранной области знания является содержание дисциплины — Комментарий | L1: 3. Характеристики учебной дисциплины (оцениваются по рабочей программе дисциплины из Git-репозитория): Релевантность: насколько дисциплина соотносится с тематикой ИИ и ML — Оценка (0–10) | M1: 3. Характеристики учебной дисциплины (оцениваются по рабочей программе дисциплины из Git-репозитория): Релевантность: насколько дисциплина соотносится с тематикой ИИ и ML — Комментарий | N1: 4. Характеристики учебной дисциплины (оцениваются по рабочей программе дисциплины из Git-репозитория): Измеримость: насколько детализированы компетенции, индикаторы и уровни освоения, достаточны ли они для оценки результата обучения — Оценка (0–10) | O1: 4. Характеристики учебной дисциплины (оцениваются по рабочей программе дисциплины из Git-репозитория): Измеримость: насколько детализированы компетенции, индикаторы и уровни освоения, достаточны ли они для оценки результата обучения — Комментарий | P1: 5. Характеристики учебной дисциплины (оцениваются по рабочей программе дисциплины из Git-репозитория): Востребованность: насколько данная дисциплина востребована в отечественном образовательном ландшафте — Оценка (0–10) | Q1: 5. Характеристики учебной дисциплины (оцениваются по рабочей программе дисциплины из Git-репозитория): Востребованность: насколько данная дисциплина востребована в отечественном образовательном ландшафте — Комментарий | R1: 6. Характеристики учебной дисциплины (оцениваются по рабочей программе дисциплины из Git-репозитория): Ресурсоемкость: насколько сложно найти компетентных преподавателей и обеспечить инфраструктуру для реализации дисциплины — Оценка (0–10) | S1: 6. Характеристики учебной дисциплины (оцениваются по рабочей программе дисциплины из Git-репозитория): Ресурсоемкость: насколько сложно найти компетентных преподавателей и обеспечить инфраструктуру для реализации дисциплины — Комментарий | T1: 7. Характеристики фонда оценочных средств (оцениваются по содержимому Git-репозитория): В какой мере предложенный ФОС покрывает результаты обучения по дисциплине — Оценка (0–10) | U1: 7. Характеристики фонда оценочных средств (оцениваются по содержимому Git-репозитория): В какой мере предложенный ФОС покрывает результаты обучения по дисциплине — Комментарий | V1: 8. Характеристики фонда оценочных средств (оцениваются по содержимому Git-репозитория): Насколько качественно проработана модель измерения уровня освоения компетенций в дисциплине — Оценка (0–10) | W1: 8. Характеристики фонда оценочных средств (оцениваются по содержимому Git-репозитория): Насколько качественно проработана модель измерения уровня освоения компетенций в дисциплине — Комментарий | X1: 9. Характеристики фонда оценочных средств (оцениваются по содержимому Git-репозитория): Насколько разнообразны виды контрольно-измерительных материалов в репозитории — Оценка (0–10) | Y1: 9. Характеристики фонда оценочных средств (оцениваются по содержимому Git-репозитория): Насколько разнообразны виды контрольно-измерительных материалов в репозитории — Комментарий | Z1: 10. Характеристики фонда оценочных средств (оцениваются по содержимому Git-репозитория): Возможно ли тиражирование контрольно-измерительных материалов на другие дисциплины в данной области знания — Оценка (0–10) | AA1: 10. Характеристики фонда оценочных средств (оцениваются по содержимому Git-репозитория): Возможно ли тиражирование контрольно-измерительных материалов на другие дисциплины в данной области знания — Комментарий | AB1: 11. Характеристики фонда оценочных средств (оцениваются по содержимому Git-репозитория): Насколько практико-ориентированными являются контрольно-измерительные материалы и ресурсы для них — Оценка (0–10) | AC1: 11. Характеристики фонда оценочных средств (оцениваются по содержимому Git-репозитория): Насколько практико-ориентированными являются контрольно-измерительные материалы и ресурсы для них — Комментарий | AD1: 12. Характеристики фонда оценочных средств (оцениваются по содержимому Git-репозитория): Насколько оригинальными видятся данные, содержащиеся в ресурсах ФОС (оценочное суждение) — Оценка (0–10) | AE1: 12. Характеристики фонда оценочных средств (оцениваются по содержимому Git-репозитория): Насколько оригинальными видятся данные, содержащиеся в ресурсах ФОС (оценочное суждение) — Комментарий | AF1: 13. Характеристики фонда оценочных средств (оцениваются по содержимому Git-репозитория): Насколько оригинальными видятся программные коды, содержащиеся в ресурсах ФОС (оценочное суждение) — Оценка (0–10) | AG1: 13. Характеристики фонда оценочных средств (оцениваются по содержимому Git-репозитория): Насколько оригинальными видятся программные коды, содержащиеся в ресурсах ФОС (оценочное суждение) — Комментарий | AH1: 14. Характеристики фонда оценочных средств (оцениваются по содержимому Git-репозитория): Насколько трудоемкой видится подготовка такого ФОС (оценочное суждение) — Оценка (0–10) | AI1: 14. Характеристики фонда оценочных средств (оцениваются по содержимому Git-репозитория): Насколько трудоемкой видится подготовка такого ФОС (оценочное суждение) — Комментарий | AJ1: 15. Характеристики качества Git-репозитория: В репозитории наглядно представлено все содержимое, сделана удобная навигация — Оценка (0–10) | AK1: 15. Характеристики качества Git-репозитория: В репозитории наглядно представлено все содержимое, сделана удобная навигация — Комментарий | AL1: 16. Характеристики качества Git-репозитория: Контрольно-измерительные материалы и ресурсы ФОС хорошо документированы — Оценка (0–10) | AM1: 16. Характеристики качества Git-репозитория: Контрольно-измерительные материалы и ресурсы ФОС хорошо документированы — Комментарий | AN1: 17. Характеристики качества Git-репозитория: Методические указания по работе с ФОС для преподавателей информативны и полны — Оценка (0–10) | AO1: 17. Характеристики качества Git-репозитория: Методические указания по работе с ФОС для преподавателей информативны и полны — Комментарий | AP1: 18. Характеристики качества Git-репозитория: Методические указания по работе с ФОС для обучаемых информативны и полны — Оценка (0–10) | AQ1: 18. Характеристики качества Git-репозитория: Методические указания по работе с ФОС для обучаемых информативны и полны — Комментарий | AR1: 19. Характеристики качества Git-репозитория: Репозиторий производит ощущение логичного и законченного цифрового продукта (оценочное суждение) — Оценка (0–10) | AS1: 19. Характеристики качества Git-репозитория: Репозиторий производит ощущение логичного и законченного цифрового продукта (оценочное суждение) — Комментарий | AT1: 20. Характеристики качества Git-репозитория: Репозиторий соответствует требованиям установочной сессии данного ДПО (см. презентацию по занятию) — Оценка (0–10) | AU1: 20. Характеристики качества Git-репозитория: Репозиторий соответствует требованиям установочной сессии данного ДПО (см. презентацию по занятию) — Комментарий | AV1: 21. Характеристики качества Git-репозитория: Я (мы) бы хотел использовать материалы из репозитория в своем вузе (вузах) — Оценка (0–10) | AW1: 21. Характеристики качества Git-репозитория: Я (мы) бы хотел использовать материалы из репозитория в своем вузе (вузах) — Комментарий | AX1: Что хорошо | AY1: Что плохо | AZ1: Что ещё можно исправить и как
A2: Группа 7 | B2: =IFERROR(__xludf.DUMMYFUNCTION("IFERROR(XLOOKUP(VALUE(REGEXEXTRACT(A31,""\d+"")),'ПА 15.07'!G:G,'ПА 15.07'!H:H),"""")"),"Волчек Д.Г.") -> Волчек Д.Г. | C2: Черновик | E2: 174 | F2: 210 | G2: 82.9 | H2: 8 | I2: Дисциплина «Прикладной искусственный интеллект для систем умного дома» — достаточно редкая и специфичная. Большинство курсов по ИИ носят общий характер, а здесь фокус на умном доме с привязкой к реальным сенсорам, Edge-устройствам и Home Assistant. | J2: 9 | K2: Курс насыщен современным материалом: Edge AI, IoT-протоколы (MQTT, Zigbee), цифровые двойники, квантизация и pruning моделей, интеграция с Home Assistant. Всё это находится на переднем крае прикладного ИИ. | L2: 9 | M2: Дисциплина напрямую связана с ИИ и ML и представляет собой полноценный прикладной ИИ-курс: используются модели машинного обучения, глубокое обучение, валидация, интеграция моделей в реальные системы. | N2: 8 | O2: В репозитории представлена детальная модель измерения с указанием модулей, компетенций, индикаторов, уровней освоения, дескрипторов и форм контроля. Однако дескрипторы могли бы быть более гранулярными для каждого уровня освоения. | P2: 8 | Q2: Тематика умного дома и Edge AI востребована во многих вузах и программах ДПО. Курс имеет чёткую профориентационную направленность на роли ML Engineer, Data Engineer и AI Architect. | R2: 6 | S2: Для реализации дисциплины требуется доступ к реальным сенсорам (DHT22, PIR), Edge-устройствам, Home Assistant, а также компетентным преподавателям в области IoT и Edge AI. | T2: 9 | U2: ФОС покрывает все заявленные результаты обучения: от архитектурного кейса до защиты проекта. Каждый модуль имеет соответствующие оценочные средства, привязанные к компетенциям КРМ. | V2: 8 | W2: Модель измерения проработана на уровне «модуль → компетенция → индикатор → уровень → дескриптор → форма контроля → КИМ → ресурсы». Присутствует чёткая связь с трудовыми функциями. Не хватает более детальных рубрик для каждого уровня освоения. | X2: 9 | Y2: Представлены разнообразные виды: архитектурный кейс, практические работы с сенсорными данными, практические работы с моделями ИИ, Edge AI и интеграция, peer-review, экзамен, защита проекта. Это покрывает разные форматы оценки. | Z2: 8 | AA2: Материалы могут быть адаптированы для других дисциплин в области прикладного ИИ и IoT. Структура (модель измерения + КИМ + критерии) является хорошим шаблоном. Однако специфика умного дома требует доработки под другие домены. | AB2: 9 | AC2: Все оценочные средства максимально приближены к реальной практике: работа с реальными сенсорами, интеграция с Home Assistant, развёртывание на Edge, анализ ошибок, документирование. Проект требует работающего прототипа полного цикла. | AD2: 7 | AE2: В репозитории не представлены конкретные датасеты, но описаны требования к ним. Ожидается, что студенты будут работать с реальными сенсорными данными, что само по себе оригинально. Однако без примеров данных сложно оценить их уникальность. | AF2: 7 | AG2: В репозитории нет готовых программных кодов, только требования и описания. Оригинальность будет определяться студенческими решениями. Сам подход к интеграции ИИ с Home Assistant и Edge является достаточно новаторским. | AH2: 8 | AI2: Подготовка такого ФОС требует значительных усилий: нужно продумать интеграцию с реальным оборудованием, разработать критерии оценки для каждого этапа, подготовить шаблоны документации. Видно, что работа проделана большая. | AJ2: 9 | AK2: Репозиторий имеет чёткую структуру с быстрой навигацией по ключевым документам. Все файлы логично именованы и расположены. README на главной странице содержит всю необходимую информацию о дисциплине. | AL2: 8 | AM2: Все оценочные средства описаны в ASSESSMENT_TOOLS.md с указанием проверяемых компетенций. Ресурсы перечислены, но не все имеют прямые ссылки на внешние материалы. | AN2: 8 | AO2: PROJECT_REQUIREMENTS.md содержит детальные требования к проекту, включая функциональные и нефункциональные требования. Однако нет пошаговых инструкций по выполнению практических работ. | AP2: 9 | AQ2: Репозиторий производит впечатление законченного цифрового продукта: есть syllabus, информация о курсе, компетенции, трудовые функции, ФОС, требования к проекту, лицензия. Всё логически связано и образует единую систему. | AR2: 9 | AS2: Репозиторий производит впечатление логичного и законченного цифрового продукта. Он структурирован, информативен, эстетичен и готов к практическому применению. Недостающие элементы (гайды, примеры, активные ссылки) носят скорее рекомендательный характер. | AT2: 10 | AU2: Репозиторий полностью соответствует требованиям, предъявляемым к ФОС на установочной сессии. Он содержит все необходимые компоненты: РПД, развернутую модель измерения, КИМы по всем модулям, критерии оценивания и итоговую аттестацию. | AV2: 8 | AW2: Материалы репозитория могут быть использованы в вузе с некоторой адаптацией под локальную инфраструктуру. Особенно ценна модель измерения и связь с компетенциями КРМ. | AX2: − репозитории имеет чёткую, логичную структуру и удобную навигацию; − дисциплина очень актуальна и релевантна для области ИИ и ML, с фокусом на практическое применение в умном доме и Edge AI; − ФОС разнообразен и покрывает все заявленные компетенции; − присутствует детальная модель измерения с привязкой к трудовым функциям (ML Engineer, Data Engineer, AI Architect); − проектная работа требует создания работающего прототипа полного цикла, что обеспечивает высокую практико-ориентированность; − присутствует лицензия (MIT), что важно для открытого использования. | AY2: – | AZ2: − добавить более детальные рубрики оценивания для каждого уровня освоения компетенций; − включить примеры датасетов или ссылки на открытые источники данных для умного дома; − добавить примеры программных кодов или шаблонов для практических работ; − разработать отдельное методическое руководство для преподавателя с пошаговыми инструкциями по проведению каждого вида оценки; − добавить больше методических указаний для студентов по выполнению практических работ; − убедиться, что все ссылки на внешние ресурсы работают. Для этого необходимо: − дополнить модель измерения конкретными рубриками для каждого уровня (пороговый, продвинутый, экспертный). − создать папку examples/ с примерами кода для работы с сенсорами и интеграции с Home Assistant. − написать TEACHER_GUIDE.md с подробными сценариями проведения занятий и критериями оценки. − добавить STUDENT_GUIDE.md с пошаговыми инструкциями по выполнению практических работ и проекта. − включить в репозиторий ссылки на открытые датасеты или сгенерировать синтетические данные для демонстрации.

Sheet Посещаемость
A1: Фамилия | B1: Имя | C1: ID студента | D1: Адрес электронной почты | E1: L (Прямой эфир) | F1: R (Запись) | G1: Не просмотрено | H1: Посещено | I1: Процент | J1: Прогресс
A2: Bermudez Soto | B2: Jose Gregorio | C2: 791 | D2: sbermudes@sfedu.ru | E2: =IF($D2="","",COUNTIF('Импорт посещаемость'!I2:AE2,"L*")) -> 11 | F2: =IF($D2="","",COUNTIF('Импорт посещаемость'!I2:AE2,"R*")) -> 12 | G2: =IF($D2="","",MAX(0,COUNTA('Импорт посещаемость'!$I$1:$AE$1)-E2-F2)) -> 0 | H2: =IF($D2="","",E2+F2) -> 23 | I2: =IFERROR(H2/COUNTA('Импорт посещаемость'!$I$1:$AE$1),"") -> 1 | J2: =IFERROR(__xludf.DUMMYFUNCTION("IF($D2="""","""",SPARKLINE(I2,{""charttype"",""bar"";""max"",1;""color1"",""#FFFFFF""}))"),"")
A3: LMS | B3: expert2025 | C3: 583 | D3: 2025expert2025@mail.ru | E3: =IF($D3="","",COUNTIF(#REF!,"L*")) -> #REF! | F3: =IF($D3="","",COUNTIF(#REF!,"R*")) -> #REF! | G3: =IF($D3="","",MAX(0,COUNTA('Импорт посещаемость'!$I$1:$AE$1)-E3-F3)) -> #REF! | H3: =IF($D3="","",E3+F3) -> #REF! | I3: =IFERROR(H3/COUNTA('Импорт посещаемость'!$I$1:$AE$1),"") | J3: =IFERROR(__xludf.DUMMYFUNCTION("IF($D3="""","""",SPARKLINE(I3,{""charttype"",""bar"";""max"",1;""color1"",""#FFFFFF""}))"),"")
A4: Succi | B4: Giancarlo | C4: 500 | D4: giancarlo.succi@gmail.com | E4: =IF($D4="","",COUNTIF('Импорт посещаемость'!I3:AE3,"L*")) -> 0 | F4: =IF($D4="","",COUNTIF('Импорт посещаемость'!I3:AE3,"R*")) -> 1 | G4: =IF($D4="","",MAX(0,COUNTA('Импорт посещаемость'!$I$1:$AE$1)-E4-F4)) -> 22 | H4: =IF($D4="","",E4+F4) -> 1 | I4: =IFERROR(H4/COUNTA('Импорт посещаемость'!$I$1:$AE$1),"") -> 0.043478261 | J4: =IFERROR(__xludf.DUMMYFUNCTION("IF($D4="""","""",SPARKLINE(I4,{""charttype"",""bar"";""max"",1;""color1"",""#FFFFFF""}))"),"")
A5: tyukov | B5: Anton | C5: 275 | D5: anton.tyukov@gmail.com | E5: =IF($D5="","",COUNTIF(#REF!,"L*")) -> #REF! | F5: =IF($D5="","",COUNTIF(#REF!,"R*")) -> #REF! | G5: =IF($D5="","",MAX(0,COUNTA('Импорт посещаемость'!$I$1:$AE$1)-E5-F5)) -> #REF! | H5: =IF($D5="","",E5+F5) -> #REF! | I5: =IFERROR(H5/COUNTA('Импорт посещаемость'!$I$1:$AE$1),"") | J5: =IFERROR(__xludf.DUMMYFUNCTION("IF($D5="""","""",SPARKLINE(I5,{""charttype"",""bar"";""max"",1;""color1"",""#FFFFFF""}))"),"")
A6: User | B6: Test | C6: 282 | D6: maxsannikovmax@gmail.com | E6: =IF($D6="","",COUNTIF('Импорт посещаемость'!I4:AE4,"L*")) -> 4 | F6: =IF($D6="","",COUNTIF('Импорт посещаемость'!I4:AE4,"R*")) -> 7 | G6: =IF($D6="","",MAX(0,COUNTA('Импорт посещаемость'!$I$1:$AE$1)-E6-F6)) -> 12 | H6: =IF($D6="","",E6+F6) -> 11 | I6: =IFERROR(H6/COUNTA('Импорт посещаемость'!$I$1:$AE$1),"") -> 0.47826087 | J6: =IFERROR(__xludf.DUMMYFUNCTION("IF($D6="""","""",SPARKLINE(I6,{""charttype"",""bar"";""max"",1;""color1"",""#FFFFFF""}))"),"")
A7: Абрамович | B7: Александра | C7: 743 | D7: ayabramovich@mail.ru | E7: =IF($D7="","",COUNTIF(#REF!,"L*")) -> #REF! | F7: =IF($D7="","",COUNTIF(#REF!,"R*")) -> #REF! | G7: =IF($D7="","",MAX(0,COUNTA('Импорт посещаемость'!$I$1:$AE$1)-E7-F7)) -> #REF! | H7: =IF($D7="","",E7+F7) -> #REF! | I7: =IFERROR(H7/COUNTA('Импорт посещаемость'!$I$1:$AE$1),"") | J7: =IFERROR(__xludf.DUMMYFUNCTION("IF($D7="""","""",SPARKLINE(I7,{""charttype"",""bar"";""max"",1;""color1"",""#FFFFFF""}))"),"")
A8: Авдюшина | B8: Анна | C8: 810 | D8: avdushina98@gmail.com | E8: =IF($D8="","",COUNTIF('Импорт посещаемость'!I5:AE5,"L*")) -> 10 | F8: =IF($D8="","",COUNTIF('Импорт посещаемость'!I5:AE5,"R*")) -> 13 | G8: =IF($D8="","",MAX(0,COUNTA('Импорт посещаемость'!$I$1:$AE$1)-E8-F8)) -> 0 | H8: =IF($D8="","",E8+F8) -> 23 | I8: =IFERROR(H8/COUNTA('Импорт посещаемость'!$I$1:$AE$1),"") -> 1 | J8: =IFERROR(__xludf.DUMMYFUNCTION("IF($D8="""","""",SPARKLINE(I8,{""charttype"",""bar"";""max"",1;""color1"",""#FFFFFF""}))"),"")
A9: Агарева | B9: Ольга | C9: 680 | D9: oyagareva@mephi.ru | E9: =IF($D9="","",COUNTIF('Импорт посещаемость'!I6:AE6,"L*")) -> 1 | F9: =IF($D9="","",COUNTIF('Импорт посещаемость'!I6:AE6,"R*")) -> 6 | G9: =IF($D9="","",MAX(0,COUNTA('Импорт посещаемость'!$I$1:$AE$1)-E9-F9)) -> 16 | H9: =IF($D9="","",E9+F9) -> 7 | I9: =IFERROR(H9/COUNTA('Импорт посещаемость'!$I$1:$AE$1),"") -> 0.30434783 | J9: =IFERROR(__xludf.DUMMYFUNCTION("IF($D9="""","""",SPARKLINE(I9,{""charttype"",""bar"";""max"",1;""color1"",""#FFFFFF""}))"),"")
A10: Акиньшина | B10: Вера | C10: 269 | D10: ak-vera@yandex.ru | E10: =IF($D10="","",COUNTIF('Импорт посещаемость'!I7:AE7,"L*")) -> 17 | F10: =IF($D10="","",COUNTIF('Импорт посещаемость'!I7:AE7,"R*")) -> 5 | G10: =IF($D10="","",MAX(0,COUNTA('Импорт посещаемость'!$I$1:$AE$1)-E10-F10)) -> 1 | H10: =IF($D10="","",E10+F10) -> 22 | I10: =IFERROR(H10/COUNTA('Импорт посещаемость'!$I$1:$AE$1),"") -> 0.95652174 | J10: =IFERROR(__xludf.DUMMYFUNCTION("IF($D10="""","""",SPARKLINE(I10,{""charttype"",""bar"";""max"",1;""color1"",""#FFFFFF""}))"),"")
A11: Алексей | B11: Баев | C11: 440 | D11: baevaa@volgatech.net | E11: =IF($D11="","",COUNTIF('Импорт посещаемость'!I8:AE8,"L*")) -> 16 | F11: =IF($D11="","",COUNTIF('Импорт посещаемость'!I8:AE8,"R*")) -> 7 | G11: =IF($D11="","",MAX(0,COUNTA('Импорт посещаемость'!$I$1:$AE$1)-E11-F11)) -> 0 | H11: =IF($D11="","",E11+F11) -> 23 | I11: =IFERROR(H11/COUNTA('Импорт посещаемость'!$I$1:$AE$1),"") -> 1 | J11: =IFERROR(__xludf.DUMMYFUNCTION("IF($D11="""","""",SPARKLINE(I11,{""charttype"",""bar"";""max"",1;""color1"",""#FFFFFF""}))"),"")
A12: Алексей | B12: Баранчиков | C12: 717 | D12: alexib@inbox.ru | E12: =IF($D12="","",COUNTIF('Импорт посещаемость'!I9:AE9,"L*")) -> 13 | F12: =IF($D12="","",COUNTIF('Импорт посещаемость'!I9:AE9,"R*")) -> 10 | G12: =IF($D12="","",MAX(0,COUNTA('Импорт посещаемость'!$I$1:$AE$1)-E12-F12)) -> 0 | H12: =IF($D12="","",E12+F12) -> 23 | I12: =IFERROR(H12/COUNTA('Импорт посещаемость'!$I$1:$AE$1),"") -> 1 | J12: =IFERROR(__xludf.DUMMYFUNCTION("IF($D12="""","""",SPARKLINE(I12,{""charttype"",""bar"";""max"",1;""color1"",""#FFFFFF""}))"),"")
A13: Али | B13: Бушра | C13: 686 | D13: bushraali9@yandex.ru | E13: =IF($D13="","",COUNTIF('Импорт посещаемость'!I10:AE10,"L*")) -> 17 | F13: =IF($D13="","",COUNTIF('Импорт посещаемость'!I10:AE10,"R*")) -> 4 | G13: =IF($D13="","",MAX(0,COUNTA('Импорт посещаемость'!$I$1:$AE$1)-E13-F13)) -> 2 | H13: =IF($D13="","",E13+F13) -> 21 | I13: =IFERROR(H13/COUNTA('Импорт посещаемость'!$I$1:$AE$1),"") -> 0.91304348 | J13: =IFERROR(__xludf.DUMMYFUNCTION("IF($D13="""","""",SPARKLINE(I13,{""charttype"",""bar"";""max"",1;""color1"",""#FFFFFF""}))"),"")
A14: Амосова | B14: Светлана | C14: 648 | D14: amosovasg@yandex.ru | E14: =IF($D14="","",COUNTIF('Импорт посещаемость'!I11:AE11,"L*")) -> 9 | F14: =IF($D14="","",COUNTIF('Импорт посещаемость'!I11:AE11,"R*")) -> 14 | G14: =IF($D14="","",MAX(0,COUNTA('Импорт посещаемость'!$I$1:$AE$1)-E14-F14)) -> 0 | H14: =IF($D14="","",E14+F14) -> 23 | I14: =IFERROR(H14/COUNTA('Импорт посещаемость'!$I$1:$AE$1),"") -> 1 | J14: =IFERROR(__xludf.DUMMYFUNCTION("IF($D14="""","""",SPARKLINE(I14,{""charttype"",""bar"";""max"",1;""color1"",""#FFFFFF""}))"),"")
A15: Анастасия | B15: Федоренко | C15: 782 | D15: fedorenko-ao@rudn.ru | E15: =IF($D15="","",COUNTIF('Импорт посещаемость'!I12:AE12,"L*")) -> 16 | F15: =IF($D15="","",COUNTIF('Импорт посещаемость'!I12:AE12,"R*")) -> 7 | G15: =IF($D15="","",MAX(0,COUNTA('Импорт посещаемость'!$I$1:$AE$1)-E15-F15)) -> 0 | H15: =IF($D15="","",E15+F15) -> 23 | I15: =IFERROR(H15/COUNTA('Импорт посещаемость'!$I$1:$AE$1),"") -> 1 | J15: =IFERROR(__xludf.DUMMYFUNCTION("IF($D15="""","""",SPARKLINE(I15,{""charttype"",""bar"";""max"",1;""color1"",""#FFFFFF""}))"),"")
A16: Андрей | B16: Тягунов | C16: 462 | D16: adi8@yandex.ru | E16: =IF($D16="","",COUNTIF('Импорт посещаемость'!I13:AE13,"L*")) -> 4 | F16: =IF($D16="","",COUNTIF('Импорт посещаемость'!I13:AE13,"R*")) -> 1 | G16: =IF($D16="","",MAX(0,COUNTA('Импорт посещаемость'!$I$1:$AE$1)-E16-F16)) -> 18 | H16: =IF($D16="","",E16+F16) -> 5 | I16: =IFERROR(H16/COUNTA('Импорт посещаемость'!$I$1:$AE$1),"") -> 0.2173913 | J16: =IFERROR(__xludf.DUMMYFUNCTION("IF($D16="""","""",SPARKLINE(I16,{""charttype"",""bar"";""max"",1;""color1"",""#FFFFFF""}))"),"")
A17: Андриянов | B17: Никита | C17: 681 | D17: naandriyanov@fa.ru | E17: =IF($D17="","",COUNTIF('Импорт посещаемость'!I14:AE14,"L*")) -> 5 | F17: =IF($D17="","",COUNTIF('Импорт посещаемость'!I14:AE14,"R*")) -> 17 | G17: =IF($D17="","",MAX(0,COUNTA('Импорт посещаемость'!$I$1:$AE$1)-E17-F17)) -> 1 | H17: =IF($D17="","",E17+F17) -> 22 | I17: =IFERROR(H17/COUNTA('Импорт посещаемость'!$I$1:$AE$1),"") -> 0.95652174 | J17: =IFERROR(__xludf.DUMMYFUNCTION("IF($D17="""","""",SPARKLINE(I17,{""charttype"",""bar"";""max"",1;""color1"",""#FFFFFF""}))"),"")
A18: Анисова | B18: Мария | C18: 785 | D18: m.anisova@g.nsu.ru | E18: =IF($D18="","",COUNTIF('Импорт посещаемость'!I15:AE15,"L*")) -> 1 | F18: =IF($D18="","",COUNTIF('Импорт посещаемость'!I15:AE15,"R*")) -> 22 | G18: =IF($D18="","",MAX(0,COUNTA('Импорт посещаемость'!$I$1:$AE$1)-E18-F18)) -> 0 | H18: =IF($D18="","",E18+F18) -> 23 | I18: =IFERROR(H18/COUNTA('Импорт посещаемость'!$I$1:$AE$1),"") -> 1 | J18: =IFERROR(__xludf.DUMMYFUNCTION("IF($D18="""","""",SPARKLINE(I18,{""charttype"",""bar"";""max"",1;""color1"",""#FFFFFF""}))"),"")
A19: Артемова | B19: Светлана | C19: 621 | D19: seartemova@fa.ru | E19: =IF($D19="","",COUNTIF('Импорт посещаемость'!I16:AE16,"L*")) -> 15 | F19: =IF($D19="","",COUNTIF('Импорт посещаемость'!I16:AE16,"R*")) -> 6 | G19: =IF($D19="","",MAX(0,COUNTA('Импорт посещаемость'!$I$1:$AE$1)-E19-F19)) -> 2 | H19: =IF($D19="","",E19+F19) -> 21 | I19: =IFERROR(H19/COUNTA('Импорт посещаемость'!$I$1:$AE$1),"") -> 0.91304348 | J19: =IFERROR(__xludf.DUMMYFUNCTION("IF($D19="""","""",SPARKLINE(I19,{""charttype"",""bar"";""max"",1;""color1"",""#FFFFFF""}))"),"")
A20: Бабушкин | B20: Максим | C20: 280 | D20: hitmaxd11@mail.ru | E20: =IF($D20="","",COUNTIF('Импорт посещаемость'!I17:AE17,"L*")) -> 14 | F20: =IF($D20="","",COUNTIF('Импорт посещаемость'!I17:AE17,"R*")) -> 9 | G20: =IF($D20="","",MAX(0,COUNTA('Импорт посещаемость'!$I$1:$AE$1)-E20-F20)) -> 0 | H20: =IF($D20="","",E20+F20) -> 23 | I20: =IFERROR(H20/COUNTA('Импорт посещаемость'!$I$1:$AE$1),"") -> 1 | J20: =IFERROR(__xludf.DUMMYFUNCTION("IF($D20="""","""",SPARKLINE(I20,{""charttype"",""bar"";""max"",1;""color1"",""#FFFFFF""}))"),"")
A21: Баглий | B21: Антон | C21: 796 | D21: abagly@sfedu.ru | E21: =IF($D21="","",COUNTIF('Импорт посещаемость'!I18:AE18,"L*")) -> 2 | F21: =IF($D21="","",COUNTIF('Импорт посещаемость'!I18:AE18,"R*")) -> 20 | G21: =IF($D21="","",MAX(0,COUNTA('Импорт посещаемость'!$I$1:$AE$1)-E21-F21)) -> 1 | H21: =IF($D21="","",E21+F21) -> 22 | I21: =IFERROR(H21/COUNTA('Импорт посещаемость'!$I$1:$AE$1),"") -> 0.95652174 | J21: =IFERROR(__xludf.DUMMYFUNCTION("IF($D21="""","""",SPARKLINE(I21,{""charttype"",""bar"";""max"",1;""color1"",""#FFFFFF""}))"),"")
A22: Багмутов | B22: Александр | C22: 747 | D22: bagmutov94@mail.ru | E22: =IF($D22="","",COUNTIF('Импорт посещаемость'!I19:AE19,"L*")) -> 15 | F22: =IF($D22="","",COUNTIF('Импорт посещаемость'!I19:AE19,"R*")) -> 8 | G22: =IF($D22="","",MAX(0,COUNTA('Импорт посещаемость'!$I$1:$AE$1)-E22-F22)) -> 0 | H22: =IF($D22="","",E22+F22) -> 23 | I22: =IFERROR(H22/COUNTA('Импорт посещаемость'!$I$1:$AE$1),"") -> 1 | J22: =IFERROR(__xludf.DUMMYFUNCTION("IF($D22="""","""",SPARKLINE(I22,{""charttype"",""bar"";""max"",1;""color1"",""#FFFFFF""}))"),"")
A23: Бакнин | B23: Максим | C23: 678 | D23: baknin@rgau-msha.ru | E23: =IF($D23="","",COUNTIF('Импорт посещаемость'!I20:AE20,"L*")) -> 7 | F23: =IF($D23="","",COUNTIF('Импорт посещаемость'!I20:AE20,"R*")) -> 2 | G23: =IF($D23="","",MAX(0,COUNTA('Импорт посещаемость'!$I$1:$AE$1)-E23-F23)) -> 14 | H23: =IF($D23="","",E23+F23) -> 9 | I23: =IFERROR(H23/COUNTA('Импорт посещаемость'!$I$1:$AE$1),"") -> 0.39130435 | J23: =IFERROR(__xludf.DUMMYFUNCTION("IF($D23="""","""",SPARKLINE(I23,{""charttype"",""bar"";""max"",1;""color1"",""#FFFFFF""}))"),"")
A24: Бакулев | B24: Александр | C24: 758 | D24: contact-bav@mail.ru | E24: =IF($D24="","",COUNTIF('Импорт посещаемость'!I21:AE21,"L*")) -> 16 | F24: =IF($D24="","",COUNTIF('Импорт посещаемость'!I21:AE21,"R*")) -> 7 | G24: =IF($D24="","",MAX(0,COUNTA('Импорт посещаемость'!$I$1:$AE$1)-E24-F24)) -> 0 | H24: =IF($D24="","",E24+F24) -> 23 | I24: =IFERROR(H24/COUNTA('Импорт посещаемость'!$I$1:$AE$1),"") -> 1 | J24: =IFERROR(__xludf.DUMMYFUNCTION("IF($D24="""","""",SPARKLINE(I24,{""charttype"",""bar"";""max"",1;""color1"",""#FFFFFF""}))"),"")
A25: Бакулева | B25: Марина | C25: 406 | D25: m.a.bakuleva@yandex.ru | E25: =IF($D25="","",COUNTIF('Импорт посещаемость'!I22:AE22,"L*")) -> 12 | F25: =IF($D25="","",COUNTIF('Импорт посещаемость'!I22:AE22,"R*")) -> 10 | G25: =IF($D25="","",MAX(0,COUNTA('Импорт посещаемость'!$I$1:$AE$1)-E25-F25)) -> 1 | H25: =IF($D25="","",E25+F25) -> 22 | I25: =IFERROR(H25/COUNTA('Импорт посещаемость'!$I$1:$AE$1),"") -> 0.95652174 | J25: =IFERROR(__xludf.DUMMYFUNCTION("IF($D25="""","""",SPARKLINE(I25,{""charttype"",""bar"";""max"",1;""color1"",""#FFFFFF""}))"),"")
A26: Бартева | B26: Виктория | C26: 720 | D26: fishka91@yandex.ru | E26: =IF($D26="","",COUNTIF('Импорт посещаемость'!I23:AE23,"L*")) -> 10 | F26: =IF($D26="","",COUNTIF('Импорт посещаемость'!I23:AE23,"R*")) -> 4 | G26: =IF($D26="","",MAX(0,COUNTA('Импорт посещаемость'!$I$1:$AE$1)-E26-F26)) -> 9 | H26: =IF($D26="","",E26+F26) -> 14 | I26: =IFERROR(H26/COUNTA('Импорт посещаемость'!$I$1:$AE$1),"") -> 0.60869565 | J26: =IFERROR(__xludf.DUMMYFUNCTION("IF($D26="""","""",SPARKLINE(I26,{""charttype"",""bar"";""max"",1;""color1"",""#FFFFFF""}))"),"")
A27: Бастрычкин | B27: Александр | C27: 671 | D27: a_s_bas@mail.ru | E27: =IF($D27="","",COUNTIF('Импорт посещаемость'!I24:AE24,"L*")) -> 10 | F27: =IF($D27="","",COUNTIF('Импорт посещаемость'!I24:AE24,"R*")) -> 13 | G27: =IF($D27="","",MAX(0,COUNTA('Импорт посещаемость'!$I$1:$AE$1)-E27-F27)) -> 0 | H27: =IF($D27="","",E27+F27) -> 23 | I27: =IFERROR(H27/COUNTA('Импорт посещаемость'!$I$1:$AE$1),"") -> 1 | J27: =IFERROR(__xludf.DUMMYFUNCTION("IF($D27="""","""",SPARKLINE(I27,{""charttype"",""bar"";""max"",1;""color1"",""#FFFFFF""}))"),"")
A28: Башуров | B28: Вячеслав | C28: 776 | D28: bashurovvv@gmail.com | E28: =IF($D28="","",COUNTIF('Импорт посещаемость'!I25:AE25,"L*")) -> 0 | F28: =IF($D28="","",COUNTIF('Импорт посещаемость'!I25:AE25,"R*")) -> 7 | G28: =IF($D28="","",MAX(0,COUNTA('Импорт посещаемость'!$I$1:$AE$1)-E28-F28)) -> 16 | H28: =IF($D28="","",E28+F28) -> 7 | I28: =IFERROR(H28/COUNTA('Импорт посещаемость'!$I$1:$AE$1),"") -> 0.30434783 | J28: =IFERROR(__xludf.DUMMYFUNCTION("IF($D28="""","""",SPARKLINE(I28,{""charttype"",""bar"";""max"",1;""color1"",""#FFFFFF""}))"),"")
A29: Безуглая | B29: Анна | C29: 301 | D29: aebezuglaya@sevsu.ru | E29: =IF($D29="","",COUNTIF('Импорт посещаемость'!I26:AE26,"L*")) -> 4 | F29: =IF($D29="","",COUNTIF('Импорт посещаемость'!I26:AE26,"R*")) -> 19 | G29: =IF($D29="","",MAX(0,COUNTA('Импорт посещаемость'!$I$1:$AE$1)-E29-F29)) -> 0 | H29: =IF($D29="","",E29+F29) -> 23 | I29: =IFERROR(H29/COUNTA('Импорт посещаемость'!$I$1:$AE$1),"") -> 1 | J29: =IFERROR(__xludf.DUMMYFUNCTION("IF($D29="""","""",SPARKLINE(I29,{""charttype"",""bar"";""max"",1;""color1"",""#FFFFFF""}))"),"")
A30: Белов | B30: Владимир | C30: 691 | D30: vvbeloff@yandex.ru | E30: =IF($D30="","",COUNTIF('Импорт посещаемость'!I27:AE27,"L*")) -> 12 | F30: =IF($D30="","",COUNTIF('Импорт посещаемость'!I27:AE27,"R*")) -> 5 | G30: =IF($D30="","",MAX(0,COUNTA('Импорт посещаемость'!$I$1:$AE$1)-E30-F30)) -> 6 | H30: =IF($D30="","",E30+F30) -> 17 | I30: =IFERROR(H30/COUNTA('Импорт посещаемость'!$I$1:$AE$1),"") -> 0.73913043 | J30: =IFERROR(__xludf.DUMMYFUNCTION("IF($D30="""","""",SPARKLINE(I30,{""charttype"",""bar"";""max"",1;""color1"",""#FFFFFF""}))"),"")
A31: Белоусов | B31: Иван | C31: 599 | D31: i_belousov@mail.ru | E31: =IF($D31="","",COUNTIF('Импорт посещаемость'!I28:AE28,"L*")) -> 17 | F31: =IF($D31="","",COUNTIF('Импорт посещаемость'!I28:AE28,"R*")) -> 2 | G31: =IF($D31="","",MAX(0,COUNTA('Импорт посещаемость'!$I$1:$AE$1)-E31-F31)) -> 4 | H31: =IF($D31="","",E31+F31) -> 19 | I31: =IFERROR(H31/COUNTA('Импорт посещаемость'!$I$1:$AE$1),"") -> 0.82608696 | J31: =IFERROR(__xludf.DUMMYFUNCTION("IF($D31="""","""",SPARKLINE(I31,{""charttype"",""bar"";""max"",1;""color1"",""#FFFFFF""}))"),"")
A32: Белоцерковский | B32: Валерий | C32: 625 | D32: v.belotserkovskii@g.nsu.ru | E32: =IF($D32="","",COUNTIF('Импорт посещаемость'!I29:AE29,"L*")) -> 10 | F32: =IF($D32="","",COUNTIF('Импорт посещаемость'!I29:AE29,"R*")) -> 13 | G32: =IF($D32="","",MAX(0,COUNTA('Импорт посещаемость'!$I$1:$AE$1)-E32-F32)) -> 0 | H32: =IF($D32="","",E32+F32) -> 23 | I32: =IFERROR(H32/COUNTA('Импорт посещаемость'!$I$1:$AE$1),"") -> 1 | J32: =IFERROR(__xludf.DUMMYFUNCTION("IF($D32="""","""",SPARKLINE(I32,{""charttype"",""bar"";""max"",1;""color1"",""#FFFFFF""}))"),"")
A33: Беляева | B33: Юлия | C33: 590 | D33: yilia-b@yandex.ru | E33: =IF($D33="","",COUNTIF('Импорт посещаемость'!I30:AE30,"L*")) -> 0 | F33: =IF($D33="","",COUNTIF('Импорт посещаемость'!I30:AE30,"R*")) -> 13 | G33: =IF($D33="","",MAX(0,COUNTA('Импорт посещаемость'!$I$1:$AE$1)-E33-F33)) -> 10 | H33: =IF($D33="","",E33+F33) -> 13 | I33: =IFERROR(H33/COUNTA('Импорт посещаемость'!$I$1:$AE$1),"") -> 0.56521739 | J33: =IFERROR(__xludf.DUMMYFUNCTION("IF($D33="""","""",SPARKLINE(I33,{""charttype"",""bar"";""max"",1;""color1"",""#FFFFFF""}))"),"")
A34: Беспалов | B34: Сергей | C34: 770 | D34: 8yp3r10@gmail.com | E34: =IF($D34="","",COUNTIF('Импорт посещаемость'!I31:AE31,"L*")) -> 2 | F34: =IF($D34="","",COUNTIF('Импорт посещаемость'!I31:AE31,"R*")) -> 12 | G34: =IF($D34="","",MAX(0,COUNTA('Импорт посещаемость'!$I$1:$AE$1)-E34-F34)) -> 9 | H34: =IF($D34="","",E34+F34) -> 14 | I34: =IFERROR(H34/COUNTA('Импорт посещаемость'!$I$1:$AE$1),"") -> 0.60869565 | J34: =IFERROR(__xludf.DUMMYFUNCTION("IF($D34="""","""",SPARKLINE(I34,{""charttype"",""bar"";""max"",1;""color1"",""#FFFFFF""}))"),"")
A35: Бодур | B35: Айсу | C35: 638 | D35: bodur_a@rgau-msha.ru | E35: =IF($D35="","",COUNTIF('Импорт посещаемость'!I32:AE32,"L*")) -> 0 | F35: =IF($D35="","",COUNTIF('Импорт посещаемость'!I32:AE32,"R*")) -> 22 | G35: =IF($D35="","",MAX(0,COUNTA('Импорт посещаемость'!$I$1:$AE$1)-E35-F35)) -> 1 | H35: =IF($D35="","",E35+F35) -> 22 | I35: =IFERROR(H35/COUNTA('Импорт посещаемость'!$I$1:$AE$1),"") -> 0.95652174 | J35: =IFERROR(__xludf.DUMMYFUNCTION("IF($D35="""","""",SPARKLINE(I35,{""charttype"",""bar"";""max"",1;""color1"",""#FFFFFF""}))"),"")
A36: Бондарев | B36: Владимир | C36: 322 | D36: bondarev@sevsu.ru | E36: =IF($D36="","",COUNTIF('Импорт посещаемость'!I33:AE33,"L*")) -> 8 | F36: =IF($D36="","",COUNTIF('Импорт посещаемость'!I33:AE33,"R*")) -> 15 | G36: =IF($D36="","",MAX(0,COUNTA('Импорт посещаемость'!$I$1:$AE$1)-E36-F36)) -> 0 | H36: =IF($D36="","",E36+F36) -> 23 | I36: =IFERROR(H36/COUNTA('Импорт посещаемость'!$I$1:$AE$1),"") -> 1 | J36: =IFERROR(__xludf.DUMMYFUNCTION("IF($D36="""","""",SPARKLINE(I36,{""charttype"",""bar"";""max"",1;""color1"",""#FFFFFF""}))"),"")
A37: Борель | B37: Лидия | C37: 303 | D37: lidiya904@yandex.ru | E37: =IF($D37="","",COUNTIF('Импорт посещаемость'!I34:AE34,"L*")) -> 17 | F37: =IF($D37="","",COUNTIF('Импорт посещаемость'!I34:AE34,"R*")) -> 6 | G37: =IF($D37="","",MAX(0,COUNTA('Импорт посещаемость'!$I$1:$AE$1)-E37-F37)) -> 0 | H37: =IF($D37="","",E37+F37) -> 23 | I37: =IFERROR(H37/COUNTA('Импорт посещаемость'!$I$1:$AE$1),"") -> 1 | J37: =IFERROR(__xludf.DUMMYFUNCTION("IF($D37="""","""",SPARKLINE(I37,{""charttype"",""bar"";""max"",1;""color1"",""#FFFFFF""}))"),"")
A38: Борзин | B38: Роман | C38: 719 | D38: roma.borzin@mail.ru | E38: =IF($D38="","",COUNTIF('Импорт посещаемость'!I35:AE35,"L*")) -> 2 | F38: =IF($D38="","",COUNTIF('Импорт посещаемость'!I35:AE35,"R*")) -> 21 | G38: =IF($D38="","",MAX(0,COUNTA('Импорт посещаемость'!$I$1:$AE$1)-E38-F38)) -> 0 | H38: =IF($D38="","",E38+F38) -> 23 | I38: =IFERROR(H38/COUNTA('Импорт посещаемость'!$I$1:$AE$1),"") -> 1 | J38: =IFERROR(__xludf.DUMMYFUNCTION("IF($D38="""","""",SPARKLINE(I38,{""charttype"",""bar"";""max"",1;""color1"",""#FFFFFF""}))"),"")
A39: Борисов | B39: Василий | C39: 457 | D39: funkyvas@ya.ru | E39: =IF($D39="","",COUNTIF('Импорт посещаемость'!I36:AE36,"L*")) -> 3 | F39: =IF($D39="","",COUNTIF('Импорт посещаемость'!I36:AE36,"R*")) -> 20 | G39: =IF($D39="","",MAX(0,COUNTA('Импорт посещаемость'!$I$1:$AE$1)-E39-F39)) -> 0 | H39: =IF($D39="","",E39+F39) -> 23 | I39: =IFERROR(H39/COUNTA('Импорт посещаемость'!$I$1:$AE$1),"") -> 1 | J39: =IFERROR(__xludf.DUMMYFUNCTION("IF($D39="""","""",SPARKLINE(I39,{""charttype"",""bar"";""max"",1;""color1"",""#FFFFFF""}))"),"")
A40: Бородин | B40: Андрей | C40: 416 | D40: borodinav@volgatech.net | E40: =IF($D40="","",COUNTIF('Импорт посещаемость'!I37:AE37,"L*")) -> 9 | F40: =IF($D40="","",COUNTIF('Импорт посещаемость'!I37:AE37,"R*")) -> 14 | G40: =IF($D40="","",MAX(0,COUNTA('Импорт посещаемость'!$I$1:$AE$1)-E40-F40)) -> 0 | H40: =IF($D40="","",E40+F40) -> 23 | I40: =IFERROR(H40/COUNTA('Импорт посещаемость'!$I$1:$AE$1),"") -> 1 | J40: =IFERROR(__xludf.DUMMYFUNCTION("IF($D40="""","""",SPARKLINE(I40,{""charttype"",""bar"";""max"",1;""color1"",""#FFFFFF""}))"),"")
A41: Брюховецкий | B41: Алексей | C41: 346 | D41: a.alexir@mail.ru | E41: =IF($D41="","",COUNTIF('Импорт посещаемость'!I38:AE38,"L*")) -> 11 | F41: =IF($D41="","",COUNTIF('Импорт посещаемость'!I38:AE38,"R*")) -> 12 | G41: =IF($D41="","",MAX(0,COUNTA('Импорт посещаемость'!$I$1:$AE$1)-E41-F41)) -> 0 | H41: =IF($D41="","",E41+F41) -> 23 | I41: =IFERROR(H41/COUNTA('Импорт посещаемость'!$I$1:$AE$1),"") -> 1 | J41: =IFERROR(__xludf.DUMMYFUNCTION("IF($D41="""","""",SPARKLINE(I41,{""charttype"",""bar"";""max"",1;""color1"",""#FFFFFF""}))"),"")
A42: Булычев | B42: Александр | C42: 777 | D42: bulytchev.isa.ran@gmail.com | E42: =IF($D42="","",COUNTIF('Импорт посещаемость'!I39:AE39,"L*")) -> 17 | F42: =IF($D42="","",COUNTIF('Импорт посещаемость'!I39:AE39,"R*")) -> 6 | G42: =IF($D42="","",MAX(0,COUNTA('Импорт посещаемость'!$I$1:$AE$1)-E42-F42)) -> 0 | H42: =IF($D42="","",E42+F42) -> 23 | I42: =IFERROR(H42/COUNTA('Импорт посещаемость'!$I$1:$AE$1),"") -> 1 | J42: =IFERROR(__xludf.DUMMYFUNCTION("IF($D42="""","""",SPARKLINE(I42,{""charttype"",""bar"";""max"",1;""color1"",""#FFFFFF""}))"),"")
A43: Быков | B43: Денис | C43: 368 | D43: bykovdv@rgau-msha.ru | E43: =IF($D43="","",COUNTIF('Импорт посещаемость'!I40:AE40,"L*")) -> 17 | F43: =IF($D43="","",COUNTIF('Импорт посещаемость'!I40:AE40,"R*")) -> 4 | G43: =IF($D43="","",MAX(0,COUNTA('Импорт посещаемость'!$I$1:$AE$1)-E43-F43)) -> 2 | H43: =IF($D43="","",E43+F43) -> 21 | I43: =IFERROR(H43/COUNTA('Импорт посещаемость'!$I$1:$AE$1),"") -> 0.91304348 | J43: =IFERROR(__xludf.DUMMYFUNCTION("IF($D43="""","""",SPARKLINE(I43,{""charttype"",""bar"";""max"",1;""color1"",""#FFFFFF""}))"),"")
A44: Былков | B44: Вадим | C44: 738 | D44: v.bylkov1@g.nsu.ru | E44: =IF($D44="","",COUNTIF('Импорт посещаемость'!I41:AE41,"L*")) -> 13 | F44: =IF($D44="","",COUNTIF('Импорт посещаемость'!I41:AE41,"R*")) -> 10 | G44: =IF($D44="","",MAX(0,COUNTA('Импорт посещаемость'!$I$1:$AE$1)-E44-F44)) -> 0 | H44: =IF($D44="","",E44+F44) -> 23 | I44: =IFERROR(H44/COUNTA('Импорт посещаемость'!$I$1:$AE$1),"") -> 1 | J44: =IFERROR(__xludf.DUMMYFUNCTION("IF($D44="""","""",SPARKLINE(I44,{""charttype"",""bar"";""max"",1;""color1"",""#FFFFFF""}))"),"")
A45: Вадим | B45: Пак | C45: 786 | D45: vadimpak917@gmail.com | E45: =IF($D45="","",COUNTIF('Импорт посещаемость'!I42:AE42,"L*")) -> 0 | F45: =IF($D45="","",COUNTIF('Импорт посещаемость'!I42:AE42,"R*")) -> 23 | G45: =IF($D45="","",MAX(0,COUNTA('Импорт посещаемость'!$I$1:$AE$1)-E45-F45)) -> 0 | H45: =IF($D45="","",E45+F45) -> 23 | I45: =IFERROR(H45/COUNTA('Импорт посещаемость'!$I$1:$AE$1),"") -> 1 | J45: =IFERROR(__xludf.DUMMYFUNCTION("IF($D45="""","""",SPARKLINE(I45,{""charttype"",""bar"";""max"",1;""color1"",""#FFFFFF""}))"),"")
A46: Вассуф | B46: Язан | C46: 764 | D46: wassouf.yazan.95@gmail.com | E46: =IF($D46="","",COUNTIF('Импорт посещаемость'!I43:AE43,"L*")) -> 1 | F46: =IF($D46="","",COUNTIF('Импорт посещаемость'!I43:AE43,"R*")) -> 22 | G46: =IF($D46="","",MAX(0,COUNTA('Импорт посещаемость'!$I$1:$AE$1)-E46-F46)) -> 0 | H46: =IF($D46="","",E46+F46) -> 23 | I46: =IFERROR(H46/COUNTA('Импорт посещаемость'!$I$1:$AE$1),"") -> 1 | J46: =IFERROR(__xludf.DUMMYFUNCTION("IF($D46="""","""",SPARKLINE(I46,{""charttype"",""bar"";""max"",1;""color1"",""#FFFFFF""}))"),"")
A47: Веденев | B47: Кирилл | C47: 694 | D47: vedenevk@gmail.com | E47: =IF($D47="","",COUNTIF('Импорт посещаемость'!I44:AE44,"L*")) -> 9 | F47: =IF($D47="","",COUNTIF('Импорт посещаемость'!I44:AE44,"R*")) -> 14 | G47: =IF($D47="","",MAX(0,COUNTA('Импорт посещаемость'!$I$1:$AE$1)-E47-F47)) -> 0 | H47: =IF($D47="","",E47+F47) -> 23 | I47: =IFERROR(H47/COUNTA('Импорт посещаемость'!$I$1:$AE$1),"") -> 1 | J47: =IFERROR(__xludf.DUMMYFUNCTION("IF($D47="""","""",SPARKLINE(I47,{""charttype"",""bar"";""max"",1;""color1"",""#FFFFFF""}))"),"")
